Workbook

Sheet Summary
A1: Evercore (EVR) - What Is an Average Year Worth?
A2: All figures link to the model; change Inputs and this page updates. Adjusted (non-GAAP) EPS basis to match consensus.
A4: Mid-cycle EPS today
A5: Mid-cycle Adjusted EPS, base year | B5: =MidCycle!C29 -> 15.085387 | C5: Blend of trend-line and SMD-capacity methods.
A6: Method 1 (trend) only | B6: =MidCycle!C30 -> 15.668743
A7: Method 2 (capacity) only | B7: =MidCycle!C31 -> 14.502031
A8: Mid-cycle operating margin | B8: =MidCycle!C22 -> 0.23753628 | C8: Read off margin-vs-revenue regression at trend revenue.
A9: Mid-cycle EPS, next year | B9: =MidCycle!C34 -> 16.216791
A10: Consensus next-year EPS | B10: =Inputs!$B$7 -> 22.19
A11: Consensus above mid-cycle by | B11: =MidCycle!C36 -> 0.36833481 | C11: Positive = consensus assumes an above-average year continues.
A13: Multiples
A14: P/E on consensus | B14: =MidCycle!C37 -> 12.081118 | C14: Looks cheap...
A15: P/E on mid-cycle EPS | B15: =MidCycle!C38 -> 16.531014 | C15: ...the cyclical-correct read.
A16: P/E on mid-cycle EPS at the 52-week high | B16: =MidCycle!C39 -> 23.9696 | C16: How rich the peak was.
A17: Fair P/E on mid-cycle EPS (model) | B17: =Value!B24 -> 12.146274
A19: Value
A20: Value per share (fading-growth model) | B20: =Value!B21 -> 183.23124
A21: Upside / (downside) vs price | B21: =Value!B23 -> -0.31650536
A22: Perpetual growth in mid-cycle earnings implied by price | B22: =Value!B30 -> 0.078044661 | C22: Compare with ~4-5% fee-pool growth. Higher = price already pays for continued share gains.
A24: Rate effect (how much of the de-rating rates alone explain)
A25: Single-stage fair P/E at current cost of equity | B25: =(1-Inputs!$B$28/Inputs!$B$29)/(Inputs!$B$35-Inputs!$B$28) -> 10.466989 | C25: At terminal growth input.
A26: Same, with risk-free rate lower by the YTD rise | B26: =(1-Inputs!$B$28/Inputs!$B$29)/(Inputs!$B$35-Inputs!$B$36-Inputs!$B$28) -> 12.070566
A27: Multiple compression from rates alone | B27: =B25/B26-1 -> -0.13285024 | C27: Compare with the ~31% peak-to-now price fall.
A28: Peak-to-now price change | B28: =Inputs!$B$5/Inputs!$B$6-1 -> -0.31033418

Sheet Inputs
A1: Evercore (NYSE: EVR) - Mid-Cycle Earnings Inputs
A2: $ in millions except per-share. Blue = hardcoded input; black = formula; green = link; yellow = key judgement call. Change any blue cell and the workbook recalculates.
A4: Market data
A5: Share price ($) | B5: 268.08 | C5: Close 6-Oct-2026, as provided by user (not independently re-checked).
A6: 52-week high ($) | B6: 388.71 | C6: As provided by user.
A7: Consensus 2027E EPS, adjusted ($) | B7: 22.19 | C7: As provided by user. Consensus is on Evercore's Adjusted basis, so this model uses Adjusted EPS throughout.
A8: H1 2026 Adjusted NI attributable to EVR ($mm) | B8: 461.8 | C8: Q2'26 release, 8-K filed 29-Jul-2026.
A9: H1 2026 Adjusted diluted EPS ($) | B9: 10.48 | C9: Q2'26 release, 8-K filed 29-Jul-2026.
A10: Current Adjusted diluted shares (mm) | B10: =B8/B9 -> 44.064885 | C10: Implied: H1'26 Adjusted NI / Adjusted EPS.
A12: Method 1 - revenue trend line
A13: Trend window start year | B13: 2016 | C13: KEY CHOICE. 2009-2015 was a start-up/scale-up phase (revenue +16%/yr) that would bias the trend upward; 2016 start = post-ISI-acquisition, mature firm, spans 2019/2023 troughs and 2021 peak.
A14: Trend window end year | B14: 2025 | C14: Last full fiscal year reported.
A15: Mid-cycle base year | B15: 2026 | C15: Year for which mid-cycle earnings are estimated.
A17: Method 2 - SMD capacity x normal productivity
A18: Investment Banking SMDs now | B18: 188 | C18: 30-Jun-2026, incl. commits, net of known departures. Q2'26 release.
A19: Investment Banking SMDs one year earlier | B19: 159 | C19: 30-Jun-2025, same basis. Q2'26 release.
A20: Productivity of SMDs added in last 12m (vs. tenured) | B20: 0.5 | C20: Assumption: lateral/promoted SMDs typically take 2-3 years to reach full productivity. Also absorbs that the count includes commits not yet on board.
A22: Blend & earnings conversion
A23: Weight on Method 1 (trend) vs Method 2 (capacity) | B23: 0.5 | C23: Assumption. Method 2 reflects today's firm; Method 1 reflects the past path. Equal weight absent a reason to prefer.
A25: Growth of mid-cycle earnings (g = fee-pool growth + share gains)
A26: Industry fee-pool growth, through-cycle (nominal) | B26: 0.045 | C26: Assumption. Over full cycles, advisory fees track deal value, which tracks corporate value / nominal GDP (~4-5%). No buyback term: value is computed on total company distributions, then divided by today's shares - adding buyback-driven EPS growth too would double count.
A27: Share-gain contribution in year 1 | B27: 0.03 | C27: Assumption. Fades linearly to zero by year 10. History: SMDs +8%/yr 2016-25 but revenue/SMD flat in nominal terms, so headcount growth has not translated 1:1 into share.
A28: Terminal growth (after year 10) | B28: 0.04 | C28: Assumption. At or below nominal GDP.
A29: Return on equity on incremental capital | B29: 0.3 | C29: Assumption. Sets reinvestment = g / ROE; payout = 1 - g/ROE. 2025 Adjusted NI / avg equity was ~35% at above-mid-cycle earnings. Growth here is funded mostly through comp (already in margins), so payout is high.
A31: Cost of equity (CAPM)
A32: Risk-free rate (10-year UST) | B32: 0.0528 | C32: As provided by user (10-year at 5.28%, up ~110bp YTD). Not re-checked.
A33: Equity beta | B33: 1.4 | C33: Assumption - verify against a data provider. Advisory boutiques typically screen 1.3-1.6.
A34: Equity risk premium | B34: 0.05 | C34: Assumption.
A35: Cost of equity | B35: =B32+B33*B34 -> 0.1228
A36: Change in 10-year yield this year (for rate-effect check) | B36: 0.011 | C36: As provided by user (~110bp). Used only on Summary to show how much of the de-rating rates alone explain.

Sheet History
A1: Evercore - Reported History, 2009-2025
A2: $ in millions except per-share. GAAP from XBRL; Adjusted (non-GAAP) and SMD counts from earnings releases and 10-Ks. Each blue cell carries its source in a comment. Years are calendar = fiscal.
A4: Year | B4: 2009 | C4: 2010 | D4: 2011 | E4: 2012 | F4: 2013 | G4: 2014 | H4: 2015 | I4: 2016 | J4: 2017 | K4: 2018 | L4: 2019 | M4: 2020 | N4: 2021 | O4: 2022 | P4: 2023 | Q4: 2024 | R4: 2025
A5: Reported - U.S. GAAP
A6: Net revenues | B6: 312.417 | C6: 375.905 | D6: 524.264 | E6: 642.373 | F6: 765.428 | G6: 915.858 | H6: 1223.273 | I6: 1440.052 | J6: 1704.349 | K6: 2064.705 | L6: 2008.698 | M6: 2263.905 | N6: 3289.499 | O6: 2762.048 | P6: 2425.949 | Q6: 2979.593 | R6: 3855.82
A7: Employee compensation & benefits | B7: 207.592 | C7: 247.737 | D7: 357.68 | E7: 430.415 | F7: 485.794 | G7: 549.516 | H7: 788.175 | I7: 900.59 | J7: 962.512 | K7: 1197.173 | L7: 1200.977 | M7: 1372.339 | N7: 1848.757 | O7: 1697.519 | P7: 1656.875 | Q7: 1974.036 | R7: 2500.834
A8: Total operating expenses | B8: 288.969 | C8: 339.045 | D8: 488.452 | E8: 576.838 | F8: 635.253 | G8: 744.911 | H8: 1094.603 | I8: 1178.878 | J8: 1275.538 | K8: 1522.628 | L8: 1570.987 | M8: 1737.472 | N8: 2187.061 | O8: 2066.006 | P8: 2066.814 | Q8: 2452.679 | R8: 3065.878
A9: Pre-tax income | B9: 22.042 | C9: 36.303 | D9: 36.731 | E9: 70.387 | F9: 138.501 | G9: 176.127 | H9: 134.72 | I9: 267.815 | J9: 437.649 | K9: 551.371 | L9: 448.707 | M9: 540.831 | N9: 1116.599 | O9: 704.041 | P9: 365.79 | Q9: 533.145 | R9: 793.814
A10: Net income attributable to Evercore | B10: -1.57 | C10: 8.954 | D10: 6.952 | E10: 28.889 | F10: 53.262 | G10: 86.874 | H10: 42.863 | I10: 107.528 | J10: 125.454 | K10: 377.24 | L10: 297.436 | M10: 350.574 | N10: 740.116 | O10: 476.52 | P10: 255.479 | Q10: 378.279 | R10: 591.922
A11: Diluted EPS ($) | B11: -0.1 | C11: 0.39 | D11: 0.23 | E11: 0.89 | F11: 1.38 | G11: 2.08 | H11: 0.98 | I11: 2.43 | J11: 2.8 | K11: 8.33 | L11: 6.89 | M11: 8.22 | N11: 17.08 | O11: 11.61 | P11: 6.37 | Q11: 9.08 | R11: 14.05
A12: Diluted shares (mm) | B12: 15.545 | C12: 22.968 | D12: 29.397 | E12: 32.548 | F12: 38.481 | G12: 41.843 | H12: 43.699 | I12: 44.193 | J12: 44.826 | K12: 45.279 | L12: 43.194 | M12: 42.623 | N12: 43.321 | O12: 41.037 | P12: 40.099 | Q12: 41.646 | R12: 42.131
A14: Reported - Adjusted (company non-GAAP basis; consensus is on this basis)
A15: Adjusted net revenues | K15: 2083.2 | L15: 2032.6 | M15: 2327.3 | N15: 3316.9 | O15: 2785.6 | P15: 2449.3 | Q15: 3002.6 | R15: 3884
A16: Adjusted operating income | K16: 591 | L16: 498.5 | M16: 639.3 | N16: 1138.4 | O16: 722.7 | P16: 385.4 | Q16: 557.3 | R16: 838.6
A17: Adjusted net income attributable to Evercore | K17: 454 | L17: 373.3 | M17: 459.6 | N17: 843.2 | O17: 528.7 | P17: 276.9 | Q17: 415.8 | R17: 646.3
A18: Adjusted diluted EPS ($) | K18: 9.01 | L18: 7.7 | M18: 9.62 | N18: 17.5 | O18: 12.01 | P18: 6.46 | Q18: 9.42 | R18: 14.56
A19: Investment Banking / Advisory SMDs, year end | E19: 60 | F19: 67 | G19: 68 | H19: 79 | I19: 81 | J19: 87 | K19: 98 | L19: 112 | M19: 107 | N19: 114 | O19: 130 | P19: 136 | Q19: 144 | R19: 171
A21: Derived ratios
A22: GAAP compensation ratio | B22: =B7/B6 -> 0.66447088 | C22: =C7/C6 -> 0.65904151 | D22: =D7/D6 -> 0.68225169 | E22: =E7/E6 -> 0.67003906 | F22: =F7/F6 -> 0.63466975 | G22: =G7/G6 -> 0.60000131 | H22: =H7/H6 -> 0.64431652 | I22: =I7/I6 -> 0.62538714 | ... R22: =R7/R6 -> 0.64858681
A23: GAAP non-comp opex / revenue | B23: =(B8-B7)/B6 -> 0.26047558 | C23: =(C8-C7)/C6 -> 0.2429018 | D23: =(D8-D7)/D6 -> 0.24943921 | E23: =(E8-E7)/E6 -> 0.22794078 | F23: =(F8-F7)/F6 -> 0.195262 | G23: =(G8-G7)/G6 -> 0.21334639 | H23: =(H8-H7)/H6 -> 0.25049846 | I23: =(I8-I7)/I6 -> 0.19324858 | ... R23: =(R8-R7)/R6 -> 0.14654315
A24: Adjusted operating margin | K24: =K16/K15 -> 0.28369816 | L24: =L16/L15 -> 0.24525239 | M24: =M16/M15 -> 0.274696 | N24: =N16/N15 -> 0.34321204 | O24: =O16/O15 -> 0.25944141 | P24: =P16/P15 -> 0.15735108 | Q24: =Q16/Q15 -> 0.18560581 | R24: =R16/R15 -> 0.21591143
A25: Adjusted NI / Adjusted operating income (tax, NCI, other) | K25: =K17/K16 -> 0.76818951 | L25: =L17/L16 -> 0.74884654 | M25: =M17/M16 -> 0.71891131 | N25: =N17/N16 -> 0.74068869 | O25: =O17/O16 -> 0.7315622 | P25: =P17/P16 -> 0.71847431 | Q25: =Q17/Q16 -> 0.74609725 | R25: =R17/R16 -> 0.77068924
A26: Adjusted diluted shares (mm) = Adj NI / Adj EPS | K26: =K17/K18 -> 50.388457 | L26: =L17/L18 -> 48.480519 | M26: =M17/M18 -> 47.775468 | N26: =N17/N18 -> 48.182857 | O26: =O17/O18 -> 44.021649 | P26: =P17/P18 -> 42.863777 | Q26: =Q17/Q18 -> 44.140127 | R26: =R17/R18 -> 44.388736
A27: Net revenue per SMD ($mm) | E27: =E6/E19 -> 10.706217 | F27: =F6/F19 -> 11.424299 | G27: =G6/G19 -> 13.4685 | H27: =H6/H19 -> 15.484468 | I27: =I6/I19 -> 17.77842 | J27: =J6/J19 -> 19.590218 | K27: =K6/K19 -> 21.068418 | L27: =L6/L19 -> 17.934804 | ... R27: =R6/R19 -> 22.548655
A28: LN(net revenue) [helper for trend regression] | B28: =LN(B6) -> 5.7443388 | C28: =LN(C6) -> 5.9293365 | D28: =LN(D6) -> 6.2619954 | E28: =LN(E6) -> 6.4651691 | F28: =LN(F6) -> 6.6404352 | G28: =LN(G6) -> 6.8198613 | H28: =LN(H6) -> 7.1092853 | I28: =LN(I6) -> 7.2724345 | ... R28: =LN(R6) -> 8.257339
A29: Trend net revenue (Method 1 line) | B29: =EXP(MidCycle!$C$8+MidCycle!$C$7*B$4) -> 841.99259 | C29: =EXP(MidCycle!$C$8+MidCycle!$C$7*C$4) -> 921.61972 | D29: =EXP(MidCycle!$C$8+MidCycle!$C$7*D$4) -> 1008.7772 | E29: =EXP(MidCycle!$C$8+MidCycle!$C$7*E$4) -> 1104.1771 | F29: =EXP(MidCycle!$C$8+MidCycle!$C$7*F$4) -> 1208.599 | G29: =EXP(MidCycle!$C$8+MidCycle!$C$7*G$4) -> 1322.896 | H29: =EXP(MidCycle!$C$8+MidCycle!$C$7*H$4) -> 1448.0021 | I29: =EXP(MidCycle!$C$8+MidCycle!$C$7*I$4) -> 1584.9395 | ... R29: =EXP(MidCycle!$C$8+MidCycle!$C$7*R$4) -> 3574.4077
A30: Revenue / trend (>1 = above-trend year) | B30: =B6/B29 -> 0.37104483 | C30: =C6/C29 -> 0.4078743 | D30: =D6/D29 -> 0.51970248 | E30: =E6/E29 -> 0.58176628 | F30: =F6/F29 -> 0.63331842 | G30: =G6/G29 -> 0.69231291 | H30: =H6/H29 -> 0.84480055 | I30: =I6/I29 -> 0.90858484 | ... R30: =R6/R29 -> 1.0787298
A31: Revenue / trend - 1 [regressor for margin] | K31: =K30-1 -> 0.087322416 | L31: =L30-1 -> -0.033567581 | M31: =M30-1 -> -0.0048889411 | N31: =N30-1 -> 0.32099029 | O31: =O30-1 -> 0.013345628 | P31: =P30-1 -> -0.18686144 | Q31: =Q30-1 -> -0.087576749 | R31: =R30-1 -> 0.078729763
A32: Mid-cycle Adjusted EPS at the time (trend rev x mid-cycle margin x conversion / shares) | K32: =K29*MidCycle!$C$22*MidCycle!$C$24/K26 -> 6.6504012 | L32: =L29*MidCycle!$C$22*MidCycle!$C$24/L26 -> 7.5658047 | M32: =M29*MidCycle!$C$22*MidCycle!$C$24/M26 -> 8.4035141 | N32: =N29*MidCycle!$C$22*MidCycle!$C$24/N26 -> 9.1204617 | O32: =O29*MidCycle!$C$22*MidCycle!$C$24/O26 -> 10.926638 | P32: =P29*MidCycle!$C$22*MidCycle!$C$24/P26 -> 12.283041 | Q32: =Q29*MidCycle!$C$22*MidCycle!$C$24/Q26 -> 13.055883 | R32: =R29*MidCycle!$C$22*MidCycle!$C$24/R26 -> 14.210539
A33: Actual Adjusted EPS / mid-cycle EPS (cycle position) | K33: =K18/K32 -> 1.3548055 | L33: =L18/L32 -> 1.0177371 | M33: =M18/M32 -> 1.1447592 | N33: =N18/N32 -> 1.9187625 | O33: =O18/O32 -> 1.0991487 | P33: =P18/P32 -> 0.52592838 | Q33: =Q18/Q32 -> 0.72151381 | R33: =R18/R32 -> 1.0245917
A35: Revenue per SMD uses total net revenue (incl. Equities and Wealth Management, ~10-15% of revenue) over year-end advisory SMDs; before 2015 it is distorted by the ISI acquisition (Oct-2014). SMD counts from 2020 are company-adjusted to include committed hires.

Sheet MidCycle
A1: Evercore - Mid-Cycle Earnings Estimate
A2: Principle: earnings = revenue x margin. Split each into a cyclical part (average it out) and a structural part (trend it forward).
B4: 1. Mid-cycle REVENUE
B6: Method 1 - log-linear trend of GAAP net revenue over the chosen window
B7: Trend slope (log points / year) | C7: =SLOPE(INDEX(History!$B$28:$R$28,MATCH(Inputs!$B$13,History!$B$4:$R$4,0)):INDEX(History!$B$28:$R$28,MATCH(Inputs!$B$14,History!$B$4:$R$4,0)),INDEX(History!$B$4:$R$4,MATCH(Inputs!$B$13,History!$B$4:$R$4,0)):INDEX(History!$B$4:$R$4,MATCH(Inputs!$B$14,History!$B$4:$R$4,0))) -> 0.090361473 | D7: Least-squares fit of LN(revenue) on year.
B8: Trend intercept | C8: =INTERCEPT(INDEX(History!$B$28:$R$28,MATCH(Inputs!$B$13,History!$B$4:$R$4,0)):INDEX(History!$B$28:$R$28,MATCH(Inputs!$B$14,History!$B$4:$R$4,0)),INDEX(History!$B$4:$R$4,MATCH(Inputs!$B$13,History!$B$4:$R$4,0)):INDEX(History!$B$4:$R$4,MATCH(Inputs!$B$14,History!$B$4:$R$4,0))) -> -174.80043
B9: Trend growth rate | C9: =EXP(C7)-1 -> 0.094569869 | D9: Through-cycle revenue growth implied by the window. Very sensitive to the start year (see note).
B10: Mid-cycle revenue, base year - Method 1 | C10: =EXP(C8+C7*Inputs!$B$15) -> 3912.439 | D10: Point on the trend line in the base year.
B12: Method 2 - SMD capacity x normal revenue per SMD
B13: Normal revenue per SMD (window average, $mm) | C13: =AVERAGE(INDEX(History!$B$27:$R$27,MATCH(Inputs!$B$13,History!$B$4:$R$4,0)):INDEX(History!$B$27:$R$27,MATCH(Inputs!$B$14,History!$B$4:$R$4,0))) -> 20.870976 | D13: Average over the same window, so booms and busts net out. Nominal: it has been ~flat since 2016.
B14: SMDs added in last 12 months | C14: =Inputs!$B$18-Inputs!$B$19 -> 29
B15: Productive-equivalent SMDs | C15: =Inputs!$B$18-C14*(1-Inputs!$B$20) -> 173.5 | D15: New SMDs counted at the ramp-productivity input.
B16: Mid-cycle revenue, base year - Method 2 | C16: =C13*C15 -> 3621.1144
B18: Blended mid-cycle revenue | C18: =Inputs!$B$23*C10+(1-Inputs!$B$23)*C16 -> 3766.7767 | D18: If Methods 1 and 2 disagree by >15%, one of the inputs is wrong - check before trusting either.
B19: Method 2 / Method 1 - 1 | C19: =C16/C10-1 -> -0.074461132
B20: 2. Mid-cycle MARGIN and earnings conversion
B21: Operating leverage: margin change per +100% revenue vs trend | C21: =SLOPE(History!K24:R24,History!K31:R31) -> 0.34602866 | D21: Regression of Adjusted operating margin on (revenue/trend - 1), 2018-2025. Sticky comp means margin rises in booms.
B22: Mid-cycle Adjusted operating margin (regression read at trend) | C22: =INTERCEPT(History!K24:R24,History!K31:R31) -> 0.23753628 | D22: Margin the firm earns when revenue is exactly on trend. Better than a simple average if the sample is skewed to booms or busts.
B23: Memo: simple average Adjusted operating margin 2018-2025 | C23: =AVERAGE(History!K24:R24) -> 0.24564604 | D23: Cross-check on C22.
B24: Adjusted NI / operating income (avg 2018-2025) | C24: =AVERAGE(History!K25:R25) -> 0.74293238 | D24: Captures tax rate (incl. recurring Q1 share-vesting tax benefits), NCI and other items. Post-2017 tax reform only.
B26: 3. Mid-cycle EARNINGS
B27: Mid-cycle Adjusted operating income ($mm) | C27: =C18*C22 -> 894.74612
B28: Mid-cycle Adjusted NI ($mm) | C28: =C27*C24 -> 664.73586
B29: Mid-cycle Adjusted EPS, base year ($) | C29: =C28/Inputs!$B$10 -> 15.085387 | D29: On today's diluted share count.
B30: Memo: Method 1 only EPS | C30: =C10*C22*C24/Inputs!$B$10 -> 15.668743
B31: Memo: Method 2 only EPS | C31: =C16*C22*C24/Inputs!$B$10 -> 14.502031
B33: 4. What the market and consensus imply
B34: Mid-cycle EPS, base year + 1 ($) | C34: =C29*(1+Inputs!$B$26+Inputs!$B$27) -> 16.216791 | D34: One year of mid-cycle growth (Value sheet, year 1).
B35: Consensus next-year EPS ($) | C35: =Inputs!$B$7 -> 22.19
B36: Consensus vs mid-cycle (same year) | C36: =C35/C34-1 -> 0.36833481 | D36: How far above an average year consensus sits. Large positive = consensus is a peak-year number.
B37: P/E on consensus | C37: =Inputs!$B$5/C35 -> 12.081118 | D37: The headline '12x'.
B38: P/E on mid-cycle EPS (same year) | C38: =Inputs!$B$5/C34 -> 16.531014 | D38: The multiple that actually matters for a cyclical.
B39: P/E at 52-week high on mid-cycle EPS | C39: =Inputs!$B$6/C34 -> 23.9696

Sheet Value
A1: Evercore - Growth of Mid-Cycle Earnings and Value
A2: Value = present value of the distributable earnings of an AVERAGE year, growing at fee-pool growth plus fading share gains. Cash flows at year end; valuation as of the base year.
A4: Year index (t) | B4: 0 | C4: 1 | D4: 2 | E4: 3 | F4: 4 | G4: 5 | H4: 6 | I4: 7 | J4: 8 | K4: 9 | L4: 10
A5: Calendar year | B5: =Inputs!$B$15+0 -> 2026 | C5: =Inputs!$B$15+1 -> 2027 | D5: =Inputs!$B$15+2 -> 2028 | E5: =Inputs!$B$15+3 -> 2029 | F5: =Inputs!$B$15+4 -> 2030 | G5: =Inputs!$B$15+5 -> 2031 | H5: =Inputs!$B$15+6 -> 2032 | I5: =Inputs!$B$15+7 -> 2033 | J5: =Inputs!$B$15+8 -> 2034 | K5: =Inputs!$B$15+9 -> 2035 | L5: =Inputs!$B$15+10 -> 2036
A6: Fee-pool growth | C6: =Inputs!$B$26 -> 0.045 | D6: =Inputs!$B$26 -> 0.045 | E6: =Inputs!$B$26 -> 0.045 | F6: =Inputs!$B$26 -> 0.045 | G6: =Inputs!$B$26 -> 0.045 | H6: =Inputs!$B$26 -> 0.045 | I6: =Inputs!$B$26 -> 0.045 | J6: =Inputs!$B$26 -> 0.045 | ... L6: =Inputs!$B$26 -> 0.045
A7: Share-gain contribution (fades to 0) | C7: =Inputs!$B$27*MAX(0,(10-C4)/(10-1)) -> 0.03 | D7: =Inputs!$B$27*MAX(0,(10-D4)/(10-1)) -> 0.026666667 | E7: =Inputs!$B$27*MAX(0,(10-E4)/(10-1)) -> 0.023333333 | F7: =Inputs!$B$27*MAX(0,(10-F4)/(10-1)) -> 0.02 | G7: =Inputs!$B$27*MAX(0,(10-G4)/(10-1)) -> 0.016666667 | H7: =Inputs!$B$27*MAX(0,(10-H4)/(10-1)) -> 0.013333333 | I7: =Inputs!$B$27*MAX(0,(10-I4)/(10-1)) -> 0.01 | J7: =Inputs!$B$27*MAX(0,(10-J4)/(10-1)) -> 0.0066666667 | ... L7: =Inputs!$B$27*MAX(0,(10-L4)/(10-1)) -> 0
A8: Mid-cycle NI growth (g) | C8: =C6+C7 -> 0.075 | D8: =D6+D7 -> 0.071666667 | E8: =E6+E7 -> 0.068333333 | F8: =F6+F7 -> 0.065 | G8: =G6+G7 -> 0.061666667 | H8: =H6+H7 -> 0.058333333 | I8: =I6+I7 -> 0.055 | J8: =J6+J7 -> 0.051666667 | ... L8: =L6+L7 -> 0.045
A9: Mid-cycle Adjusted NI ($mm) | B9: =MidCycle!C28 -> 664.73586 | C9: =B9*(1+C8) -> 714.59105 | D9: =C9*(1+D8) -> 765.80341 | E9: =D9*(1+E8) -> 818.13331 | F9: =E9*(1+F8) -> 871.31198 | G9: =F9*(1+G8) -> 925.04288 | H9: =G9*(1+H8) -> 979.00372 | I9: =H9*(1+I8) -> 1032.8489 | J9: =I9*(1+J8) -> 1086.2128 | ... L9: =K9*(1+L8) -> 1189.9552
A10: Payout ratio = 1 - g / ROE | C10: =1-C8/Inputs!$B$29 -> 0.75 | D10: =1-D8/Inputs!$B$29 -> 0.76111111 | E10: =1-E8/Inputs!$B$29 -> 0.77222222 | F10: =1-F8/Inputs!$B$29 -> 0.78333333 | G10: =1-G8/Inputs!$B$29 -> 0.79444444 | H10: =1-H8/Inputs!$B$29 -> 0.80555556 | I10: =1-I8/Inputs!$B$29 -> 0.81666667 | J10: =1-J8/Inputs!$B$29 -> 0.82777778 | ... L10: =1-L8/Inputs!$B$29 -> 0.85
A11: Distributable earnings ($mm) | C11: =C9*C10 -> 535.94329 | D11: =D9*D10 -> 582.86148 | E11: =E9*E10 -> 631.78072 | F11: =F9*F10 -> 682.52771 | G11: =G9*G10 -> 734.89518 | H11: =H9*H10 -> 788.64188 | I11: =I9*I10 -> 843.49328 | J11: =J9*J10 -> 899.1428 | ... L11: =L9*L10 -> 1011.4619
A12: Discount factor | C12: =1/(1+Inputs!$B$35)^C4 -> 0.89063057 | D12: =1/(1+Inputs!$B$35)^D4 -> 0.79322281 | E12: =1/(1+Inputs!$B$35)^E4 -> 0.70646848 | F12: =1/(1+Inputs!$B$35)^F4 -> 0.62920242 | G12: =1/(1+Inputs!$B$35)^G4 -> 0.56038691 | H12: =1/(1+Inputs!$B$35)^H4 -> 0.49909771 | I12: =1/(1+Inputs!$B$35)^I4 -> 0.44451168 | J12: =1/(1+Inputs!$B$35)^J4 -> 0.39589569 | ... L12: =1/(1+Inputs!$B$35)^L4 -> 0.31403349
A13: PV of distributions ($mm) | C13: =C11*C12 -> 477.32748 | D13: =D11*D12 -> 462.33902 | E13: =E11*E12 -> 446.33317 | F13: =F11*F12 -> 429.44809 | G13: =G11*G12 -> 411.82564 | H13: =H11*H12 -> 393.60936 | I13: =I11*I12 -> 374.94261 | J13: =J11*J12 -> 355.96676 | ... L13: =L11*L12 -> 317.6329
A14: Memo: mid-cycle EPS on today's shares ($) | B14: =B9/Inputs!$B$10 -> 15.085387 | C14: =C9/Inputs!$B$10 -> 16.216791 | D14: =D9/Inputs!$B$10 -> 17.378995 | E14: =E9/Inputs!$B$10 -> 18.566559 | F14: =F9/Inputs!$B$10 -> 19.773386 | G14: =G9/Inputs!$B$10 -> 20.992744 | H14: =H9/Inputs!$B$10 -> 22.217321 | I14: =I9/Inputs!$B$10 -> 23.439274 | ... L14: =L9/Inputs!$B$10 -> 27.004612
A16: Valuation
A17: Sum of PV, years 1-10 ($mm) | B17: =SUM(C13:L13) -> 4006.2444
A18: Terminal value at year 10 ($mm) | B18: =L9*(1+Inputs!$B$28)*(1-Inputs!$B$28/Inputs!$B$29)/(Inputs!$B$35-Inputs!$B$28) -> 12953.457
A19: PV of terminal value ($mm) | B19: =B18*L12 -> 4067.8193
A20: Equity value ($mm) | B20: =B17+B19 -> 8074.0637
A21: Value per share ($) | B21: =B20/Inputs!$B$10 -> 183.23124
A22: Current price ($) | B22: =Inputs!$B$5 -> 268.08
A23: Upside / (downside) | B23: =B21/B22-1 -> -0.31650536
A24: Implied fair P/E on base-year mid-cycle EPS | B24: =B21/MidCycle!C29 -> 12.146274
A25: Terminal value share of equity value | B25: =B19/B20 -> 0.50381313
A26: No net-cash adjustment: Evercore's cash largely funds accrued year-end bonuses, so it is treated as operating. Excess cash would add to value.
A28: Reverse test: what perpetual growth in mid-cycle earnings does today's price imply?
A29: Next-year mid-cycle EPS (E1) | B29: =MidCycle!C34 -> 16.216791
A30: Implied perpetual g [solves P = E1 (1 - g/ROE) / (r - g)] | B30: =(Inputs!$B$5*Inputs!$B$35-B29)/(Inputs!$B$5-B29/Inputs!$B$29) -> 0.078044661
A31: Compare with fee-pool growth input | B31: =Inputs!$B$26 -> 0.045
A33: Sensitivity: single-stage value per share = E1 x (1 - g/ROE) / (r - g)
A34: Cost of equity (down) / perpetual g (across) | B34: 0.03 | C34: 0.04 | D34: 0.05 | E34: 0.06 | F34: 0.07
A35: 0.09 | B35: =IF($A35>B$34,$B$29*(1-B$34/Inputs!$B$29)/($A35-B$34),NA()) -> 243.25187 | C35: =IF($A35>C$34,$B$29*(1-C$34/Inputs!$B$29)/($A35-C$34),NA()) -> 281.09105 | D35: =IF($A35>D$34,$B$29*(1-D$34/Inputs!$B$29)/($A35-D$34),NA()) -> 337.84982 | E35: =IF($A35>E$34,$B$29*(1-E$34/Inputs!$B$29)/($A35-E$34),NA()) -> 432.44777 | F35: =IF($A35>F$34,$B$29*(1-F$34/Inputs!$B$29)/($A35-F$34),NA()) -> 621.64367
A36: 0.1 | B36: =IF($A36>B$34,$B$29*(1-B$34/Inputs!$B$29)/($A36-B$34),NA()) -> 208.5016 | C36: =IF($A36>C$34,$B$29*(1-C$34/Inputs!$B$29)/($A36-C$34),NA()) -> 234.24254 | D36: =IF($A36>D$34,$B$29*(1-D$34/Inputs!$B$29)/($A36-D$34),NA()) -> 270.27986 | E36: =IF($A36>E$34,$B$29*(1-E$34/Inputs!$B$29)/($A36-E$34),NA()) -> 324.33583 | F36: =IF($A36>F$34,$B$29*(1-F$34/Inputs!$B$29)/($A36-F$34),NA()) -> 414.42911
A37: 0.11 | B37: =IF($A37>B$34,$B$29*(1-B$34/Inputs!$B$29)/($A37-B$34),NA()) -> 182.4389 | C37: =IF($A37>C$34,$B$29*(1-C$34/Inputs!$B$29)/($A37-C$34),NA()) -> 200.77932 | D37: =IF($A37>D$34,$B$29*(1-D$34/Inputs!$B$29)/($A37-D$34),NA()) -> 225.23321 | E37: =IF($A37>E$34,$B$29*(1-E$34/Inputs!$B$29)/($A37-E$34),NA()) -> 259.46866 | F37: =IF($A37>F$34,$B$29*(1-F$34/Inputs!$B$29)/($A37-F$34),NA()) -> 310.82183
A38: 0.12 | B38: =IF($A38>B$34,$B$29*(1-B$34/Inputs!$B$29)/($A38-B$34),NA()) -> 162.16791 | C38: =IF($A38>C$34,$B$29*(1-C$34/Inputs!$B$29)/($A38-C$34),NA()) -> 175.68191 | D38: =IF($A38>D$34,$B$29*(1-D$34/Inputs!$B$29)/($A38-D$34),NA()) -> 193.05704 | E38: =IF($A38>E$34,$B$29*(1-E$34/Inputs!$B$29)/($A38-E$34),NA()) -> 216.22388 | F38: =IF($A38>F$34,$B$29*(1-F$34/Inputs!$B$29)/($A38-F$34),NA()) -> 248.65747
A39: 0.13 | B39: =IF($A39>B$34,$B$29*(1-B$34/Inputs!$B$29)/($A39-B$34),NA()) -> 145.95112 | C39: =IF($A39>C$34,$B$29*(1-C$34/Inputs!$B$29)/($A39-C$34),NA()) -> 156.16169 | D39: =IF($A39>D$34,$B$29*(1-D$34/Inputs!$B$29)/($A39-D$34),NA()) -> 168.92491 | E39: =IF($A39>E$34,$B$29*(1-E$34/Inputs!$B$29)/($A39-E$34),NA()) -> 185.33476 | F39: =IF($A39>F$34,$B$29*(1-F$34/Inputs!$B$29)/($A39-F$34),NA()) -> 207.21456
A41: Price ($) for comparison | B41: =Inputs!$B$5 -> 268.08

Sheet Sources
A1: SOURCES
A2: GAAP history: SEC EDGAR XBRL companyfacts API, CIK 0001360901 (https://data.sec.gov/api/xbrl/companyfacts/CIK0001360901.json), 10-K full-year durations; latest filed value used where restated.
A3: Adjusted results: Evercore Q4 earnings releases (Exhibit 99.1 to 8-K, Item 2.02) filed 29-Jan-2020, 3-Feb-2021, 2-Feb-2022, 1-Feb-2023, 31-Jan-2024, 5-Feb-2025, 4-Feb-2026; H1 2026 from the Q2'26 release filed 29-Jul-2026.
A4: SMD counts: 10-K Item 1 (2012-2019) and earnings-release headcount footnotes (2020-2026). Definitions drift slightly ('Advisory' -> 'Investment Banking'; company-adjusted for commits from 2020).
A5: User-provided (not independently re-checked): share price 268.08 (6-Oct-2026), 52-week high 388.71, 2027E consensus EPS 22.19, 10-year UST 5.28% and ~110bp YTD rise.
A7: KNOWN LIMITATIONS
A8: 1. Trend line is sensitive to the window: 2009-2025 gives ~16%/yr growth (start-up phase), 2016-2025 ~9.5%, 2018-2025 ~8%. Default is 2016.
A9: 2. Margin regression has only 8 observations (2018-2025), roughly one cycle. Treat the mid-cycle margin as +/- 2pp.
A10: 3. Adjusted NI conversion includes Q1 share-vesting tax benefits, which scale with the share price (Q1'26: $94mm Adjusted). Lower prices shrink this benefit - a small reflexive effect not modelled.
A11: 4. Revenue per SMD uses total firm revenue; Equities and Wealth Management are not driven by advisory SMDs.
A12: 5. Pre-2018 adjusted figures are excluded (client-expense gross-up and the 2017 tax reform break comparability).
