Workbook
Name BaseVal: Assumptions!$P$9
Name beta: Assumptions!$D$22
Name Capacity: Assumptions!$D$36
Name CapDebt: Capitalization!$D$8
Name CapexIntensity: Assumptions!$D$38
Name cash: Assumptions!$D$24
Name CashYield: Assumptions!$D$35
Name ClassA: Assumptions!$D$13
Name ClassB: Assumptions!$D$14
Name DCFPrice: DCF!$E$37
Name Debt: Capitalization!$D$8
Name DepOpex: Assumptions!$D$34
Name DilutedShares: Assumptions!$D$17
Name DTA: Assumptions!$D$27
Name Enterprise: Tearsheet!$N$21
Name Exchange: Assumptions!$D$9
Name ExitMult: Assumptions!$D$41
Name ExitOverride: Assumptions!$D$40
Name FYE: Assumptions!$D$11
Name high: Assumptions!$D$19
Name HighVal: Assumptions!$P$10
Name Kd: Capitalization!$H$8
Name low: Assumptions!$D$20
Name LowVal: Assumptions!$P$11
Name marketcap: Assumptions!$D$18
Name MidYear: Assumptions!$D$43
Name mininterest: Assumptions!$D$28
Name Name: Assumptions!$D$7
Name NCIpct: Assumptions!$D$32
Name NetClaims: DCF!$E$40
Name prefstock: Assumptions!$D$29
Name rcash: Assumptions!$D$25
Name Recommendation: Assumptions!$D$4
Name RSUs: Assumptions!$D$15
Name Scenario: Assumptions!$C$45
Name shareprice: Assumptions!$D$12
Name shares: Assumptions!$D$16
Name TargetPrice: Assumptions!$L$13
Name TaxRate: Assumptions!$D$33
Name TerminalValue: DCF!$R$17
Name TGR: Assumptions!$D$39
Name Ticker: Assumptions!$D$8
Name TLAmort: Capitalization!$D$13
Name totaldebt: Assumptions!$D$23
Name TRA: Assumptions!$D$26
Name TV: DCF!$R$17
Name TVweight: Assumptions!$D$42
Name Util: Assumptions!$D$37
Name valdate: Assumptions!$D$10
Name WACC: WACC!$D$23
Name yield: Assumptions!$D$21

Sheet Tearsheet
C2: =Name&" ("&Exchange&": "&Ticker&")" -> Forgent Power Solutions, Inc. (NYSE: FPS) | H2: ="As of: "&TEXT(valdate,"mm/dd/yyyy") -> As of: 09/25/2026
C4: Tear Sheet | H4: Summary Statistics
C5: Business description: | H5: Stock rating | N5: =Recommendation -> Buy
C6: Forgent Power Solutions designs and manufactures electrical distribution equipment — switchgear, switchboards, dry-type and liquid-filled transformers, eHouses, PDUs and integrated power skids — for data center (59% of FY26 revenue), grid (21%), industrial (10%) and other customers, substantially all in North America. Formed through Neos Partners' 2023–24 roll-up of MGM Transformer, PwrQ, States Manufacturing and VanTran; IPO'd on the NYSE in February 2026 at $27.00. FY26 (June YE) revenue $1.42bn (+89%), adj. EBITDA $323m; backlog $3.0bn at 6/30/26. ~2.3m sq ft of leased plants in MN, TX, CA, MD and Mexico. [10-K FY26; Q4 FY26 release] | H6: Price target (base DCF) | N6: =TargetPrice -> 36.341509
H7: Valuation range (bear / bull, DCF + comps avg) | N7: =IF(OR(LowVal=0,HighVal=0),"run scenarios","$"&TEXT(LowVal,"0.00")&" – $"&TEXT(HighVal,"0.00")) -> $29.32 – $43.48
H8: Current price | N8: =shareprice -> 38.97
H9: Since-IPO low / high | N9: ="$"&TEXT(low,"0.00")&" / $"&TEXT(high,"0.00") -> $25.95 / $66.00
H10: % upside to target | N10: =N6/N8-1 -> -0.067449101
H12: Beta (relevered peer median) | N12: =beta -> 1.1673281
H13: Dividend yield | N13: =yield -> 0
H14: Diluted shares, fully exchanged (MM) | N14: =DilutedShares -> 305.12388
H16: Market capitalization ($MM) | N16: =marketcap -> 11863.594
C17: Investment thesis (analytical — analyst to confirm): | H17: + Debt ($MM) | N17: =totaldebt -> 598.5
C18: 1) Backlog-backed growth: $3.0bn backlog (~2.1x FY26 revenue) and a 3.3x Q4 book-to-bill underpin FY27 guidance of $2.4–2.6bn revenue (+76% at midpoint); FY26 beat the top of guidance after two raises. 2) Operating leverage on a largely built footprint: the 2025–26 capacity program is substantially complete (~$5bn revenue capacity, ~$5.8bn after the $35m PTS Tijuana expansion), so FY27 capex is guided to only ~$87m. 3) Margin ramp: adj. EBITDA margin rose from 20.4% (Q2) to 24.4% (Q4 FY26) as new plants reached rate; sponsor fees ended at IPO. 4) Technical overhang: shares fell from $55.86 (6/30) to $38.97 amid Neos secondary sales and the 8/4 lock-up expiry; Neos' stake is now 37.2% (Class B down from 90.2m to 29.9m units). The debate: the base-case DCF (below) vs. what the market already prices in on margin durability. | H18: + TRA, net of DTA & restricted cash ($MM) | N18: =TRA-DTA-rcash -> 33.718
H19: + Preferred & minority interest ($MM) | N19: =prefstock+mininterest -> 0
H20: − Cash & equivalents ($MM) | N20: =cash -> 97.477
H21: Enterprise value ($MM) | N21: =N16+N17+N18+N19-N20 -> 12398.335
H23: ="Financial projections — fiscal years ending "&TEXT(FYE,"mmmm d") -> Financial projections — fiscal years ending June 30
H24: All numbers in $MM except per-share data
I25: =Inc_Stmt!E5 -> FY26A | J25: =Inc_Stmt!F5 -> FY27E | K25: =Inc_Stmt!G5 -> FY28E | L25: =Inc_Stmt!H5 -> FY29E | M25: =Inc_Stmt!I5 -> FY30E | N25: =Inc_Stmt!J5 -> FY31E
H26: Revenue | I26: =Inc_Stmt!E12 -> 1420.059 | J26: =Inc_Stmt!F12 -> 2501.26 | K26: =Inc_Stmt!G12 -> 3266.9585 | L26: =Inc_Stmt!H12 -> 3909.8604 | M26: =Inc_Stmt!I12 -> 4448.1804 | N26: =Inc_Stmt!J12 -> 4886.6753
H27: YoY growth | I27: =Inc_Stmt!E67 -> 0.8853978 | J27: =Inc_Stmt!F67 -> 0.76137752 | K27: =Inc_Stmt!G67 -> 0.30612511 | L27: =Inc_Stmt!H67 -> 0.19678913 | M27: =Inc_Stmt!I67 -> 0.13768265 | N27: =Inc_Stmt!J67 -> 0.098578498
H28: Adj. EBITDA | I28: =Inc_Stmt!E43 -> 322.9 | J28: =Inc_Stmt!F43 -> 606.58909 | K28: =Inc_Stmt!G43 -> 843.80101 | L28: =Inc_Stmt!H43 -> 1031.2549 | M28: =Inc_Stmt!I43 -> 1170.4164 | N28: =Inc_Stmt!J43 -> 1275.3755
H29: YoY growth | I29: =Inc_Stmt!E69 -> 0.90839243 | J29: =Inc_Stmt!F69 -> 0.87856639 | K29: =Inc_Stmt!G69 -> 0.39105867 | L29: =Inc_Stmt!H69 -> 0.22215413 | M29: =Inc_Stmt!I69 -> 0.13494381 | N29: =Inc_Stmt!J69 -> 0.08967672
H30: EBITDA (GAAP) | I30: =Inc_Stmt!E40 -> 249.389 | J30: =Inc_Stmt!F40 -> 586.57901 | K30: =Inc_Stmt!G40 -> 817.66534 | L30: =Inc_Stmt!H40 -> 999.976 | M30: =Inc_Stmt!I40 -> 1134.8309 | N30: =Inc_Stmt!J40 -> 1236.2821
H31: Net income (incl. NCI) | I31: =Inc_Stmt!E30 -> 106.035 | J31: =Inc_Stmt!F30 -> 371.05367 | K31: =Inc_Stmt!G30 -> 542.58864 | L31: =Inc_Stmt!H30 -> 689.45005 | M31: =Inc_Stmt!I30 -> 802.78264 | N31: =Inc_Stmt!J30 -> 891.1284
H32: Diluted EPS (fully exchanged) | I32: =Inc_Stmt!E36 -> 0.34799803 | J32: =Inc_Stmt!F36 -> 1.2160755 | K32: =Inc_Stmt!G36 -> 1.7782569 | L32: =Inc_Stmt!H36 -> 2.2595742 | M32: =Inc_Stmt!I36 -> 2.6310056 | N32: =Inc_Stmt!J36 -> 2.9205462
H33: Unlevered FCF | I33: =Cash_Flow!E47 -> -10.40225 | J33: =Cash_Flow!F47 -> 230.76174 | K33: =Cash_Flow!G47 -> 495.51009 | L33: =Cash_Flow!H47 -> 635.749 | M33: =Cash_Flow!I47 -> 737.36404 | N33: =Cash_Flow!J47 -> 814.47244
C34: Catalysts: | H34: Capex | I34: =-Inc_Stmt!E44 -> 115.905 | J34: =-Inc_Stmt!F44 -> 87.0126 | K34: =-Inc_Stmt!G44 -> 39.203502 | L34: =-Inc_Stmt!H44 -> 50.828185 | M34: =-Inc_Stmt!I44 -> 62.274525 | N34: =-Inc_Stmt!J44 -> 73.30013
C35: • Q1 FY27 print (mgmt guides sequential revenue & EBITDA growth every quarter; Q1 burdened by hiring). • PTS Tijuana expansion online Q4 FY27 (+~$800m capacity). • Continued conversion of $3.0bn backlog; grid/utility share gains (utility sales ~$110m FY25 from <$50m). • Diminishing sponsor overhang as Neos sells down; sponsor consent rights lapse below 35%.
H36: EV / revenue | I36: =Enterprise/Inc_Stmt!E12 -> 8.7308589 | J36: =Enterprise/Inc_Stmt!F12 -> 4.9568357 | K36: =Enterprise/Inc_Stmt!G12 -> 3.7950696 | L36: =Enterprise/Inc_Stmt!H12 -> 3.1710428 | M36: =Enterprise/Inc_Stmt!I12 -> 2.7872824 | N36: =Enterprise/Inc_Stmt!J12 -> 2.5371718
H37: EV / adj. EBITDA | I37: =Enterprise/Inc_Stmt!E43 -> 38.396825 | J37: =Enterprise/Inc_Stmt!F43 -> 20.439429 | K37: =Enterprise/Inc_Stmt!G43 -> 14.693434 | L37: =Enterprise/Inc_Stmt!H43 -> 12.022571 | M37: =Enterprise/Inc_Stmt!I43 -> 10.593098 | N37: =Enterprise/Inc_Stmt!J43 -> 9.7213215
H38: P / E | I38: =shareprice/Inc_Stmt!E36 -> 111.98339 | J38: =shareprice/Inc_Stmt!F36 -> 32.045708 | K38: =shareprice/Inc_Stmt!G36 -> 21.914719 | L38: =shareprice/Inc_Stmt!H36 -> 17.246612 | M38: =shareprice/Inc_Stmt!I36 -> 14.811827 | N38: =shareprice/Inc_Stmt!J36 -> 13.343394
H39: Debt / adj. EBITDA | I39: =totaldebt/Inc_Stmt!E43 -> 1.853515 | J39: =totaldebt/Inc_Stmt!F43 -> 0.98666463 | K39: =totaldebt/Inc_Stmt!G43 -> 0.70929045 | L39: =totaldebt/Inc_Stmt!H43 -> 0.58036089 | M39: =totaldebt/Inc_Stmt!I43 -> 0.51135649 | N39: =totaldebt/Inc_Stmt!J43 -> 0.46927358
H40: Adj. EBITDA / interest | I40: =Inc_Stmt!E43/-Inc_Stmt!E22 -> 5.6523185 | J40: =Inc_Stmt!F43/-Inc_Stmt!F22 -> 15.860964 | K40: =Inc_Stmt!G43/-Inc_Stmt!G22 -> 22.28696 | L40: =Inc_Stmt!H43/-Inc_Stmt!H22 -> 27.51675 | M40: =Inc_Stmt!I43/-Inc_Stmt!I22 -> 31.552756 | N40: =Inc_Stmt!J43/-Inc_Stmt!J22 -> 34.741388
H42: Comparables analysis
I43: Mkt cap | J43: EV | K43: EV/LTM EBITDA | L43: LTM P/E | M43: NTM P/E
H44: =Ticker&" (at market)" -> FPS (at market) | I44: ='Comps Analysis'!E14 -> 11863.594 | J44: ='Comps Analysis'!G14 -> 12398.335 | K44: ='Comps Analysis'!D26 -> 38.396825 | L44: ='Comps Analysis'!E26 -> 111.98339 | M44: ='Comps Analysis'!F26 -> 29.08209
H45: Peer median | I45: =MEDIAN('Comps Analysis'!E7:E12) -> 62060.835 | J45: =MEDIAN('Comps Analysis'!G7:G12) -> 63781.101 | K45: ='Comps Analysis'!D30 -> 27.752828 | L45: ='Comps Analysis'!E30 -> 40.556455 | M45: ='Comps Analysis'!F30 -> 27.768465
C46: Risks: | H46: Peer max | I46: =MAX('Comps Analysis'!E7:E12) -> 255045.6 | J46: =MAX('Comps Analysis'!G7:G12) -> 247203.6 | K46: ='Comps Analysis'!D28 -> 62.901679 | L46: ='Comps Analysis'!E28 -> 57.303167 | M46: ='Comps Analysis'!F28 -> 43.146204
C47: 1) Concentration: data center = 59% of revenue; one customer ~11% of FY26 revenue (unnamed). 2) Ramp execution: under-absorption cost 1.8–2.0% of revenue in Q2–Q3 FY26; gross margin fell 36.9% → 35.0%. 3) Inputs & trade: unhedged electrical steel, copper, aluminum; ~1/3 of footprint in Mexico (tariff exposure). 4) Capital structure: $598.5m floating-rate term loan (±$6m interest per 100bp); $339m TRA liability. 5) Cycle: AI/data-center capex slowdown or incumbents (Eaton, Schneider, Vertiv) adding capacity compresses pricing — the base case already fades EBITDA margin from ~25% to ~22%. | H47: Peer min | I47: =MIN('Comps Analysis'!E7:E12) -> 6904.5779 | J47: =MIN('Comps Analysis'!G7:G12) -> 6273.5379 | K47: ='Comps Analysis'!D33 -> 19.621667 | L47: ='Comps Analysis'!E33 -> 27.407842 | M47: ='Comps Analysis'!F33 -> 20.917629
H49: Peers: ETN, VRT, HUBB, NVT, GEV, POWL. Stock-price chart deferred (needs daily price history).

Sheet Assumptions
A1: ="Assumptions for "&Name -> Assumptions for Forgent Power Solutions, Inc.
A2: (Dollars in Millions unless stated)
B3: Valuation prepared by | D3: KJ | F3: HY Fund
B4: Recommendation | D4: Buy
B6: Company Information | D6: Input | F6: Name | J6: Share Price Outputs
B7: Company name | D7: Forgent Power Solutions, Inc. | F7: "Name" | H7: 10-K cover (FY26), filed 9/15/2026
B8: Ticker | D8: FPS | F8: "Ticker" | H8: 10-K cover | J8: Scenario | L8: DCF | N8: Comps | P8: Average
B9: Exchange | D9: NYSE | F9: "Exchange" | H9: 10-K cover | J9: =B46 -> Base | L9: 36.3415 | N9: ='Comps Analysis'!G43 -> 37.209743 | P9: =AVERAGE(L9,N9) -> 36.775621
B10: Valuation date | D10: 46290 | F10: "valdate" | H10: Last close used for price | J10: =B47 -> Bull | L10: 47.7447 | N10: ='Comps Analysis'!G42 -> 39.206242 | P10: =AVERAGE(L10,N10) -> 43.475471
B11: Last fiscal year end | D11: 46203 | F11: "FYE" | H11: 10-K: FY ends June 30 | J11: =B48 -> Bear | L11: 22.8707 | N11: ='Comps Analysis'!G44 -> 35.776725 | P11: =AVERAGE(L11,N11) -> 29.323712
B12: Last share price | D12: 38.97 | F12: "shareprice" | H12: Close 9/25/2026 — StockAnalysis / MarketBeat / MarketScreener | J12: Live DCF (current scenario) | L12: =DCF!E37 -> 36.341509
B13: Class A shares (MM) | D13: 274.52709 | F13: "ClassA" | H13: 10-K cover, as of 9/8/2026 | J13: Target Price (base DCF) | L13: =IF(Scenario=1,DCF!E37,L9) -> 36.341509
B14: Class B shares = exchangeable Opco units (MM) | D14: 29.901795 | F14: "ClassB" | H14: 10-K cover, as of 9/8/2026 (held by Neos vehicles) | J14: **DCF column L9:L11 is pasted from running each scenario (same convention as the Oracle model). Re-run Scenario 1/2/3 and re-paste if any driver changes.
B15: Unvested RSUs (MM) | D15: 0.694991 | F15: "RSUs" | H15: 10-K Note 20, 6/30/2026 (no options outstanding)
B16: Basic shares, fully exchanged (MM) | D16: =D13+D14 -> 304.42889 | F16: "shares" | H16: Up-C: Class B exchangeable 1:1 — value on fully-exchanged basis
B17: Diluted shares, fully exchanged (MM) | D17: =D16+D15 -> 305.12388 | F17: "DilutedShares" | H17: Basic + all RSUs (no strike -> no treasury method)
B18: Market cap ($MM) | D18: =shareprice*shares -> 11863.594 | F18: "marketcap"
B19: Since-IPO high | D19: 66 | F19: "high" | H19: StockAnalysis / MarketBeat (IPO 2/5/2026)
B20: Since-IPO low | D20: 25.95 | F20: "low" | H20: StockAnalysis / MarketBeat
B21: Dividend yield | D21: 0 | F21: "yield" | H21: 10-K Item 5: no dividend intended
B22: Beta (relevered peer median) | D22: =WACC!D36 -> 1.1673281 | F22: "beta" | H22: No usable FPS beta (<8 months trading) — see WACC tab
B23: Total debt ($MM, principal) | D23: =CapDebt -> 598.5 | F23: "totaldebt" | H23: Capitalization tab
B24: Cash & equivalents ($MM) | D24: 97.477 | F24: "cash" | H24: 10-K balance sheet 6/30/2026
B25: Restricted cash for TRA ($MM) | D25: 24.236 | F25: "rcash" | H25: 10-K: in prepaid & other current assets
B26: Tax receivable agreement liability ($MM) | D26: 338.925 | F26: "TRA" | H26: 10-K balance sheet 6/30/2026 (total liabilities less other lines)
B27: Deferred tax asset backing TRA ($MM) | D27: 280.971 | F27: "DTA" | H27: 10-K balance sheet 6/30/2026 (DTA, net)
B28: Minority interest subtracted in bridge ($MM) | D28: 0 | F28: "mininterest" | H28: Book NCI $107.1m NOT subtracted: Class B holders are already in the share count
B29: Preferred stock ($MM) | D29: 0 | F29: "prefstock" | H29: None outstanding
B31: Model Inputs
B32: NCI economic interest (Class B / fully exchanged) | D32: =ClassB/shares -> 0.098222593 | F32: "NCIpct" | H32: Used only to split GAAP net income
B33: Tax rate (normalized, fully exchanged) | D33: 0.25 | F33: "TaxRate" | H33: 21% federal + state; FY26 ETR 16.8% is depressed by untaxed NCI share
B34: Share of depreciation booked in opex | D34: 0.226 | F34: "DepOpex" | H34: 10-K Note 7: $4.3m of $19.0m FY26 depreciation in opex
B35: Interest yield on cash | D35: 0.025 | F35: "CashYield" | H35: FY26 interest income $2.8m on ~$104m avg cash = 2.7%
B36: Revenue capacity after FY27 expansion ($MM) | D36: 5800 | F36: "Capacity" | H36: Q4 FY26 release: ~$5bn today + ~$0.8bn PTS Tijuana expansion (online Q4 FY27)
B37: Max sustainable utilization | D37: 0.9 | F37: "Util" | H37: Analyst assumption — plants can't run at 100%
B38: Growth capex per $1 of new revenue capacity | D38: =35/800 -> 0.04375 | F38: "CapexIntensity" | H38: Q4 FY26 release: $35m PTS expansion adds ~$800m capacity
B39: Terminal growth rate (Gordon) | D39: 0.03 | F39: "TGR" | H39: <= long-run nominal GDP
B40: Exit EV/EBITDA override (blank = comps median) | D40: 14 | F40: "ExitOverride" | H40: 14.0x = mature-company exit for FY36 (growth ~3%): between precedent median (~12.6x) and 25th-pct peer EV / CY27E EBITDA (~15.5x) on 'Fwd Comps'. Blank reverts to peer EV/LTM median (27.8x), which implied ~7% perpetual growth (DCF!E47). At 14.0x DCF!E47 still shows ~4.7% (Gordon-consistent multiple ~10.3x), so 14.0x is not conservative.
B41: Exit EV/EBITDA multiple used | D41: =IF(ISNUMBER(ExitOverride),ExitOverride,'Comps Analysis'!D30) -> 14 | F41: "ExitMult"
B42: Weight on Gordon TV in blended TV | D42: 0.5 | F42: "TVweight" | H42: Oracle template averaged both methods; kept as an input
B43: Mid-year convention (1 = on, 0 = off) | D43: 1 | F43: "MidYear" | H43: IB standard
B45: Scenarios | C45: 1 | D45: =INDEX(B46:B48,C45) -> Base | F45: <- 1 = Base, 2 = Bull, 3 = Bear
B46: Base | C46: 1
B47: Bull | C47: 2
B48: Bear | C48: 3
B51: Ratios & Assumptions
C52: ="Historical — fiscal years ending "&TEXT(FYE,"mmmm d") -> Historical — fiscal years ending June 30 | F52: ="Projected — fiscal years ending "&TEXT(FYE,"mmmm d") -> Projected — fiscal years ending June 30
C53: FY24PF | D53: FY25A | E53: FY26A | F53: FY27E | G53: FY28E | H53: FY29E | I53: FY30E | J53: FY31E | K53: FY32E | L53: FY33E | M53: FY34E | N53: FY35E | O53: FY36E
B55: =Inc_Stmt!B8&" revenue growth" -> Custom products revenue growth | E55: =Inc_Stmt!E8/Inc_Stmt!D8-1 -> 0.67710803 | F55: =OFFSET(F55,Scenario,0) -> 0.54 | G55: =OFFSET(G55,Scenario,0) -> 0.25 | H55: =OFFSET(H55,Scenario,0) -> 0.16 | I55: =OFFSET(I55,Scenario,0) -> 0.11 | J55: =OFFSET(J55,Scenario,0) -> 0.08 | K55: =OFFSET(K55,Scenario,0) -> 0.065 | L55: =OFFSET(L55,Scenario,0) -> 0.055 | M55: =OFFSET(M55,Scenario,0) -> 0.045 | ... O55: =OFFSET(O55,Scenario,0) -> 0.03 | Q55: Base FY27 total calibrated to guidance midpoint $2.5bn (range $2.4–2.6bn, Q4 FY26 release)
B56: =$B$46 -> Base | F56: 0.54 | G56: 0.25 | H56: 0.16 | I56: 0.11 | J56: 0.08 | K56: 0.065 | L56: 0.055 | M56: 0.045 | N56: 0.035 | O56: 0.03
B57: =$B$47 -> Bull | F57: =F56+0.06 -> 0.6 | G57: =G56+0.04 -> 0.29 | H57: =H56+0.04 -> 0.2 | I57: =I56+0.04 -> 0.15 | J57: =J56+0.02 -> 0.1 | K57: =K56+0.02 -> 0.085 | L57: =L56+0.02 -> 0.075 | M57: =M56+0.005 -> 0.05 | N57: =N56+0.005 -> 0.04 | O57: =O56+0 -> 0.03
B58: =$B$48 -> Bear | F58: =F56-0.06 -> 0.48 | G58: =G56-0.06 -> 0.19 | H58: =H56-0.06 -> 0.1 | I58: =I56-0.06 -> 0.05 | J58: =J56-0.03 -> 0.05 | K58: =K56-0.03 -> 0.035 | L58: =L56-0.03 -> 0.025 | M58: =M56-0.005 -> 0.04 | N58: =N56-0.005 -> 0.03 | O58: =O56+0 -> 0.03
B60: =Inc_Stmt!B9&" revenue growth" -> Powertrain solutions (PTS) revenue growth | E60: =Inc_Stmt!E9/Inc_Stmt!D9-1 -> 2.5919598 | F60: =OFFSET(F60,Scenario,0) -> 1.5 | G60: =OFFSET(G60,Scenario,0) -> 0.42 | H60: =OFFSET(H60,Scenario,0) -> 0.26 | I60: =OFFSET(I60,Scenario,0) -> 0.18 | J60: =OFFSET(J60,Scenario,0) -> 0.125 | K60: =OFFSET(K60,Scenario,0) -> 0.1 | L60: =OFFSET(L60,Scenario,0) -> 0.075 | M60: =OFFSET(M60,Scenario,0) -> 0.055 | ... O60: =OFFSET(O60,Scenario,0) -> 0.03 | Q60: PTS +259% in FY26; ~1/3 of Q4 FY26 revenue
B61: =$B$46 -> Base | F61: 1.5 | G61: 0.42 | H61: 0.26 | I61: 0.18 | J61: 0.125 | K61: 0.1 | L61: 0.075 | M61: 0.055 | N61: 0.045 | O61: 0.03
B62: =$B$47 -> Bull | F62: =F61+0.06 -> 1.56 | G62: =G61+0.04 -> 0.46 | H62: =H61+0.04 -> 0.3 | I62: =I61+0.04 -> 0.22 | J62: =J61+0.02 -> 0.145 | K62: =K61+0.02 -> 0.12 | L62: =L61+0.02 -> 0.095 | M62: =M61+0.005 -> 0.06 | N62: =N61+0.005 -> 0.05 | O62: =O61+0 -> 0.03
B63: =$B$48 -> Bear | F63: =F61-0.06 -> 1.44 | G63: =G61-0.06 -> 0.36 | H63: =H61-0.06 -> 0.2 | I63: =I61-0.06 -> 0.12 | J63: =J61-0.03 -> 0.095 | K63: =K61-0.03 -> 0.07 | L63: =L61-0.03 -> 0.045 | M63: =M61-0.005 -> 0.05 | N63: =N61-0.005 -> 0.04 | O63: =O61+0 -> 0.03
B65: =Inc_Stmt!B10&" revenue growth" -> Standard products revenue growth | E65: =Inc_Stmt!E10/Inc_Stmt!D10-1 -> 0.2283237 | F65: =OFFSET(F65,Scenario,0) -> 0.1 | G65: =OFFSET(G65,Scenario,0) -> 0.08 | H65: =OFFSET(H65,Scenario,0) -> 0.06 | I65: =OFFSET(I65,Scenario,0) -> 0.05 | J65: =OFFSET(J65,Scenario,0) -> 0.04 | K65: =OFFSET(K65,Scenario,0) -> 0.04 | L65: =OFFSET(L65,Scenario,0) -> 0.035 | M65: =OFFSET(M65,Scenario,0) -> 0.03 | ... O65: =OFFSET(O65,Scenario,0) -> 0.03
B66: =$B$46 -> Base | F66: 0.1 | G66: 0.08 | H66: 0.06 | I66: 0.05 | J66: 0.04 | K66: 0.04 | L66: 0.035 | M66: 0.03 | N66: 0.03 | O66: 0.03
B67: =$B$47 -> Bull | F67: =F66+0.06 -> 0.16 | G67: =G66+0.04 -> 0.12 | H67: =H66+0.04 -> 0.1 | I67: =I66+0.04 -> 0.09 | J67: =J66+0.02 -> 0.06 | K67: =K66+0.02 -> 0.06 | L67: =L66+0.02 -> 0.055 | M67: =M66+0.005 -> 0.035 | N67: =N66+0.005 -> 0.035 | O67: =O66+0 -> 0.03
B68: =$B$48 -> Bear | F68: =F66-0.06 -> 0.04 | G68: =G66-0.06 -> 0.02 | H68: =H66-0.06 -> 0 | I68: =I66-0.06 -> -0.01 | J68: =J66-0.03 -> 0.01 | K68: =K66-0.03 -> 0.01 | L68: =L66-0.03 -> 0.005 | M68: =M66-0.005 -> 0.025 | N68: =N66-0.005 -> 0.025 | O68: =O66+0 -> 0.03
B70: =Inc_Stmt!B11&" revenue growth" -> Services revenue growth | E70: =Inc_Stmt!E11/Inc_Stmt!D11-1 -> 0.045774648 | F70: =OFFSET(F70,Scenario,0) -> 0.2 | G70: =OFFSET(G70,Scenario,0) -> 0.15 | H70: =OFFSET(H70,Scenario,0) -> 0.12 | I70: =OFFSET(I70,Scenario,0) -> 0.1 | J70: =OFFSET(J70,Scenario,0) -> 0.08 | K70: =OFFSET(K70,Scenario,0) -> 0.07 | L70: =OFFSET(L70,Scenario,0) -> 0.06 | M70: =OFFSET(M70,Scenario,0) -> 0.05 | ... O70: =OFFSET(O70,Scenario,0) -> 0.03
B71: =$B$46 -> Base | F71: 0.2 | G71: 0.15 | H71: 0.12 | I71: 0.1 | J71: 0.08 | K71: 0.07 | L71: 0.06 | M71: 0.05 | N71: 0.045 | O71: 0.03
B72: =$B$47 -> Bull | F72: =F71+0.06 -> 0.26 | G72: =G71+0.04 -> 0.19 | H72: =H71+0.04 -> 0.16 | I72: =I71+0.04 -> 0.14 | J72: =J71+0.02 -> 0.1 | K72: =K71+0.02 -> 0.09 | L72: =L71+0.02 -> 0.08 | M72: =M71+0.005 -> 0.055 | N72: =N71+0.005 -> 0.05 | O72: =O71+0 -> 0.03
B73: =$B$48 -> Bear | F73: =F71-0.06 -> 0.14 | G73: =G71-0.06 -> 0.09 | H73: =H71-0.06 -> 0.06 | I73: =I71-0.06 -> 0.04 | J73: =J71-0.03 -> 0.05 | K73: =K71-0.03 -> 0.04 | L73: =L71-0.03 -> 0.03 | M73: =M71-0.005 -> 0.045 | N73: =N71-0.005 -> 0.04 | O73: =O71+0 -> 0.03
B75: Gross margin (incl. depreciation in COGS) | C75: =Inc_Stmt!C15/Inc_Stmt!C12 -> 0.3944479 | D75: =Inc_Stmt!D15/Inc_Stmt!D12 -> 0.36918538 | E75: =Inc_Stmt!E15/Inc_Stmt!E12 -> 0.35040798 | F75: =OFFSET(F75,Scenario,0) -> 0.36 | G75: =OFFSET(G75,Scenario,0) -> 0.365 | H75: =OFFSET(H75,Scenario,0) -> 0.368 | I75: =OFFSET(I75,Scenario,0) -> 0.368 | J75: =OFFSET(J75,Scenario,0) -> 0.366 | K75: =OFFSET(K75,Scenario,0) -> 0.362 | L75: =OFFSET(L75,Scenario,0) -> 0.358 | M75: =OFFSET(M75,Scenario,0) -> 0.354 | ... O75: =OFFSET(O75,Scenario,0) -> 0.348 | Q75: Ramp inefficiencies roll off (1.8–2.0% of rev in Q2–Q3 FY26), then fade as industry capacity arrives
B76: =$B$46 -> Base | F76: 0.36 | G76: 0.365 | H76: 0.368 | I76: 0.368 | J76: 0.366 | K76: 0.362 | L76: 0.358 | M76: 0.354 | N76: 0.35 | O76: 0.348
B77: =$B$47 -> Bull | F77: =F76+0.01 -> 0.37 | G77: =G76+0.01 -> 0.375 | H77: =H76+0.01 -> 0.378 | I77: =I76+0.01 -> 0.378 | J77: =J76+0.01 -> 0.376 | K77: =K76+0.01 -> 0.372 | L77: =L76+0.01 -> 0.368 | M77: =M76+0.01 -> 0.364 | ... O77: =O76+0.01 -> 0.358
B78: =$B$48 -> Bear | F78: =F76-0.02 -> 0.34 | G78: =G76-0.02 -> 0.345 | H78: =H76-0.02 -> 0.348 | I78: =I76-0.02 -> 0.348 | J78: =J76-0.02 -> 0.346 | K78: =K76-0.02 -> 0.342 | L78: =L76-0.02 -> 0.338 | M78: =M76-0.02 -> 0.334 | ... O78: =O76-0.02 -> 0.328
B80: SG&A (% of revenue, incl. SBC) | C80: =-Inc_Stmt!C17/Inc_Stmt!C12 -> 0.20861819 | D80: =-Inc_Stmt!D17/Inc_Stmt!D12 -> 0.19420118 | E80: =-Inc_Stmt!E17/Inc_Stmt!E12 -> 0.18512329 | F80: =OFFSET(F80,Scenario,0) -> 0.135 | G80: =OFFSET(G80,Scenario,0) -> 0.124 | H80: =OFFSET(H80,Scenario,0) -> 0.12 | I80: =OFFSET(I80,Scenario,0) -> 0.12 | J80: =OFFSET(J80,Scenario,0) -> 0.12 | K80: =OFFSET(K80,Scenario,0) -> 0.122 | L80: =OFFSET(L80,Scenario,0) -> 0.124 | M80: =OFFSET(M80,Scenario,0) -> 0.126 | ... O80: =OFFSET(O80,Scenario,0) -> 0.13 | Q80: FY26 18.5% incl. $64.2m IPO/one-off items (14.0% ex-items); FY27 set so adj. EBITDA ~ guidance midpoint $600m
B81: =$B$46 -> Base | F81: 0.135 | G81: 0.124 | H81: 0.12 | I81: 0.12 | J81: 0.12 | K81: 0.122 | L81: 0.124 | M81: 0.126 | N81: 0.128 | O81: 0.13
B82: =$B$47 -> Bull | F82: =F81-0.005 -> 0.13 | G82: =G81-0.005 -> 0.119 | H82: =H81-0.005 -> 0.115 | I82: =I81-0.005 -> 0.115 | J82: =J81-0.005 -> 0.115 | K82: =K81-0.005 -> 0.117 | L82: =L81-0.005 -> 0.119 | M82: =M81-0.005 -> 0.121 | ... O82: =O81-0.005 -> 0.125
B83: =$B$48 -> Bear | F83: =F81+0.01 -> 0.145 | G83: =G81+0.01 -> 0.134 | H83: =H81+0.01 -> 0.13 | I83: =I81+0.01 -> 0.13 | J83: =J81+0.01 -> 0.13 | K83: =K81+0.01 -> 0.132 | L83: =L81+0.01 -> 0.134 | M83: =M81+0.01 -> 0.136 | ... O83: =O81+0.01 -> 0.14
B85: Stock-based compensation (% of revenue) | C85: =Inc_Stmt!C41/Inc_Stmt!C12 -> 0.0031075202 | D85: =Inc_Stmt!D41/Inc_Stmt!D12 -> 0.0023685985 | E85: =Inc_Stmt!E41/Inc_Stmt!E12 -> 0.007067312 | F85: =OFFSET(F85,Scenario,0) -> 0.008 | G85: =OFFSET(G85,Scenario,0) -> 0.008 | H85: =OFFSET(H85,Scenario,0) -> 0.008 | I85: =OFFSET(I85,Scenario,0) -> 0.008 | J85: =OFFSET(J85,Scenario,0) -> 0.008 | K85: =OFFSET(K85,Scenario,0) -> 0.008 | L85: =OFFSET(L85,Scenario,0) -> 0.008 | M85: =OFFSET(M85,Scenario,0) -> 0.008 | ... O85: =OFFSET(O85,Scenario,0) -> 0.008 | Q85: Non-cash; embedded in SG&A. Treated as a real cost in the DCF (not added back)
B86: =$B$46 -> Base | F86: 0.008 | G86: 0.008 | H86: 0.008 | I86: 0.008 | J86: 0.008 | K86: 0.008 | L86: 0.008 | M86: 0.008 | N86: 0.008 | O86: 0.008
B87: =$B$47 -> Bull | F87: =F86+0 -> 0.008 | G87: =G86+0 -> 0.008 | H87: =H86+0 -> 0.008 | I87: =I86+0 -> 0.008 | J87: =J86+0 -> 0.008 | K87: =K86+0 -> 0.008 | L87: =L86+0 -> 0.008 | M87: =M86+0 -> 0.008 | ... O87: =O86+0 -> 0.008
B88: =$B$48 -> Bear | F88: =F86+0 -> 0.008 | G88: =G86+0 -> 0.008 | H88: =H86+0 -> 0.008 | I88: =I86+0 -> 0.008 | J88: =J86+0 -> 0.008 | K88: =K86+0 -> 0.008 | L88: =L86+0 -> 0.008 | M88: =M86+0 -> 0.008 | ... O88: =O86+0 -> 0.008
B90: Depreciation (% of beginning net PP&E) | E90: =Inc_Stmt!E37/Bal_Sht!D16 -> 0.17564944 | F90: =OFFSET(F90,Scenario,0) -> 0.15 | G90: =OFFSET(G90,Scenario,0) -> 0.15 | H90: =OFFSET(H90,Scenario,0) -> 0.15 | I90: =OFFSET(I90,Scenario,0) -> 0.15 | J90: =OFFSET(J90,Scenario,0) -> 0.15 | K90: =OFFSET(K90,Scenario,0) -> 0.15 | L90: =OFFSET(L90,Scenario,0) -> 0.15 | M90: =OFFSET(M90,Scenario,0) -> 0.15 | ... O90: =OFFSET(O90,Scenario,0) -> 0.15 | Q90: FY26: $19.0m on $108.2m opening net PP&E = 17.6% (new plants partial-year)
B91: =$B$46 -> Base | F91: 0.15 | G91: 0.15 | H91: 0.15 | I91: 0.15 | J91: 0.15 | K91: 0.15 | L91: 0.15 | M91: 0.15 | N91: 0.15 | O91: 0.15
B92: =$B$47 -> Bull | F92: =F91+0 -> 0.15 | G92: =G91+0 -> 0.15 | H92: =H91+0 -> 0.15 | I92: =I91+0 -> 0.15 | J92: =J91+0 -> 0.15 | K92: =K91+0 -> 0.15 | L92: =L91+0 -> 0.15 | M92: =M91+0 -> 0.15 | ... O92: =O91+0 -> 0.15
B93: =$B$48 -> Bear | F93: =F91+0 -> 0.15 | G93: =G91+0 -> 0.15 | H93: =H91+0 -> 0.15 | I93: =I91+0 -> 0.15 | J93: =J91+0 -> 0.15 | K93: =K91+0 -> 0.15 | L93: =L91+0 -> 0.15 | M93: =M91+0 -> 0.15 | ... O93: =O91+0 -> 0.15
B95: Maintenance capex (% of revenue) | D95: =-Inc_Stmt!D44/Inc_Stmt!D12 -> 0.11167862 | E95: =-Inc_Stmt!E44/Inc_Stmt!E12 -> 0.081619848 | F95: =OFFSET(F95,Scenario,0) -> 0.01 | G95: =OFFSET(G95,Scenario,0) -> 0.012 | H95: =OFFSET(H95,Scenario,0) -> 0.013 | I95: =OFFSET(I95,Scenario,0) -> 0.014 | J95: =OFFSET(J95,Scenario,0) -> 0.015 | K95: =OFFSET(K95,Scenario,0) -> 0.015 | L95: =OFFSET(L95,Scenario,0) -> 0.015 | M95: =OFFSET(M95,Scenario,0) -> 0.015 | ... O95: =OFFSET(O95,Scenario,0) -> 0.015 | Q95: Mgmt: maintenance ~1% of revenue (Q4 FY26 release); stepped to 1.5% so capex converges toward D&A. Hist = total capex
B96: =$B$46 -> Base | F96: 0.01 | G96: 0.012 | H96: 0.013 | I96: 0.014 | J96: 0.015 | K96: 0.015 | L96: 0.015 | M96: 0.015 | N96: 0.015 | O96: 0.015
B97: =$B$47 -> Bull | F97: =F96+0 -> 0.01 | G97: =G96+0 -> 0.012 | H97: =H96+0 -> 0.013 | I97: =I96+0 -> 0.014 | J97: =J96+0 -> 0.015 | K97: =K96+0 -> 0.015 | L97: =L96+0 -> 0.015 | M97: =M96+0 -> 0.015 | ... O97: =O96+0 -> 0.015
B98: =$B$48 -> Bear | F98: =F96+0 -> 0.01 | G98: =G96+0 -> 0.012 | H98: =H96+0 -> 0.013 | I98: =I96+0 -> 0.014 | J98: =J96+0 -> 0.015 | K98: =K96+0 -> 0.015 | L98: =L96+0 -> 0.015 | M98: =M96+0 -> 0.015 | ... O98: =O96+0 -> 0.015
B100: Committed expansion capex ($MM) | F100: =OFFSET(F100,Scenario,0) -> 62 | G100: =OFFSET(G100,Scenario,0) -> 0 | H100: =OFFSET(H100,Scenario,0) -> 0 | I100: =OFFSET(I100,Scenario,0) -> 0 | J100: =OFFSET(J100,Scenario,0) -> 0 | K100: =OFFSET(K100,Scenario,0) -> 0 | L100: =OFFSET(L100,Scenario,0) -> 0 | M100: =OFFSET(M100,Scenario,0) -> 0 | ... O100: =OFFSET(O100,Scenario,0) -> 0 | Q100: FY27 capex guide ~$87m less 1% maintenance (~$25m) = $62m (remaining 2025–26 program + $35m PTS Tijuana)
B101: =$B$46 -> Base | F101: 62 | G101: 0 | H101: 0 | I101: 0 | J101: 0 | K101: 0 | L101: 0 | M101: 0 | N101: 0 | O101: 0
B102: =$B$47 -> Bull | F102: =F101+0 -> 62 | G102: =G101+0 -> 0 | H102: =H101+0 -> 0 | I102: =I101+0 -> 0 | J102: =J101+0 -> 0 | K102: =K101+0 -> 0 | L102: =L101+0 -> 0 | M102: =M101+0 -> 0 | ... O102: =O101+0 -> 0
B103: =$B$48 -> Bear | F103: =F101+0 -> 62 | G103: =G101+0 -> 0 | H103: =H101+0 -> 0 | I103: =I101+0 -> 0 | J103: =J101+0 -> 0 | K103: =K101+0 -> 0 | L103: =L101+0 -> 0 | M103: =M101+0 -> 0 | ... O103: =O101+0 -> 0
B105: Days sales outstanding (A/R, 365-day) | D105: =Bal_Sht!D8/Inc_Stmt!D12*365 -> 77.522544 | E105: =Bal_Sht!E8/Inc_Stmt!E12*365 -> 84.724804 | F105: =OFFSET(F105,Scenario,0) -> 85 | G105: =OFFSET(G105,Scenario,0) -> 85 | H105: =OFFSET(H105,Scenario,0) -> 85 | I105: =OFFSET(I105,Scenario,0) -> 85 | J105: =OFFSET(J105,Scenario,0) -> 85 | K105: =OFFSET(K105,Scenario,0) -> 85 | L105: =OFFSET(L105,Scenario,0) -> 85 | M105: =OFFSET(M105,Scenario,0) -> 85 | ... O105: =OFFSET(O105,Scenario,0) -> 85
B106: =$B$46 -> Base | F106: 85 | G106: 85 | H106: 85 | I106: 85 | J106: 85 | K106: 85 | L106: 85 | M106: 85 | N106: 85 | O106: 85
B107: =$B$47 -> Bull | F107: 80 | G107: 80 | H107: 80 | I107: 80 | J107: 80 | K107: 80 | L107: 80 | M107: 80 | N107: 80 | O107: 80
B108: =$B$48 -> Bear | F108: 90 | G108: 90 | H108: 90 | I108: 90 | J108: 90 | K108: 90 | L108: 90 | M108: 90 | N108: 90 | O108: 90
B110: Days inventory outstanding (on COGS) | D110: =Bal_Sht!D9/-Inc_Stmt!D14*365 -> 90.325443 | E110: =Bal_Sht!E9/-Inc_Stmt!E14*365 -> 98.847976 | F110: =OFFSET(F110,Scenario,0) -> 99 | G110: =OFFSET(G110,Scenario,0) -> 99 | H110: =OFFSET(H110,Scenario,0) -> 99 | I110: =OFFSET(I110,Scenario,0) -> 99 | J110: =OFFSET(J110,Scenario,0) -> 99 | K110: =OFFSET(K110,Scenario,0) -> 99 | L110: =OFFSET(L110,Scenario,0) -> 99 | M110: =OFFSET(M110,Scenario,0) -> 99 | ... O110: =OFFSET(O110,Scenario,0) -> 99
B111: =$B$46 -> Base | F111: 99 | G111: 99 | H111: 99 | I111: 99 | J111: 99 | K111: 99 | L111: 99 | M111: 99 | N111: 99 | O111: 99
B112: =$B$47 -> Bull | F112: 92 | G112: 92 | H112: 92 | I112: 92 | J112: 92 | K112: 92 | L112: 92 | M112: 92 | N112: 92 | O112: 92
B113: =$B$48 -> Bear | F113: 110 | G113: 110 | H113: 110 | I113: 110 | J113: 110 | K113: 110 | L113: 110 | M113: 110 | N113: 110 | O113: 110
B115: Days payable outstanding (on COGS) | D115: =Bal_Sht!D25/-Inc_Stmt!D14*365 -> 47.586083 | E115: =Bal_Sht!E25/-Inc_Stmt!E14*365 -> 51.617844 | F115: =OFFSET(F115,Scenario,0) -> 52 | G115: =OFFSET(G115,Scenario,0) -> 52 | H115: =OFFSET(H115,Scenario,0) -> 52 | I115: =OFFSET(I115,Scenario,0) -> 52 | J115: =OFFSET(J115,Scenario,0) -> 52 | K115: =OFFSET(K115,Scenario,0) -> 52 | L115: =OFFSET(L115,Scenario,0) -> 52 | M115: =OFFSET(M115,Scenario,0) -> 52 | ... O115: =OFFSET(O115,Scenario,0) -> 52
B116: =$B$46 -> Base | F116: 52 | G116: 52 | H116: 52 | I116: 52 | J116: 52 | K116: 52 | L116: 52 | M116: 52 | N116: 52 | O116: 52
B117: =$B$47 -> Bull | F117: 55 | G117: 55 | H117: 55 | I117: 55 | J117: 55 | K117: 55 | L117: 55 | M117: 55 | N117: 55 | O117: 55
B118: =$B$48 -> Bear | F118: 48 | G118: 48 | H118: 48 | I118: 48 | J118: 48 | K118: 48 | L118: 48 | M118: 48 | N118: 48 | O118: 48
...

Sheet Inc_Stmt
A1: ="Income Statement for "&Name -> Income Statement for Forgent Power Solutions, Inc.
A2: (Dollars in Millions unless stated)
C4: ="Historical — fiscal years ending "&TEXT(FYE,"mmmm d") -> Historical — fiscal years ending June 30 | F4: ="Projected — fiscal years ending "&TEXT(FYE,"mmmm d") -> Projected — fiscal years ending June 30
C5: FY24PF | D5: FY25A | E5: FY26A | F5: FY27E | G5: FY28E | H5: FY29E | I5: FY30E | J5: FY31E | K5: FY32E | L5: FY33E | M5: FY34E | N5: FY35E | O5: FY36E
B7: Revenue
B8: Custom products | D8: 590.6 | E8: 990.5 | F8: =E8*(1+Assumptions!F55) -> 1525.37 | G8: =F8*(1+Assumptions!G55) -> 1906.7125 | H8: =G8*(1+Assumptions!H55) -> 2211.7865 | I8: =H8*(1+Assumptions!I55) -> 2455.083 | J8: =I8*(1+Assumptions!J55) -> 2651.4897 | K8: =J8*(1+Assumptions!K55) -> 2823.8365 | L8: =K8*(1+Assumptions!L55) -> 2979.1475 | M8: =L8*(1+Assumptions!M55) -> 3113.2091 | ... O8: =N8*(1+Assumptions!O55) -> 3318.8366 | Q8: 10-K Note 14 disaggregation ($0.1m rounding; PF FY24 by offering not disclosed)
B9: Powertrain solutions (PTS) | D9: 99.5 | E9: 357.4 | F9: =E9*(1+Assumptions!F60) -> 893.5 | G9: =F9*(1+Assumptions!G60) -> 1268.77 | H9: =G9*(1+Assumptions!H60) -> 1598.6502 | I9: =H9*(1+Assumptions!I60) -> 1886.4072 | J9: =I9*(1+Assumptions!J60) -> 2122.2081 | K9: =J9*(1+Assumptions!K60) -> 2334.429 | L9: =K9*(1+Assumptions!L60) -> 2509.5111 | M9: =L9*(1+Assumptions!M60) -> 2647.5342 | ... O9: =N9*(1+Assumptions!O60) -> 2849.6735
B10: Standard products | D10: 34.6 | E10: 42.5 | F10: =E10*(1+Assumptions!F65) -> 46.75 | G10: =F10*(1+Assumptions!G65) -> 50.49 | H10: =G10*(1+Assumptions!H65) -> 53.5194 | I10: =H10*(1+Assumptions!I65) -> 56.19537 | J10: =I10*(1+Assumptions!J65) -> 58.443185 | K10: =J10*(1+Assumptions!K65) -> 60.780912 | L10: =K10*(1+Assumptions!L65) -> 62.908244 | M10: =L10*(1+Assumptions!M65) -> 64.795491 | ... O10: =N10*(1+Assumptions!O65) -> 68.741537
B11: Services | D11: 28.4 | E11: 29.7 | F11: =E11*(1+Assumptions!F70) -> 35.64 | G11: =F11*(1+Assumptions!G70) -> 40.986 | H11: =G11*(1+Assumptions!H70) -> 45.90432 | I11: =H11*(1+Assumptions!I70) -> 50.494752 | J11: =I11*(1+Assumptions!J70) -> 54.534332 | K11: =J11*(1+Assumptions!K70) -> 58.351735 | L11: =K11*(1+Assumptions!L70) -> 61.85284 | M11: =L11*(1+Assumptions!M70) -> 64.945482 | ... O11: =N11*(1+Assumptions!O70) -> 69.904069
B12: Total revenue | C12: 482.7 | D12: 753.188 | E12: 1420.059 | F12: =SUM(F8:F11) -> 2501.26 | G12: =SUM(G8:G11) -> 3266.9585 | H12: =SUM(H8:H11) -> 3909.8604 | I12: =SUM(I8:I11) -> 4448.1804 | J12: =SUM(J8:J11) -> 4886.6753 | K12: =SUM(K8:K11) -> 5277.3981 | L12: =SUM(L8:L11) -> 5613.4197 | M12: =SUM(M8:M11) -> 5890.4843 | ... O12: =SUM(O8:O11) -> 6307.1557 | Q12: PF FY24: IPO 424B4 pro forma (all acquisitions from 7/1/23); FY25–26: 10-K
B14: Cost of revenues (incl. depreciation) | C14: -292.3 | D14: -475.122 | E14: -922.459 | F14: =-F12*(1-Assumptions!F75) -> -1600.8064 | G14: =-G12*(1-Assumptions!G75) -> -2074.5186 | H14: =-H12*(1-Assumptions!H75) -> -2471.0318 | I14: =-I12*(1-Assumptions!I75) -> -2811.25 | J14: =-J12*(1-Assumptions!J75) -> -3098.1521 | K14: =-K12*(1-Assumptions!K75) -> -3366.98 | L14: =-L12*(1-Assumptions!L75) -> -3603.8154 | M14: =-M12*(1-Assumptions!M75) -> -3805.2529 | ... O14: =-O12*(1-Assumptions!O75) -> -4112.2655 | Q14: FY26 COGS includes $14.7m depreciation (10-K Note 7)
B15: Gross profit | C15: =C12+C14 -> 190.4 | D15: =D12+D14 -> 278.066 | E15: =E12+E14 -> 497.6 | F15: =F12+F14 -> 900.4536 | G15: =G12+G14 -> 1192.4399 | H15: =H12+H14 -> 1438.8286 | I15: =I12+I14 -> 1636.9304 | J15: =J12+J14 -> 1788.5232 | ... O15: =O12+O14 -> 2194.8902
B17: Selling, general & administrative | C17: -100.7 | D17: -146.27 | E17: -262.886 | F17: =-F12*Assumptions!F80 -> -337.6701 | G17: =-G12*Assumptions!G80 -> -405.10285 | H17: =-H12*Assumptions!H80 -> -469.18325 | I17: =-I12*Assumptions!I80 -> -533.78164 | J17: =-J12*Assumptions!J80 -> -586.40104 | K17: =-K12*Assumptions!K80 -> -643.84257 | L17: =-L12*Assumptions!L80 -> -696.06404 | M17: =-M12*Assumptions!M80 -> -742.20103 | ... O17: =-O12*Assumptions!O80 -> -819.93024
B18: Depreciation & amortization (opex line) | C18: -71.3 | D18: -59.559 | E18: -52.225 | F18: =-(F38+F37*DepOpex) -> -32.238042 | G18: =-(G38+G37*DepOpex) -> -33.909563 | H18: =-(H38+H37*DepOpex) -> -33.115227 | I18: =-(I38+I37*DepOpex) -> -32.093869 | J18: =-(J38+J37*DepOpex) -> -32.817345 | K18: =-(K38+K37*DepOpex) -> -33.806068 | L18: =-(L38+L37*DepOpex) -> -34.939752 | M18: =-(M38+M37*DepOpex) -> -36.533398 | ... O18: =-(O38+O37*DepOpex) -> -39.166107 | Q18: Projected = intangible amortization + opex share of depreciation
B20: Operating income (EBIT) | C20: =C15+C17+C18 -> 18.4 | D20: =D15+D17+D18 -> 72.237 | E20: =E15+E17+E18 -> 182.489 | F20: =F15+F17+F18 -> 530.54546 | G20: =G15+G17+G18 -> 753.42744 | H20: =H15+H17+H18 -> 936.53016 | I20: =I15+I17+I18 -> 1071.0549 | J20: =J15+J17+J18 -> 1169.3048 | ... O20: =O15+O17+O18 -> 1335.7938
B22: Interest expense | C22: -58.7 | D22: -54.778 | E22: -57.127 | F22: =-Capitalization!F22 -> -38.24415 | G22: =-Capitalization!G22 -> -37.86075 | H22: =-Capitalization!H22 -> -37.47735 | I22: =-Capitalization!I22 -> -37.09395 | J22: =-Capitalization!J22 -> -36.71055 | K22: =-Capitalization!K22 -> -36.32715 | L22: =-Capitalization!L22 -> -35.94375 | M22: =-Capitalization!M22 -> -35.56035 | ... O22: =-Capitalization!O22 -> -34.79355 | Q22: Capitalization tab: beginning term-loan balance x 6.39%
B23: Interest income | C23: 4.4 | D23: 5.558 | E23: 2.787 | F23: =Bal_Sht!E7*CashYield -> 2.436925 | G23: =Bal_Sht!F7*CashYield -> 7.8848351 | H23: =Bal_Sht!G7*CashYield -> 20.213931 | I23: =Bal_Sht!H7*CashYield -> 36.415939 | J23: =Bal_Sht!I7*CashYield -> 55.576963 | K23: =Bal_Sht!J7*CashYield -> 77.119854 | L23: =Bal_Sht!K7*CashYield -> 100.34565 | M23: =Bal_Sht!L7*CashYield -> 124.76445 | ... O23: =Bal_Sht!N7*CashYield -> 177.40689 | Q23: Beginning cash x CashYield (no circularity)
B24: Other non-operating income / (expense) | C24: -0.6 | D24: -0.231 | E24: -0.749 | F24: 0 | G24: 0 | H24: 0 | I24: 0 | J24: 0 | K24: 0 | L24: 0 | M24: 0 | N24: 0 | O24: 0
B26: Earnings before income taxes | C26: =SUM(C20:C24) -> -36.5 | D26: =SUM(D20:D24) -> 22.786 | E26: =SUM(E20:E24) -> 127.4 | F26: =SUM(F20:F24) -> 494.73823 | G26: =SUM(G20:G24) -> 723.45152 | H26: =SUM(H20:H24) -> 919.26674 | I26: =SUM(I20:I24) -> 1070.3769 | J26: =SUM(J20:J24) -> 1188.1712 | ... O26: =SUM(O20:O24) -> 1478.4072
B28: Income tax (expense) / benefit | C28: 8.4 | D28: -5.34 | E28: -21.365 | F28: =-F26*TaxRate -> -123.68456 | G28: =-G26*TaxRate -> -180.86288 | H28: =-H26*TaxRate -> -229.81668 | I28: =-I26*TaxRate -> -267.59421 | J28: =-J26*TaxRate -> -297.0428 | K28: =-K26*TaxRate -> -318.39054 | L28: =-L26*TaxRate -> -335.75059 | M28: =-M26*TaxRate -> -348.92528 | ... O28: =-O26*TaxRate -> -369.60179 | Q28: Normalized 25% (fully exchanged); history as reported
B30: Net income (incl. NCI) | C30: =C26+C28 -> -28.1 | D30: =D26+D28 -> 17.446 | E30: =E26+E28 -> 106.035 | F30: =F26+F28 -> 371.05367 | G30: =G26+G28 -> 542.58864 | H30: =H26+H28 -> 689.45005 | I30: =I26+I28 -> 802.78264 | J30: =J26+J28 -> 891.1284 | ... O30: =O26+O28 -> 1108.8054
B31: Less: net income attributable to NCI | C31: 8.7 | D31: -2.25 | E31: -24.19 | F31: =-F30*NCIpct -> -36.445854 | G31: =-G30*NCIpct -> -53.294463 | H31: =-H30*NCIpct -> -67.719572 | I31: =-I30*NCIpct -> -78.851393 | J31: =-J30*NCIpct -> -87.528942 | K31: =-K30*NCIpct -> -93.819435 | L31: =-L30*NCIpct -> -98.934881 | M31: =-M30*NCIpct -> -102.81704 | ... O31: =-O30*NCIpct -> -108.90974 | Q31: Projected at Class B share of Opco (9.82% post-July 2026 follow-on)
B32: Net income attributable to FPS | C32: =C30+C31 -> -19.4 | D32: =D30+D31 -> 15.196 | E32: =E30+E31 -> 81.845 | F32: =F30+F31 -> 334.60782 | G32: =G30+G31 -> 489.29418 | H32: =H30+H31 -> 621.73048 | I32: =I30+I31 -> 723.93125 | J32: =J30+J31 -> 803.59945 | ... O32: =O30+O31 -> 999.89563
B34: Supplemental information
B35: Diluted shares, fully exchanged (MM) | E35: 304.7 | F35: =DilutedShares -> 305.12388 | G35: =DilutedShares -> 305.12388 | H35: =DilutedShares -> 305.12388 | I35: =DilutedShares -> 305.12388 | J35: =DilutedShares -> 305.12388 | K35: =DilutedShares -> 305.12388 | L35: =DilutedShares -> 305.12388 | M35: =DilutedShares -> 305.12388 | ... O35: =DilutedShares -> 305.12388 | Q35: FY26: company adj. diluted weighted shares (10-K MD&A); FY24–25 pre-IPO n/a
B36: Diluted EPS, fully exchanged (GAAP NI incl. NCI / shares) | E36: =E30/E35 -> 0.34799803 | F36: =F30/F35 -> 1.2160755 | G36: =G30/G35 -> 1.7782569 | H36: =H30/H35 -> 2.2595742 | I36: =I30/I35 -> 2.6310056 | J36: =J30/J35 -> 2.9205462 | K36: =K30/K35 -> 3.1304388 | L36: =L30/L35 -> 3.301124 | ... O36: =O30/O35 -> 3.6339515 | Q36: Reported GAAP Class A EPS $0.30 covers 2/6–6/30/26 only; this is the full-year economic EPS
B37: Depreciation (total) | C37: 3.4 | D37: 6.2 | E37: 19 | F37: =Assumptions!F90*Bal_Sht!E16 -> 30.74355 | G37: =Assumptions!G90*Bal_Sht!F16 -> 39.183907 | H37: =Assumptions!H90*Bal_Sht!G16 -> 39.186847 | I37: =Assumptions!I90*Bal_Sht!H16 -> 40.933047 | J37: =Assumptions!J90*Bal_Sht!I16 -> 44.134269 | K37: =Assumptions!K90*Bal_Sht!J16 -> 48.509148 | L37: =Assumptions!L90*Bal_Sht!K16 -> 53.525449 | M37: =Assumptions!M90*Bal_Sht!L16 -> 60.576984 | ... O37: =Assumptions!O90*Bal_Sht!N16 -> 72.226136
B38: Amortization of intangibles | C38: 70.1 | D38: 58.7 | E38: 47.9 | F38: =MIN(Assumptions!F135,Bal_Sht!E19) -> 25.29 | G38: =MIN(Assumptions!G135,Bal_Sht!F19) -> 25.054 | H38: =MIN(Assumptions!H135,Bal_Sht!G19) -> 24.259 | I38: =MIN(Assumptions!I135,Bal_Sht!H19) -> 22.843 | J38: =MIN(Assumptions!J135,Bal_Sht!I19) -> 22.843 | K38: =MIN(Assumptions!K135,Bal_Sht!J19) -> 22.843 | L38: =MIN(Assumptions!L135,Bal_Sht!K19) -> 22.843 | M38: =MIN(Assumptions!M135,Bal_Sht!L19) -> 22.843 | ... O38: =MIN(Assumptions!O135,Bal_Sht!N19) -> 22.843
B39: Total D&A | C39: =C37+C38 -> 73.5 | D39: =D37+D38 -> 64.9 | E39: =E37+E38 -> 66.9 | F39: =F37+F38 -> 56.03355 | G39: =G37+G38 -> 64.237907 | H39: =H37+H38 -> 63.445847 | I39: =I37+I38 -> 63.776047 | J39: =J37+J38 -> 66.977269 | ... O39: =O37+O38 -> 95.069136
B40: EBITDA (GAAP: EBIT + D&A) | C40: =C20+C39 -> 91.9 | D40: =D20+D39 -> 137.137 | E40: =E20+E39 -> 249.389 | F40: =F20+F39 -> 586.57901 | G40: =G20+G39 -> 817.66534 | H40: =H20+H39 -> 999.976 | I40: =I20+I39 -> 1134.8309 | J40: =J20+J39 -> 1236.2821 | ... O40: =O20+O39 -> 1430.863
B41: Stock-based compensation | C41: 1.5 | D41: 1.784 | E41: 10.036 | F41: =F12*Assumptions!F85 -> 20.01008 | G41: =G12*Assumptions!G85 -> 26.135668 | H41: =H12*Assumptions!H85 -> 31.278883 | I41: =I12*Assumptions!I85 -> 35.585443 | J41: =J12*Assumptions!J85 -> 39.093403 | K41: =K12*Assumptions!K85 -> 42.219185 | L41: =L12*Assumptions!L85 -> 44.907358 | M41: =M12*Assumptions!M85 -> 47.123875 | ... O41: =O12*Assumptions!O85 -> 50.457245
B42: IPO / sponsor / integration one-offs | C42: 6.4 | D42: 30.6 | E42: 64.2 | F42: 0 | G42: 0 | H42: 0 | I42: 0 | J42: 0 | K42: 0 | L42: 0 | M42: 0 | N42: 0 | O42: 0 | Q42: FY26: sponsor fees 18.8 + public-co readiness 21.2 + earnout 5.4 + integration 18.8 (Q4 FY26 release recon)
B43: Adj. EBITDA (company definition) | C43: 99.2 | D43: 169.2 | E43: 322.9 | F43: =F40+F41+F42 -> 606.58909 | G43: =G40+G41+G42 -> 843.80101 | H43: =H40+H41+H42 -> 1031.2549 | I43: =I40+I41+I42 -> 1170.4164 | J43: =J40+J41+J42 -> 1275.3755 | K43: =K40+K41+K42 -> 1346.3408 | L43: =L40+L41+L42 -> 1399.8763 | M43: =M40+M41+M42 -> 1437.0409 | ... O43: =O40+O41+O42 -> 1481.3202 | Q43: History as reported; FY27 guidance $575–625m
B44: Capital expenditures | D44: -84.115 | E44: -115.905 | F44: =-SUM(F45:F47) -> -87.0126 | G44: =-SUM(G45:G47) -> -39.203502 | H44: =-SUM(H45:H47) -> -50.828185 | I44: =-SUM(I45:I47) -> -62.274525 | J44: =-SUM(J45:J47) -> -73.30013 | K44: =-SUM(K45:K47) -> -81.951156 | L44: =-SUM(L45:L47) -> -100.53568 | M44: =-SUM(M45:M47) -> -101.82568 | ... O44: =-SUM(O45:O47) -> -103.53737
B45: Maintenance | F45: =F12*Assumptions!F95 -> 25.0126 | G45: =G12*Assumptions!G95 -> 39.203502 | H45: =H12*Assumptions!H95 -> 50.828185 | I45: =I12*Assumptions!I95 -> 62.274525 | J45: =J12*Assumptions!J95 -> 73.30013 | K45: =K12*Assumptions!K95 -> 79.160971 | L45: =L12*Assumptions!L95 -> 84.201296 | M45: =M12*Assumptions!M95 -> 88.357265 | ... O45: =O12*Assumptions!O95 -> 94.607335
B46: Committed expansion | F46: =Assumptions!F100 -> 62 | G46: =Assumptions!G100 -> 0 | H46: =Assumptions!H100 -> 0 | I46: =Assumptions!I100 -> 0 | J46: =Assumptions!J100 -> 0 | K46: =Assumptions!K100 -> 0 | L46: =Assumptions!L100 -> 0 | M46: =Assumptions!M100 -> 0 | ... O46: =Assumptions!O100 -> 0
B47: Capacity-driven growth capex | F47: =(F49-Capacity)*CapexIntensity -> 0 | G47: =(G49-F49)*CapexIntensity -> 0 | H47: =(H49-G49)*CapexIntensity -> 0 | I47: =(I49-H49)*CapexIntensity -> 0 | J47: =(J49-I49)*CapexIntensity -> 0 | K47: =(K49-J49)*CapexIntensity -> 2.7901847 | L47: =(L49-K49)*CapexIntensity -> 16.334384 | M47: =(M49-L49)*CapexIntensity -> 13.46842 | N47: =(N49-M49)*CapexIntensity -> 11.324822 | O47: =(O49-N49)*CapexIntensity -> 8.9300343
B49: Revenue capacity, end of year | F49: =MAX(Capacity,F12/Util) -> 5800 | G49: =MAX(F49,G12/Util) -> 5800 | H49: =MAX(G49,H12/Util) -> 5800 | I49: =MAX(H49,I12/Util) -> 5800 | J49: =MAX(I49,J12/Util) -> 5800 | K49: =MAX(J49,K12/Util) -> 5863.7757 | L49: =MAX(K49,L12/Util) -> 6237.133 | M49: =MAX(L49,M12/Util) -> 6544.9826 | N49: =MAX(M49,N12/Util) -> 6803.8357 | O49: =MAX(N49,O12/Util) -> 7007.9507 | Q49: Capacity only expands once revenue / Util exceeds it; growth capex = new capacity x intensity
B50: Utilization (revenue / capacity) | F50: =F12/F49 -> 0.43125172 | G50: =G12/G49 -> 0.56326871 | H50: =H12/H49 -> 0.67411387 | I50: =I12/I49 -> 0.76692765 | J50: =J12/J49 -> 0.84253023 | K50: =K12/K49 -> 0.9 | L50: =L12/L49 -> 0.9 | M50: =M12/M49 -> 0.9 | ... O50: =O12/O49 -> 0.9
B52: Net working capital (AR + inv + prepaid − AP − accrued − deposits) | D52: =Bal_Sht!D8+Bal_Sht!D9+Bal_Sht!D10-Bal_Sht!D25-Bal_Sht!D26-Bal_Sht!D28 -> 81.446 | E52: =Bal_Sht!E8+Bal_Sht!E9+Bal_Sht!E10-Bal_Sht!E25-Bal_Sht!E26-Bal_Sht!E28 -> 179.71 | F52: =Bal_Sht!F8+Bal_Sht!F9+Bal_Sht!F10-Bal_Sht!F25-Bal_Sht!F26-Bal_Sht!F28 -> 315.8783 | G52: =Bal_Sht!G8+Bal_Sht!G9+Bal_Sht!G10-Bal_Sht!G25-Bal_Sht!G26-Bal_Sht!G28 -> 410.4732 | H52: =Bal_Sht!H8+Bal_Sht!H9+Bal_Sht!H10-Bal_Sht!H25-Bal_Sht!H26-Bal_Sht!H28 -> 489.73948 | I52: =Bal_Sht!I8+Bal_Sht!I9+Bal_Sht!I10-Bal_Sht!I25-Bal_Sht!I26-Bal_Sht!I28 -> 557.16811 | J52: =Bal_Sht!J8+Bal_Sht!J9+Bal_Sht!J10-Bal_Sht!J25-Bal_Sht!J26-Bal_Sht!J28 -> 613.35139 | K52: =Bal_Sht!K8+Bal_Sht!K9+Bal_Sht!K10-Bal_Sht!K25-Bal_Sht!K26-Bal_Sht!K28 -> 665.1112 | ... O52: =Bal_Sht!O8+Bal_Sht!O9+Bal_Sht!O10-Bal_Sht!O25-Bal_Sht!O26-Bal_Sht!O28 -> 806.26185
B53: Increase / (decrease) in NWC | E53: =E52-D52 -> 98.264 | F53: =F52-E52 -> 136.1683 | G53: =G52-F52 -> 94.594896 | H53: =H52-G52 -> 79.266279 | I53: =I52-H52 -> 67.42863 | J53: =J52-I52 -> 56.183281 | K53: =K52-J52 -> 51.759817 | L53: =L52-K52 -> 45.240146 | ... O53: =O52-N52 -> 25.060354
B55: Margins
B56: Gross margin | C56: =C15/C12 -> 0.3944479 | D56: =D15/D12 -> 0.36918538 | E56: =E15/E12 -> 0.35040798 | F56: =F15/F12 -> 0.36 | G56: =G15/G12 -> 0.365 | H56: =H15/H12 -> 0.368 | I56: =I15/I12 -> 0.368 | J56: =J15/J12 -> 0.366 | ... O56: =O15/O12 -> 0.348
B57: EBITDA margin (GAAP) | C57: =C40/C12 -> 0.1903874 | D57: =D40/D12 -> 0.18207539 | E57: =E40/E12 -> 0.17561876 | F57: =F40/F12 -> 0.23451341 | G57: =G40/G12 -> 0.25028336 | H57: =H40/H12 -> 0.25575747 | I57: =I40/I12 -> 0.2551225 | J57: =J40/J12 -> 0.25299042 | ... O57: =O40/O12 -> 0.22686343
B58: Adj. EBITDA margin | C58: =C43/C12 -> 0.20551067 | D58: =D43/D12 -> 0.22464511 | E58: =E43/E12 -> 0.22738492 | F58: =F43/F12 -> 0.24251341 | G58: =G43/G12 -> 0.25828336 | H58: =H43/H12 -> 0.26375747 | I58: =I43/I12 -> 0.2631225 | J58: =J43/J12 -> 0.26099042 | ... O58: =O43/O12 -> 0.23486343
B59: Operating (EBIT) margin | C59: =C20/C12 -> 0.038118914 | D59: =D20/D12 -> 0.095908326 | E59: =E20/E12 -> 0.12850804 | F59: =F20/F12 -> 0.21211128 | G59: =G20/G12 -> 0.23062045 | H59: =H20/H12 -> 0.23953033 | I59: =I20/I12 -> 0.24078494 | J59: =J20/J12 -> 0.23928432 | ... O59: =O20/O12 -> 0.21179021
B60: Net income margin | C60: =C30/C12 -> -0.058214212 | D60: =D30/D12 -> 0.023162876 | E60: =E30/E12 -> 0.074669433 | F60: =F30/F12 -> 0.1483467 | G60: =G30/G12 -> 0.16608373 | H60: =H30/H12 -> 0.17633623 | I60: =I30/I12 -> 0.18047439 | J60: =J30/J12 -> 0.18235883 | ... O60: =O30/O12 -> 0.17580117
B62: Growth
B63: =B8 -> Custom products | E63: =E8/D8-1 -> 0.67710803 | F63: =F8/E8-1 -> 0.54 | G63: =G8/F8-1 -> 0.25 | H63: =H8/G8-1 -> 0.16 | I63: =I8/H8-1 -> 0.11 | J63: =J8/I8-1 -> 0.08 | K63: =K8/J8-1 -> 0.065 | L63: =L8/K8-1 -> 0.055 | ... O63: =O8/N8-1 -> 0.03
B64: =B9 -> Powertrain solutions (PTS) | E64: =E9/D9-1 -> 2.5919598 | F64: =F9/E9-1 -> 1.5 | G64: =G9/F9-1 -> 0.42 | H64: =H9/G9-1 -> 0.26 | I64: =I9/H9-1 -> 0.18 | J64: =J9/I9-1 -> 0.125 | K64: =K9/J9-1 -> 0.1 | L64: =L9/K9-1 -> 0.075 | ... O64: =O9/N9-1 -> 0.03
B65: =B10 -> Standard products | E65: =E10/D10-1 -> 0.2283237 | F65: =F10/E10-1 -> 0.1 | G65: =G10/F10-1 -> 0.08 | H65: =H10/G10-1 -> 0.06 | I65: =I10/H10-1 -> 0.05 | J65: =J10/I10-1 -> 0.04 | K65: =K10/J10-1 -> 0.04 | L65: =L10/K10-1 -> 0.035 | ... O65: =O10/N10-1 -> 0.03
B66: =B11 -> Services | E66: =E11/D11-1 -> 0.045774648 | F66: =F11/E11-1 -> 0.2 | G66: =G11/F11-1 -> 0.15 | H66: =H11/G11-1 -> 0.12 | I66: =I11/H11-1 -> 0.1 | J66: =J11/I11-1 -> 0.08 | K66: =K11/J11-1 -> 0.07 | L66: =L11/K11-1 -> 0.06 | ... O66: =O11/N11-1 -> 0.03
B67: Total revenue | D67: =D12/C12-1 -> 0.56036462 | E67: =E12/D12-1 -> 0.8853978 | F67: =F12/E12-1 -> 0.76137752 | G67: =G12/F12-1 -> 0.30612511 | H67: =H12/G12-1 -> 0.19678913 | I67: =I12/H12-1 -> 0.13768265 | J67: =J12/I12-1 -> 0.098578498 | K67: =K12/J12-1 -> 0.07995677 | ... O67: =O12/N12-1 -> 0.03
B68: EBITDA (GAAP) | E68: =E40/D40-1 -> 0.81853913 | F68: =F40/E40-1 -> 1.3520645 | G68: =G40/F40-1 -> 0.39395603 | H68: =H40/G40-1 -> 0.22296489 | I68: =I40/H40-1 -> 0.13485814 | J68: =J40/I40-1 -> 0.089397583 | K68: =K40/J40-1 -> 0.054873861 | L68: =L40/K40-1 -> 0.038989681 | ... O68: =O40/N40-1 -> 0.014018348
B69: Adj. EBITDA | D69: =D43/C43-1 -> 0.70564516 | E69: =E43/D43-1 -> 0.90839243 | F69: =F43/E43-1 -> 0.87856639 | G69: =G43/F43-1 -> 0.39105867 | H69: =H43/G43-1 -> 0.22215413 | I69: =I43/H43-1 -> 0.13494381 | J69: =J43/I43-1 -> 0.08967672 | K69: =K43/J43-1 -> 0.055642714 | ... O69: =O43/N43-1 -> 0.014554558
B70: Operating income | D70: =D20/C20-1 -> 2.9259239 | E70: =E20/D20-1 -> 1.5262539 | F70: =F20/E20-1 -> 1.9072736 | G70: =G20/F20-1 -> 0.42009968 | H70: =H20/G20-1 -> 0.24302635 | I70: =I20/H20-1 -> 0.14364162 | J70: =J20/I20-1 -> 0.09173192 | K70: =K20/J20-1 -> 0.054275576 | ... O70: =O20/N20-1 -> 0.010835767
B71: Net income | E71: =E30/D30-1 -> 5.0778975 | F71: =F30/E30-1 -> 2.4993509 | G71: =G30/F30-1 -> 0.46229152 | H71: =H30/G30-1 -> 0.27066806 | I71: =I30/H30-1 -> 0.16438114 | J71: =J30/I30-1 -> 0.11004941 | K71: =K30/J30-1 -> 0.071867575 | L71: =L30/K30-1 -> 0.054524378 | ... O71: =O30/N30-1 -> 0.028924482 | Q71: FY25 base is small ($17.4m) — growth optically large
B72: Diluted EPS | F72: =F36/E36-1 -> 2.4944896 | G72: =G36/F36-1 -> 0.46229152 | H72: =H36/G36-1 -> 0.27066806 | I72: =I36/H36-1 -> 0.16438114 | J72: =J36/I36-1 -> 0.11004941 | K72: =K36/J36-1 -> 0.071867575 | L72: =L36/K36-1 -> 0.054524378 | M72: =M36/L36-1 -> 0.039239519 | ... O72: =O36/N36-1 -> 0.028924482
D75: FY26A unlevered FCF (memo)
C76: EBIT | E76: =E20 -> 182.489 | Q76: GAAP EBIT still includes $64.2m of IPO one-offs
C77: Less: tax @ normalized rate | E77: =-E76*TaxRate -> -45.62225
C78: NOPAT | E78: =E76+E77 -> 136.86675
C79: Plus: D&A | E79: =E39 -> 66.9
C80: Less: capex | E80: =E44 -> -115.905
C81: Less: increase in NWC | E81: =-E53 -> -98.264
C82: Unlevered FCF | E82: =SUM(E78:E81) -> -10.40225

Sheet Bal_Sht
A1: ="Balance Sheet for "&Name -> Balance Sheet for Forgent Power Solutions, Inc.
A2: (Dollars in Millions unless stated)
C4: ="Historical — fiscal years ending "&TEXT(FYE,"mmmm d") -> Historical — fiscal years ending June 30 | F4: ="Projected — fiscal years ending "&TEXT(FYE,"mmmm d") -> Projected — fiscal years ending June 30
C5: n/a | D5: FY25A | E5: FY26A | F5: FY27E | G5: FY28E | H5: FY29E | I5: FY30E | J5: FY31E | K5: FY32E | L5: FY33E | M5: FY34E | N5: FY35E | O5: FY36E
B6: Assets
B7: Cash & equivalents | D7: 111.322 | E7: 97.477 | F7: =Cash_Flow!F41 -> 315.3934 | G7: =Cash_Flow!G41 -> 808.55722 | H7: =Cash_Flow!H41 -> 1456.6375 | I7: =Cash_Flow!I41 -> 2223.0785 | J7: =Cash_Flow!J41 -> 3084.7942 | K7: =Cash_Flow!K41 -> 4013.8262 | L7: =Cash_Flow!L41 -> 4990.5779 | M7: =Cash_Flow!M41 -> 6021.9767 | ... O7: =Cash_Flow!O41 -> 8216.0095 | Q7: 10-K balance sheets (XBRL, $000s / 1,000)
B8: Accounts receivable, net | D8: 159.97 | E8: 329.628 | F8: =Assumptions!F105/365*Inc_Stmt!F12 -> 582.48521 | G8: =Assumptions!G105/365*Inc_Stmt!G12 -> 760.79855 | H8: =Assumptions!H105/365*Inc_Stmt!H12 -> 910.51544 | I8: =Assumptions!I105/365*Inc_Stmt!I12 -> 1035.8776 | J8: =Assumptions!J105/365*Inc_Stmt!J12 -> 1137.9929 | K8: =Assumptions!K105/365*Inc_Stmt!K12 -> 1228.9831 | L8: =Assumptions!L105/365*Inc_Stmt!L12 -> 1307.2347 | M8: =Assumptions!M105/365*Inc_Stmt!M12 -> 1371.7566 | ... O8: =Assumptions!O105/365*Inc_Stmt!O12 -> 1468.7897
B9: Inventory, net | D9: 117.577 | E9: 249.817 | F9: =Assumptions!F110/365*-Inc_Stmt!F14 -> 434.19132 | G9: =Assumptions!G110/365*-Inc_Stmt!G14 -> 562.67766 | H9: =Assumptions!H110/365*-Inc_Stmt!H14 -> 670.22506 | I9: =Assumptions!I110/365*-Inc_Stmt!I14 -> 762.50342 | J9: =Assumptions!J110/365*-Inc_Stmt!J14 -> 840.32072 | K9: =Assumptions!K110/365*-Inc_Stmt!K14 -> 913.23567 | L9: =Assumptions!L110/365*-Inc_Stmt!L14 -> 977.47323 | M9: =Assumptions!M110/365*-Inc_Stmt!M14 -> 1032.1097 | ... O9: =Assumptions!O110/365*-Inc_Stmt!O14 -> 1115.3816
B10: Prepaid & other current (ex restricted cash) | D10: 56.278 | E10: 116.933 | F10: =Assumptions!F120*Inc_Stmt!F12 -> 205.10332 | G10: =Assumptions!G120*Inc_Stmt!G12 -> 267.8906 | H10: =Assumptions!H120*Inc_Stmt!H12 -> 320.60855 | I10: =Assumptions!I120*Inc_Stmt!I12 -> 364.75079 | J10: =Assumptions!J120*Inc_Stmt!J12 -> 400.70738 | K10: =Assumptions!K120*Inc_Stmt!K12 -> 432.74664 | L10: =Assumptions!L120*Inc_Stmt!L12 -> 460.30042 | M10: =Assumptions!M120*Inc_Stmt!M12 -> 483.01972 | ... O10: =Assumptions!O120*Inc_Stmt!O12 -> 517.18677 | Q10: Reported $141.2m less $24.2m TRA-restricted cash
B11: Restricted cash (TRA) | D11: 0 | E11: 24.236 | F11: =E11 -> 24.236 | G11: =F11 -> 24.236 | H11: =G11 -> 24.236 | I11: =H11 -> 24.236 | J11: =I11 -> 24.236 | K11: =J11 -> 24.236 | L11: =K11 -> 24.236 | M11: =L11 -> 24.236 | ... O11: =N11 -> 24.236
B12: Total current assets | D12: =SUM(D7:D11) -> 445.147 | E12: =SUM(E7:E11) -> 818.091 | F12: =SUM(F7:F11) -> 1561.4093 | G12: =SUM(G7:G11) -> 2424.16 | H12: =SUM(H7:H11) -> 3382.2226 | I12: =SUM(I7:I11) -> 4410.4464 | J12: =SUM(J7:J11) -> 5488.0511 | K12: =SUM(K7:K11) -> 6613.0276 | ... O12: =SUM(O7:O11) -> 11341.603
B14: Gross PP&E | D14: 115.52 | E14: 229.331 | F14: =E14-Inc_Stmt!F44 -> 316.3436 | G14: =F14-Inc_Stmt!G44 -> 355.5471 | H14: =G14-Inc_Stmt!H44 -> 406.37529 | I14: =H14-Inc_Stmt!I44 -> 468.64981 | J14: =I14-Inc_Stmt!J44 -> 541.94994 | K14: =J14-Inc_Stmt!K44 -> 623.9011 | L14: =K14-Inc_Stmt!L44 -> 724.43678 | M14: =L14-Inc_Stmt!M44 -> 826.26246 | ... O14: =N14-Inc_Stmt!O44 -> 1032.9764
B15: Accumulated depreciation | D15: -7.35 | E15: -24.374 | F15: =E15-Inc_Stmt!F37 -> -55.11755 | G15: =F15-Inc_Stmt!G37 -> -94.301457 | H15: =G15-Inc_Stmt!H37 -> -133.4883 | I15: =H15-Inc_Stmt!I37 -> -174.42135 | J15: =I15-Inc_Stmt!J37 -> -218.55562 | K15: =J15-Inc_Stmt!K37 -> -267.06477 | L15: =K15-Inc_Stmt!L37 -> -320.59022 | M15: =L15-Inc_Stmt!M37 -> -381.1672 | ... O15: =N15-Inc_Stmt!O37 -> -520.15763
B16: Net PP&E | D16: =D14+D15 -> 108.17 | E16: =E14+E15 -> 204.957 | F16: =F14+F15 -> 261.22605 | G16: =G14+G15 -> 261.24564 | H16: =H14+H15 -> 272.88698 | I16: =I14+I15 -> 294.22846 | J16: =J14+J15 -> 323.39432 | K16: =K14+K15 -> 356.83633 | ... O16: =O14+O15 -> 512.81881
B17: Operating lease ROU assets | D17: 117.769 | E17: 108.432 | F17: =E17 -> 108.432 | G17: =F17 -> 108.432 | H17: =G17 -> 108.432 | I17: =H17 -> 108.432 | J17: =I17 -> 108.432 | K17: =J17 -> 108.432 | L17: =K17 -> 108.432 | M17: =L17 -> 108.432 | ... O17: =N17 -> 108.432
B18: Goodwill | D18: 516.629 | E18: 516.629 | F18: =E18 -> 516.629 | G18: =F18 -> 516.629 | H18: =G18 -> 516.629 | I18: =H18 -> 516.629 | J18: =I18 -> 516.629 | K18: =J18 -> 516.629 | L18: =K18 -> 516.629 | M18: =L18 -> 516.629 | ... O18: =N18 -> 516.629
B19: Intangible assets, net | D19: 337.271 | E19: 289.49 | F19: =E19-Inc_Stmt!F38 -> 264.2 | G19: =F19-Inc_Stmt!G38 -> 239.146 | H19: =G19-Inc_Stmt!H38 -> 214.887 | I19: =H19-Inc_Stmt!I38 -> 192.044 | J19: =I19-Inc_Stmt!J38 -> 169.201 | K19: =J19-Inc_Stmt!K38 -> 146.358 | L19: =K19-Inc_Stmt!L38 -> 123.515 | M19: =L19-Inc_Stmt!M38 -> 100.672 | ... O19: =N19-Inc_Stmt!O38 -> 54.986
B20: Deferred tax assets, net | D20: 0 | E20: 280.971 | F20: =E20 -> 280.971 | G20: =F20 -> 280.971 | H20: =G20 -> 280.971 | I20: =H20 -> 280.971 | J20: =I20 -> 280.971 | K20: =J20 -> 280.971 | L20: =K20 -> 280.971 | M20: =L20 -> 280.971 | ... O20: =N20 -> 280.971
B21: Other long-term assets | D21: 11.7 | E21: 12.195 | F21: =E21 -> 12.195 | G21: =F21 -> 12.195 | H21: =G21 -> 12.195 | I21: =H21 -> 12.195 | J21: =I21 -> 12.195 | K21: =J21 -> 12.195 | L21: =K21 -> 12.195 | M21: =L21 -> 12.195 | ... O21: =N21 -> 12.195
B22: Total assets | D22: =D12+D16+SUM(D17:D21) -> 1536.686 | E22: =E12+E16+SUM(E17:E21) -> 2230.765 | F22: =F12+F16+SUM(F17:F21) -> 3005.0623 | G22: =G12+G16+SUM(G17:G21) -> 3842.7787 | H22: =H12+H16+SUM(H17:H21) -> 4788.2236 | I22: =I12+I16+SUM(I17:I21) -> 5814.9458 | J22: =J12+J16+SUM(J17:J21) -> 6898.8735 | K22: =K12+K16+SUM(K17:K21) -> 8034.4489 | ... O22: =O12+O16+SUM(O17:O21) -> 12827.635
B24: Liabilities & equity
B25: Accounts payable | D25: 61.943 | E25: 130.453 | F25: =Assumptions!F115/365*-Inc_Stmt!F14 -> 228.06009 | G25: =Assumptions!G115/365*-Inc_Stmt!G14 -> 295.54786 | H25: =Assumptions!H115/365*-Inc_Stmt!H14 -> 352.03741 | I25: =Assumptions!I115/365*-Inc_Stmt!I14 -> 400.50685 | J25: =Assumptions!J115/365*-Inc_Stmt!J14 -> 441.38058 | K25: =Assumptions!K115/365*-Inc_Stmt!K14 -> 479.67934 | L25: =Assumptions!L115/365*-Inc_Stmt!L14 -> 513.42028 | M25: =Assumptions!M115/365*-Inc_Stmt!M14 -> 542.11822 | ... O25: =Assumptions!O115/365*-Inc_Stmt!O14 -> 585.857
B26: Accrued expenses | D26: 79.541 | E26: 122.356 | F26: =Assumptions!F125*Inc_Stmt!F12 -> 212.6071 | G26: =Assumptions!G125*Inc_Stmt!G12 -> 277.69147 | H26: =Assumptions!H125*Inc_Stmt!H12 -> 332.33814 | I26: =Assumptions!I125*Inc_Stmt!I12 -> 378.09533 | J26: =Assumptions!J125*Inc_Stmt!J12 -> 415.3674 | K26: =Assumptions!K125*Inc_Stmt!K12 -> 448.57884 | L26: =Assumptions!L125*Inc_Stmt!L12 -> 477.14067 | M26: =Assumptions!M125*Inc_Stmt!M12 -> 500.69117 | ... O26: =Assumptions!O125*Inc_Stmt!O12 -> 536.10823
B27: Payables pursuant to acquisitions | D27: 17.226 | E27: 0 | F27: 0 | G27: 0 | H27: 0 | I27: 0 | J27: 0 | K27: 0 | L27: 0 | M27: 0 | N27: 0 | O27: 0
B28: Customer deposits / deferred revenue | D28: 110.895 | E28: 263.859 | F28: =Assumptions!F130*Inc_Stmt!F12 -> 465.23436 | G28: =Assumptions!G130*Inc_Stmt!G12 -> 607.65428 | H28: =Assumptions!H130*Inc_Stmt!H12 -> 727.23404 | I28: =Assumptions!I130*Inc_Stmt!I12 -> 827.36155 | J28: =Assumptions!J130*Inc_Stmt!J12 -> 908.92161 | K28: =Assumptions!K130*Inc_Stmt!K12 -> 981.59604 | L28: =Assumptions!L130*Inc_Stmt!L12 -> 1044.0961 | M28: =Assumptions!M130*Inc_Stmt!M12 -> 1095.6301 | ... O28: =Assumptions!O130*Inc_Stmt!O12 -> 1173.131
B29: Operating lease liabilities, current | D29: 6.879 | E29: 8.626 | F29: =E29 -> 8.626 | G29: =F29 -> 8.626 | H29: =G29 -> 8.626 | I29: =H29 -> 8.626 | J29: =I29 -> 8.626 | K29: =J29 -> 8.626 | L29: =K29 -> 8.626 | M29: =L29 -> 8.626 | ... O29: =N29 -> 8.626
B30: Current portion of long-term debt | D30: 5.173 | E30: 6 | F30: =MIN(TLAmort,Capitalization!F18) -> 6 | G30: =MIN(TLAmort,Capitalization!G18) -> 6 | H30: =MIN(TLAmort,Capitalization!H18) -> 6 | I30: =MIN(TLAmort,Capitalization!I18) -> 6 | J30: =MIN(TLAmort,Capitalization!J18) -> 6 | K30: =MIN(TLAmort,Capitalization!K18) -> 6 | L30: =MIN(TLAmort,Capitalization!L18) -> 6 | M30: =MIN(TLAmort,Capitalization!M18) -> 6 | ... O30: =MIN(TLAmort,Capitalization!O18) -> 6
B31: Total current liabilities | D31: =SUM(D25:D30) -> 281.657 | E31: =SUM(E25:E30) -> 531.294 | F31: =SUM(F25:F30) -> 920.52755 | G31: =SUM(G25:G30) -> 1195.5196 | H31: =SUM(H25:H30) -> 1426.2356 | I31: =SUM(I25:I30) -> 1620.5897 | J31: =SUM(J25:J30) -> 1780.2956 | K31: =SUM(K25:K30) -> 1924.4802 | ... O31: =SUM(O25:O30) -> 2309.7222
B32: Long-term debt, net of discount | D32: 496.934 | E32: 576.175 | F32: =E30+E32-Capitalization!F17-F30 -> 570.175 | G32: =F30+F32-Capitalization!G17-G30 -> 564.175 | H32: =G30+G32-Capitalization!H17-H30 -> 558.175 | I32: =H30+H32-Capitalization!I17-I30 -> 552.175 | J32: =I30+I32-Capitalization!J17-J30 -> 546.175 | K32: =J30+J32-Capitalization!K17-K30 -> 540.175 | L32: =K30+K32-Capitalization!L17-L30 -> 534.175 | M32: =L30+L32-Capitalization!M17-M30 -> 528.175 | ... O32: =N30+N32-Capitalization!O17-O30 -> 516.175 | Q32: Carrying value: OID/fees ($16.3m) held flat; interest computed on principal
B33: Tax receivable agreement liability | D33: 0 | E33: 338.925 | F33: =E33 -> 338.925 | G33: =F33 -> 338.925 | H33: =G33 -> 338.925 | I33: =H33 -> 338.925 | J33: =I33 -> 338.925 | K33: =J33 -> 338.925 | L33: =K33 -> 338.925 | M33: =L33 -> 338.925 | ... O33: =N33 -> 338.925
B34: Deferred tax liabilities | D34: 63.318 | E34: 0 | F34: =E34 -> 0 | G34: =F34 -> 0 | H34: =G34 -> 0 | I34: =H34 -> 0 | J34: =I34 -> 0 | K34: =J34 -> 0 | L34: =K34 -> 0 | M34: =L34 -> 0 | ... O34: =N34 -> 0
B35: Operating lease liabilities, non-current | D35: 121.491 | E35: 112.97 | F35: =E35 -> 112.97 | G35: =F35 -> 112.97 | H35: =G35 -> 112.97 | I35: =H35 -> 112.97 | J35: =I35 -> 112.97 | K35: =J35 -> 112.97 | L35: =K35 -> 112.97 | M35: =L35 -> 112.97 | ... O35: =N35 -> 112.97
B36: Total liabilities | D36: =D31+SUM(D32:D35) -> 963.4 | E36: =E31+SUM(E32:E35) -> 1559.364 | F36: =F31+SUM(F32:F35) -> 1942.5975 | G36: =G31+SUM(G32:G35) -> 2211.5896 | H36: =H31+SUM(H32:H35) -> 2436.3056 | I36: =I31+SUM(I32:I35) -> 2624.6597 | J36: =J31+SUM(J32:J35) -> 2778.3656 | K36: =K31+SUM(K32:K35) -> 2916.5502 | ... O36: =O31+SUM(O32:O35) -> 3277.7922
B38: Total equity (incl. NCI) | D38: 573.286 | E38: 671.401 | F38: =E38+Inc_Stmt!F30+Inc_Stmt!F41 -> 1062.4648 | G38: =F38+Inc_Stmt!G30+Inc_Stmt!G41 -> 1631.1891 | H38: =G38+Inc_Stmt!H30+Inc_Stmt!H41 -> 2351.918 | I38: =H38+Inc_Stmt!I30+Inc_Stmt!I41 -> 3190.2861 | J38: =I38+Inc_Stmt!J30+Inc_Stmt!J41 -> 4120.5079 | K38: =J38+Inc_Stmt!K30+Inc_Stmt!K41 -> 5117.8987 | L38: =K38+Inc_Stmt!L30+Inc_Stmt!L41 -> 6170.0578 | M38: =L38+Inc_Stmt!M30+Inc_Stmt!M41 -> 7263.9575 | ... O38: =N38+Inc_Stmt!O30+Inc_Stmt!O41 -> 9549.8431 | Q38: Roll-forward: + net income + SBC (no dividends / buybacks / TRA payments modeled)
B40: Total liabilities & equity | D40: =D36+D38 -> 1536.686 | E40: =E36+E38 -> 2230.765 | F40: =F36+F38 -> 3005.0623 | G40: =G36+G38 -> 3842.7787 | H40: =H36+H38 -> 4788.2236 | I40: =I36+I38 -> 5814.9458 | J40: =J36+J38 -> 6898.8735 | K40: =K36+K38 -> 8034.4489 | ... O40: =O36+O38 -> 12827.635
B42: Balance check (assets − L&E) | D42: =ROUND(D22-D40,3) -> 0 | E42: =ROUND(E22-E40,3) -> 0 | F42: =ROUND(F22-F40,3) -> 0 | G42: =ROUND(G22-G40,3) -> 0 | H42: =ROUND(H22-H40,3) -> 0 | I42: =ROUND(I22-I40,3) -> 0 | J42: =ROUND(J22-J40,3) -> 0 | K42: =ROUND(K22-K40,3) -> 0 | ... O42: =ROUND(O22-O40,3) -> 0

Sheet Cash_Flow
A1: ="Cash Flow Statement for "&Name -> Cash Flow Statement for Forgent Power Solutions, Inc.
A2: (Dollars in Millions unless stated)
C4: ="Historical — fiscal years ending "&TEXT(FYE,"mmmm d") -> Historical — fiscal years ending June 30 | F4: ="Projected — fiscal years ending "&TEXT(FYE,"mmmm d") -> Projected — fiscal years ending June 30
C5: n/a | D5: FY25A | E5: FY26A | F5: FY27E | G5: FY28E | H5: FY29E | I5: FY30E | J5: FY31E | K5: FY32E | L5: FY33E | M5: FY34E | N5: FY35E | O5: FY36E
B6: Cash flow from operations
B7: Net income (incl. NCI) | D7: 17.446 | E7: 106.035 | F7: =Inc_Stmt!F30 -> 371.05367 | G7: =Inc_Stmt!G30 -> 542.58864 | H7: =Inc_Stmt!H30 -> 689.45005 | I7: =Inc_Stmt!I30 -> 802.78264 | J7: =Inc_Stmt!J30 -> 891.1284 | K7: =Inc_Stmt!K30 -> 955.17163 | L7: =Inc_Stmt!L30 -> 1007.2518 | M7: =Inc_Stmt!M30 -> 1046.7758 | ... O7: =Inc_Stmt!O30 -> 1108.8054 | Q7: 10-K cash flow statement (XBRL)
B8: Depreciation & amortization | D8: 64.864 | E8: 66.899 | F8: =Inc_Stmt!F39 -> 56.03355 | G8: =Inc_Stmt!G39 -> 64.237907 | H8: =Inc_Stmt!H39 -> 63.445847 | I8: =Inc_Stmt!I39 -> 63.776047 | J8: =Inc_Stmt!J39 -> 66.977269 | K8: =Inc_Stmt!K39 -> 71.352148 | L8: =Inc_Stmt!L39 -> 76.368449 | M8: =Inc_Stmt!M39 -> 83.419984 | ... O8: =Inc_Stmt!O39 -> 95.069136
B9: Amortization / write-off of debt costs | D9: 2.511 | E9: 12.987 | F9: 0 | G9: 0 | H9: 0 | I9: 0 | J9: 0 | K9: 0 | L9: 0 | M9: 0 | N9: 0 | O9: 0
B10: Deferred income taxes | D10: -15.733 | E10: 14.635 | F10: 0 | G10: 0 | H10: 0 | I10: 0 | J10: 0 | K10: 0 | L10: 0 | M10: 0 | N10: 0 | O10: 0
B11: Stock-based compensation | D11: 1.784 | E11: 10.036 | F11: =Inc_Stmt!F41 -> 20.01008 | G11: =Inc_Stmt!G41 -> 26.135668 | H11: =Inc_Stmt!H41 -> 31.278883 | I11: =Inc_Stmt!I41 -> 35.585443 | J11: =Inc_Stmt!J41 -> 39.093403 | K11: =Inc_Stmt!K41 -> 42.219185 | L11: =Inc_Stmt!L41 -> 44.907358 | M11: =Inc_Stmt!M41 -> 47.123875 | ... O11: =Inc_Stmt!O41 -> 50.457245
B12: Other non-cash items | D12: 8.153 | E12: 23.005 | F12: 0 | G12: 0 | H12: 0 | I12: 0 | J12: 0 | K12: 0 | L12: 0 | M12: 0 | N12: 0 | O12: 0 | Q12: Derived: reported CFO less all other listed lines (credit loss, inventory provisions, ROU amortization)
B14: (Increase) / decrease in A/R | D14: -78.51 | E14: -172.657 | F14: =-(Bal_Sht!F8-Bal_Sht!E8) -> -252.85721 | G14: =-(Bal_Sht!G8-Bal_Sht!F8) -> -178.31335 | H14: =-(Bal_Sht!H8-Bal_Sht!G8) -> -149.71689 | I14: =-(Bal_Sht!I8-Bal_Sht!H8) -> -125.36218 | J14: =-(Bal_Sht!J8-Bal_Sht!I8) -> -102.11526 | K14: =-(Bal_Sht!K8-Bal_Sht!J8) -> -90.990235 | L14: =-(Bal_Sht!L8-Bal_Sht!K8) -> -78.251609 | M14: =-(Bal_Sht!M8-Bal_Sht!L8) -> -64.521902 | ... O14: =-(Bal_Sht!O8-Bal_Sht!N8) -> -42.780282
B15: (Increase) / decrease in inventory | D15: -34.47 | E15: -142.909 | F15: =-(Bal_Sht!F9-Bal_Sht!E9) -> -184.37432 | G15: =-(Bal_Sht!G9-Bal_Sht!F9) -> -128.48634 | H15: =-(Bal_Sht!H9-Bal_Sht!G9) -> -107.5474 | I15: =-(Bal_Sht!I9-Bal_Sht!H9) -> -92.278364 | J15: =-(Bal_Sht!J9-Bal_Sht!I9) -> -77.817296 | K15: =-(Bal_Sht!K9-Bal_Sht!J9) -> -72.914946 | L15: =-(Bal_Sht!L9-Bal_Sht!K9) -> -64.237565 | M15: =-(Bal_Sht!M9-Bal_Sht!L9) -> -54.636455 | ... O15: =-(Bal_Sht!O9-Bal_Sht!N9) -> -35.808606
B16: (Increase) / decrease in prepaid & other | D16: -18.493 | E16: -66.465 | F16: =-(Bal_Sht!F10-Bal_Sht!E10) -> -88.17032 | G16: =-(Bal_Sht!G10-Bal_Sht!F10) -> -62.787277 | H16: =-(Bal_Sht!H10-Bal_Sht!G10) -> -52.717957 | I16: =-(Bal_Sht!I10-Bal_Sht!H10) -> -44.142236 | J16: =-(Bal_Sht!J10-Bal_Sht!I10) -> -35.956585 | K16: =-(Bal_Sht!K10-Bal_Sht!J10) -> -32.039267 | L16: =-(Bal_Sht!L10-Bal_Sht!K10) -> -27.553772 | M16: =-(Bal_Sht!M10-Bal_Sht!L10) -> -22.7193 | ... O16: =-(Bal_Sht!O10-Bal_Sht!N10) -> -15.063692
B17: Increase / (decrease) in A/P | D17: 35.183 | E17: 68.51 | F17: =Bal_Sht!F25-Bal_Sht!E25 -> 97.60709 | G17: =Bal_Sht!G25-Bal_Sht!F25 -> 67.487772 | H17: =Bal_Sht!H25-Bal_Sht!G25 -> 56.489543 | I17: =Bal_Sht!I25-Bal_Sht!H25 -> 48.469444 | J17: =Bal_Sht!J25-Bal_Sht!I25 -> 40.873731 | K17: =Bal_Sht!K25-Bal_Sht!J25 -> 38.298759 | L17: =Bal_Sht!L25-Bal_Sht!K25 -> 33.740943 | M17: =Bal_Sht!M25-Bal_Sht!L25 -> 28.697936 | ... O17: =Bal_Sht!O25-Bal_Sht!N25 -> 18.808561
B18: Increase / (decrease) in accrued expenses | D18: 44.481 | E18: 42.815 | F18: =Bal_Sht!F26-Bal_Sht!E26 -> 90.2511 | G18: =Bal_Sht!G26-Bal_Sht!F26 -> 65.084372 | H18: =Bal_Sht!H26-Bal_Sht!G26 -> 54.646663 | I18: =Bal_Sht!I26-Bal_Sht!H26 -> 45.757196 | J18: =Bal_Sht!J26-Bal_Sht!I26 -> 37.27207 | K18: =Bal_Sht!K26-Bal_Sht!J26 -> 33.211436 | L18: =Bal_Sht!L26-Bal_Sht!K26 -> 28.561837 | M18: =Bal_Sht!M26-Bal_Sht!L26 -> 23.550494 | ... O18: =Bal_Sht!O26-Bal_Sht!N26 -> 15.614803
B19: Increase / (decrease) in customer deposits | D19: 20.747 | E19: 152.964 | F19: =Bal_Sht!F28-Bal_Sht!E28 -> 201.37536 | G19: =Bal_Sht!G28-Bal_Sht!F28 -> 142.41992 | H19: =Bal_Sht!H28-Bal_Sht!G28 -> 119.57976 | I19: =Bal_Sht!I28-Bal_Sht!H28 -> 100.12751 | J19: =Bal_Sht!J28-Bal_Sht!I28 -> 81.560059 | K19: =Bal_Sht!K28-Bal_Sht!J28 -> 72.674436 | L19: =Bal_Sht!L28-Bal_Sht!K28 -> 62.50002 | M19: =Bal_Sht!M28-Bal_Sht!L28 -> 51.534023 | ... O19: =Bal_Sht!O28-Bal_Sht!N28 -> 34.168863
B20: Operating lease & other | D20: -2.941 | E20: -6.774 | F20: =(Bal_Sht!F29-Bal_Sht!E29)+(Bal_Sht!F35-Bal_Sht!E35)-(Bal_Sht!F17-Bal_Sht!E17) -> 0 | G20: =(Bal_Sht!G29-Bal_Sht!F29)+(Bal_Sht!G35-Bal_Sht!F35)-(Bal_Sht!G17-Bal_Sht!F17) -> 0 | H20: =(Bal_Sht!H29-Bal_Sht!G29)+(Bal_Sht!H35-Bal_Sht!G35)-(Bal_Sht!H17-Bal_Sht!G17) -> 0 | I20: =(Bal_Sht!I29-Bal_Sht!H29)+(Bal_Sht!I35-Bal_Sht!H35)-(Bal_Sht!I17-Bal_Sht!H17) -> 0 | J20: =(Bal_Sht!J29-Bal_Sht!I29)+(Bal_Sht!J35-Bal_Sht!I35)-(Bal_Sht!J17-Bal_Sht!I17) -> 0 | K20: =(Bal_Sht!K29-Bal_Sht!J29)+(Bal_Sht!K35-Bal_Sht!J35)-(Bal_Sht!K17-Bal_Sht!J17) -> 0 | L20: =(Bal_Sht!L29-Bal_Sht!K29)+(Bal_Sht!L35-Bal_Sht!K35)-(Bal_Sht!L17-Bal_Sht!K17) -> 0 | M20: =(Bal_Sht!M29-Bal_Sht!L29)+(Bal_Sht!M35-Bal_Sht!L35)-(Bal_Sht!M17-Bal_Sht!L17) -> 0 | ... O20: =(Bal_Sht!O29-Bal_Sht!N29)+(Bal_Sht!O35-Bal_Sht!N35)-(Bal_Sht!O17-Bal_Sht!N17) -> 0
B21: Total change in working capital | D21: =SUM(D14:D20) -> -34.003 | E21: =SUM(E14:E20) -> -124.516 | F21: =SUM(F14:F20) -> -136.1683 | G21: =SUM(G14:G20) -> -94.594896 | H21: =SUM(H14:H20) -> -79.266279 | I21: =SUM(I14:I20) -> -67.42863 | J21: =SUM(J14:J20) -> -56.183281 | K21: =SUM(K14:K20) -> -51.759817 | ... O21: =SUM(O14:O20) -> -25.060354
B23: Cash from operations | D23: =SUM(D7:D12)+D21 -> 45.022 | E23: =SUM(E7:E12)+E21 -> 109.081 | F23: =SUM(F7:F12)+F21 -> 310.929 | G23: =SUM(G7:G12)+G21 -> 538.36732 | H23: =SUM(H7:H12)+H21 -> 704.9085 | I23: =SUM(I7:I12)+I21 -> 834.7155 | J23: =SUM(J7:J12)+J21 -> 941.01579 | K23: =SUM(K7:K12)+K21 -> 1016.9831 | ... O23: =SUM(O7:O12)+O21 -> 1229.2714
B24: Cash flow from investing
B25: Capital expenditures | D25: -84.115 | E25: -115.905 | F25: =Inc_Stmt!F44 -> -87.0126 | G25: =Inc_Stmt!G44 -> -39.203502 | H25: =Inc_Stmt!H44 -> -50.828185 | I25: =Inc_Stmt!I44 -> -62.274525 | J25: =Inc_Stmt!J44 -> -73.30013 | K25: =Inc_Stmt!K44 -> -81.951156 | L25: =Inc_Stmt!L44 -> -100.53568 | M25: =Inc_Stmt!M44 -> -101.82568 | ... O25: =Inc_Stmt!O44 -> -103.53737
B26: Acquisitions | D26: 0 | E26: 0 | F26: 0 | G26: 0 | H26: 0 | I26: 0 | J26: 0 | K26: 0 | L26: 0 | M26: 0 | N26: 0 | O26: 0
B27: Cash from investing | D27: =SUM(D25:D26) -> -84.115 | E27: =SUM(E25:E26) -> -115.905 | F27: =SUM(F25:F26) -> -87.0126 | G27: =SUM(G25:G26) -> -39.203502 | H27: =SUM(H25:H26) -> -50.828185 | I27: =SUM(I25:I26) -> -62.274525 | J27: =SUM(J25:J26) -> -73.30013 | K27: =SUM(K25:K26) -> -81.951156 | ... O27: =SUM(O25:O26) -> -103.53737
B28: Cash flow from financing
B29: Debt issued | D29: 0 | E29: 594 | F29: 0 | G29: 0 | H29: 0 | I29: 0 | J29: 0 | K29: 0 | L29: 0 | M29: 0 | N29: 0 | O29: 0
B30: Debt repaid | D30: -5.173 | E30: -512.61 | F30: =-Capitalization!F17 -> -6 | G30: =-Capitalization!G17 -> -6 | H30: =-Capitalization!H17 -> -6 | I30: =-Capitalization!I17 -> -6 | J30: =-Capitalization!J17 -> -6 | K30: =-Capitalization!K17 -> -6 | L30: =-Capitalization!L17 -> -6 | M30: =-Capitalization!M17 -> -6 | ... O30: =-Capitalization!O17 -> -6
B31: IPO / follow-on proceeds, net (primary) | D31: 0 | E31: 1524.9 | F31: 0 | G31: 0 | H31: 0 | I31: 0 | J31: 0 | K31: 0 | L31: 0 | M31: 0 | N31: 0 | O31: 0 | Q31: IPO $491.8m + Mar/Jun follow-ons $1,033.1m — 100% used to buy Opco units (no cash to FPS)
B32: Purchase of Opco units from Neos (use of proceeds) | D32: 0 | E32: -1524.9 | F32: 0 | G32: 0 | H32: 0 | I32: 0 | J32: 0 | K32: 0 | L32: 0 | M32: 0 | N32: 0 | O32: 0
B33: Distributions to members / NCI | D33: -13.269 | E33: -1.44 | F33: 0 | G33: 0 | H33: 0 | I33: 0 | J33: 0 | K33: 0 | L33: 0 | M33: 0 | N33: 0 | O33: 0
B34: Other financing (debt costs, earnout, offering costs, tax distr.) | D34: -17.539 | E34: -62.735 | F34: 0 | G34: 0 | H34: 0 | I34: 0 | J34: 0 | K34: 0 | L34: 0 | M34: 0 | N34: 0 | O34: 0 | Q34: FY26: financing costs 13.5, earnout 17.2, offering costs 23.5, tax distributions ~8.6
B35: Cash from financing | D35: =SUM(D29:D34) -> -35.981 | E35: =SUM(E29:E34) -> 17.215 | F35: =SUM(F29:F34) -> -6 | G35: =SUM(G29:G34) -> -6 | H35: =SUM(H29:H34) -> -6 | I35: =SUM(I29:I34) -> -6 | J35: =SUM(J29:J34) -> -6 | K35: =SUM(K29:K34) -> -6 | ... O35: =SUM(O29:O34) -> -6
B37: Net change in cash & restricted cash | D37: =D23+D27+D35 -> -75.074 | E37: =E23+E27+E35 -> 10.391 | F37: =F23+F27+F35 -> 217.9164 | G37: =G23+G27+G35 -> 493.16382 | H37: =H23+H27+H35 -> 648.08032 | I37: =I23+I27+I35 -> 766.44097 | J37: =J23+J27+J35 -> 861.71566 | K37: =K23+K27+K35 -> 929.03199 | ... O37: =O23+O27+O35 -> 1119.734
B38: Beginning cash & restricted cash | D38: 186.396 | E38: =D39 -> 111.322 | F38: =E39 -> 121.713 | G38: =F39 -> 339.6294 | H38: =G39 -> 832.79322 | I38: =H39 -> 1480.8735 | J38: =I39 -> 2247.3145 | K38: =J39 -> 3109.0302 | L38: =K39 -> 4038.0622 | ... O38: =N39 -> 7120.5114 | Q38: FY25 beginning = FY25 ending $111.3m + $75.1m decrease
B39: Ending cash & restricted cash | D39: =D38+D37 -> 111.322 | E39: =E38+E37 -> 121.713 | F39: =F38+F37 -> 339.6294 | G39: =G38+G37 -> 832.79322 | H39: =H38+H37 -> 1480.8735 | I39: =I38+I37 -> 2247.3145 | J39: =J38+J37 -> 3109.0302 | K39: =K38+K37 -> 4038.0622 | ... O39: =O38+O37 -> 8240.2455
B40: Less: restricted cash (TRA) | D40: =-Bal_Sht!D11 -> 0 | E40: =-Bal_Sht!E11 -> -24.236 | F40: =-Bal_Sht!F11 -> -24.236 | G40: =-Bal_Sht!G11 -> -24.236 | H40: =-Bal_Sht!H11 -> -24.236 | I40: =-Bal_Sht!I11 -> -24.236 | J40: =-Bal_Sht!J11 -> -24.236 | K40: =-Bal_Sht!K11 -> -24.236 | ... O40: =-Bal_Sht!O11 -> -24.236
B41: Ending cash & equivalents (to balance sheet) | D41: =D39+D40 -> 111.322 | E41: =E39+E40 -> 97.477 | F41: =F39+F40 -> 315.3934 | G41: =G39+G40 -> 808.55722 | H41: =H39+H40 -> 1456.6375 | I41: =I39+I40 -> 2223.0785 | J41: =J39+J40 -> 3084.7942 | K41: =K39+K40 -> 4013.8262 | ... O41: =O39+O40 -> 8216.0095
B43: Supplemental
B44: Cash interest paid | D44: 54.605 | E44: 48.163 | F44: =-Inc_Stmt!F22 -> 38.24415 | G44: =-Inc_Stmt!G22 -> 37.86075 | H44: =-Inc_Stmt!H22 -> 37.47735 | I44: =-Inc_Stmt!I22 -> 37.09395 | J44: =-Inc_Stmt!J22 -> 36.71055 | K44: =-Inc_Stmt!K22 -> 36.32715 | L44: =-Inc_Stmt!L22 -> 35.94375 | M44: =-Inc_Stmt!M22 -> 35.56035 | ... O44: =-Inc_Stmt!O22 -> 34.79355
B45: Cash taxes paid | D45: 7.392 | E45: 13.687 | F45: =-Inc_Stmt!F28 -> 123.68456 | G45: =-Inc_Stmt!G28 -> 180.86288 | H45: =-Inc_Stmt!H28 -> 229.81668 | I45: =-Inc_Stmt!I28 -> 267.59421 | J45: =-Inc_Stmt!J28 -> 297.0428 | K45: =-Inc_Stmt!K28 -> 318.39054 | L45: =-Inc_Stmt!L28 -> 335.75059 | M45: =-Inc_Stmt!M28 -> 348.92528 | ... O45: =-Inc_Stmt!O28 -> 369.60179
B46: Levered free cash flow (CFO + capex) | D46: =D23+D25 -> -39.093 | E46: =E23+E25 -> -6.824 | F46: =F23+F25 -> 223.9164 | G46: =G23+G25 -> 499.16382 | H46: =H23+H25 -> 654.08032 | I46: =I23+I25 -> 772.44097 | J46: =J23+J25 -> 867.71566 | K46: =K23+K25 -> 935.03199 | ... O46: =O23+O25 -> 1125.734
B47: Unlevered free cash flow (DCF) | E47: =Inc_Stmt!E82 -> -10.40225 | F47: =DCF!F17 -> 230.76174 | G47: =DCF!G17 -> 495.51009 | H47: =DCF!H17 -> 635.749 | I47: =DCF!I17 -> 737.36404 | J47: =DCF!J17 -> 814.47244 | K47: =DCF!K17 -> 862.21828 | L47: =DCF!L17 -> 889.54297 | M47: =DCF!M17 -> 923.37187 | ... O47: =DCF!O17 -> 968.31679

Sheet WACC
A1: ="WACC Calculation for "&Name -> WACC Calculation for Forgent Power Solutions, Inc.
A2: (Dollars in Millions unless stated)
B3: WACC Calculation
B4: Cost of equity
B5: Risk-free rate (10Y UST) | D5: 0.0517 | F5: US Treasury daily par yield, 9/25/2026 (FRED DGS10 5.18% on 9/24)
B6: Equity risk premium | D6: 0.0414 | F6: Damodaran implied ERP, 9/1/2026 update (computed vs 4.75% Rf — rates rose since; see note)
B7: =Ticker&" beta (relevered peer median)" -> FPS beta (relevered peer median) | D7: =beta -> 1.1673281
B8: Size / company-specific premium | D8: 0
B9: Cost of equity | D9: =D5+D6*D7+D8 -> 0.10002738
B11: Cost of debt
B12: Pre-tax cost of debt (WACD) | D12: =Kd -> 0.0639
B13: Tax rate | D13: =TaxRate -> 0.25
B14: After-tax cost of debt | D14: =D12*(1-D13) -> 0.047925
B16: Capital structure (market value)
B17: Equity value | D17: =marketcap -> 11863.594
B18: Debt | D18: =totaldebt -> 598.5
B19: E / V | D19: =D17/SUM(D17:D18) -> 0.95197436
B20: D / V | D20: =D18/SUM(D17:D18) -> 0.048025638
B21: D / E | D21: =D18/D17 -> 0.050448457
B23: WACC | D23: =D9*D19+D14*D20 -> 0.097525133
B26: Peer beta relevering
B27: Company | C27: Levered β | D27: Market cap | E27: Total debt | F27: D / E | G27: Tax | H27: Unlevered β
B28: Eaton (ETN) | C28: 1.17 | D28: ='Financial Data'!F8 -> 170888.23 | E28: ='Financial Data'!G8 -> 21326 | F28: =E28/D28 -> 0.12479502 | G28: =TaxRate -> 0.25 | H28: =C28/(1+(1-G28)*F28) -> 1.0698647 | I28: Levered β: StockAnalysis 'Beta (5Y)' vs S&P 500, as of 9/25/2026 (Finviz within ±0.05)
B29: Vertiv (VRT) | C29: 2.07 | D29: ='Financial Data'!F9 -> 97510.267 | E29: ='Financial Data'!G9 -> 3338 | F29: =E29/D29 -> 0.034232293 | G29: =TaxRate -> 0.25 | H29: =C29/(1+(1-G29)*F29) -> 2.0181847
B30: Hubbell (HUBB) | C30: 0.89 | D30: ='Financial Data'!F10 -> 24651.535 | E30: ='Financial Data'!G10 -> 5557 | F30: =E30/D30 -> 0.22542207 | G30: =TaxRate -> 0.25 | H30: =C30/(1+(1-G30)*F30) -> 0.76129113
B31: nVent (NVT) | C31: 1.35 | D31: ='Financial Data'!F11 -> 26611.403 | E31: ='Financial Data'!G11 -> 1633 | F31: =E31/D31 -> 0.061364672 | G31: =TaxRate -> 0.25 | H31: =C31/(1+(1-G31)*F31) -> 1.290602
B32: GE Vernova (GEV) | C32: 0.97 | D32: ='Financial Data'!F12 -> 255045.6 | E32: ='Financial Data'!G12 -> 3720 | F32: =E32/D32 -> 0.014585627 | G32: =TaxRate -> 0.25 | H32: =C32/(1+(1-G32)*F32) -> 0.95950378 | I32: GEV: ~2.5 yrs of trading history
B33: Powell Industries (POWL) | C33: 1.18 | D33: ='Financial Data'!F13 -> 6904.5779 | E33: ='Financial Data'!G13 -> 2.52 | F33: =E33/D33 -> 0.00036497524 | G33: =TaxRate -> 0.25 | H33: =C33/(1+(1-G33)*F33) -> 1.1796771
B34: Median unlevered beta | H34: =MEDIAN(H28:H33) -> 1.1247709
B35: =Ticker&" target D / E" -> FPS target D / E | H35: =D21 -> 0.050448457
B36: Relevered beta | D36: =H34*(1+(1-TaxRate)*H35) -> 1.1673281
B38: Note: Damodaran's 4.14% implied ERP was computed against a 4.75% Rf; the 10Y has since risen to 5.17%. Pairing them mixes dates — flex D6 (e.g., 4.5%) to test.

Sheet Capitalization
A1: ="Debt Capitalization for "&Name -> Debt Capitalization for Forgent Power Solutions, Inc.
A2: (Dollars in Millions unless stated)
B4: Debt instrument | D4: Amount | F4: Maturity | H4: Rate | I4: Wtd. rate
B5: Term Loan B (Term SOFR + 2.25%) | D5: 598.5 | F5: 48567 | H5: 0.0639 | I5: =IF(CapDebt=0,0,D5/CapDebt*H5) -> 0.0639 | K5: 10-K Note 10: $598.5m principal, matures 12/19/2032, effective rate 6.39% at 6/30/26 (repriced 6/23/26)
B6: Revolver ($250m commitment, undrawn) | D6: 0 | F6: 47836 | H6: 0.0639 | I6: =IF(CapDebt=0,0,D6/CapDebt*H6) -> 0 | K6: 10-K Note 10: $246.4m available at 6/30/26 (LCs outstanding)
B8: Total debt | D8: =SUM(D5:D6) -> 598.5 | F8: WACD | H8: =SUM(I5:I6) -> 0.0639
B10: Memo — excluded from debt
B11: Operating lease liabilities | D11: 121.596 | K11: US GAAP operating lease cost sits inside EBITDA/EBIT, so leases are NOT treated as debt (avoids double count)
B12: TRA liability (in bridge, net of DTA & restricted cash) | D12: =TRA -> 338.925
B13: Mandatory amortization ($MM / yr) | D13: 6 | K13: 1% of original $600m per year (10-K maturities table: $6.0m FY27–FY31)
B15: Debt & Interest Schedule | F15: FY27E | G15: FY28E | H15: FY29E | I15: FY30E | J15: FY31E | K15: FY32E | L15: FY33E | M15: FY34E | N15: FY35E | O15: FY36E
B16: Term loan — beginning balance | F16: =$D$5 -> 598.5 | G16: =F18 -> 592.5 | H16: =G18 -> 586.5 | I16: =H18 -> 580.5 | J16: =I18 -> 574.5 | K16: =J18 -> 568.5 | L16: =K18 -> 562.5 | M16: =L18 -> 556.5 | N16: =M18 -> 550.5 | O16: =N18 -> 544.5
B17: Mandatory repayment | F17: =MIN(TLAmort,F16) -> 6 | G17: =MIN(TLAmort,G16) -> 6 | H17: =MIN(TLAmort,H16) -> 6 | I17: =MIN(TLAmort,I16) -> 6 | J17: =MIN(TLAmort,J16) -> 6 | K17: =MIN(TLAmort,K16) -> 6 | L17: =MIN(TLAmort,L16) -> 6 | M17: =MIN(TLAmort,M16) -> 6 | ... O17: =MIN(TLAmort,O16) -> 6
B18: Term loan — ending balance | F18: =F16-F17 -> 592.5 | G18: =G16-G17 -> 586.5 | H18: =H16-H17 -> 580.5 | I18: =I16-I17 -> 574.5 | J18: =J16-J17 -> 568.5 | K18: =K16-K17 -> 562.5 | L18: =L16-L17 -> 556.5 | M18: =M16-M17 -> 550.5 | ... O18: =O16-O17 -> 538.5
B19: Term loan interest (beginning bal. x rate) | F19: =F16*$H$5 -> 38.24415 | G19: =G16*$H$5 -> 37.86075 | H19: =H16*$H$5 -> 37.47735 | I19: =I16*$H$5 -> 37.09395 | J19: =J16*$H$5 -> 36.71055 | K19: =K16*$H$5 -> 36.32715 | L19: =L16*$H$5 -> 35.94375 | M19: =M16*$H$5 -> 35.56035 | ... O19: =O16*$H$5 -> 34.79355
B20: Revolver balance | F20: =$D$6 -> 0 | G20: =$D$6 -> 0 | H20: =$D$6 -> 0 | I20: =$D$6 -> 0 | J20: =$D$6 -> 0 | K20: =$D$6 -> 0 | L20: =$D$6 -> 0 | M20: =$D$6 -> 0 | ... O20: =$D$6 -> 0
B21: Revolver interest | F21: =F20*$H$6 -> 0 | G21: =G20*$H$6 -> 0 | H21: =H20*$H$6 -> 0 | I21: =I20*$H$6 -> 0 | J21: =J20*$H$6 -> 0 | K21: =K20*$H$6 -> 0 | L21: =L20*$H$6 -> 0 | M21: =M20*$H$6 -> 0 | ... O21: =O20*$H$6 -> 0
B22: Total interest expense | F22: =F19+F21 -> 38.24415 | G22: =G19+G21 -> 37.86075 | H22: =H19+H21 -> 37.47735 | I22: =I19+I21 -> 37.09395 | J22: =J19+J21 -> 36.71055 | K22: =K19+K21 -> 36.32715 | L22: =L19+L21 -> 35.94375 | M22: =M19+M21 -> 35.56035 | ... O22: =O19+O21 -> 34.79355
B24: Term loan matures 12/19/2032 (FY33). Model assumes refinancing on the same terms with 1% amortization continuing; floating rate — each ±100bp moves interest ~$6m/yr (10-K Item 7A).
B25: Undrawn revolver commitment fees and OID amortization are excluded (immaterial to UFCF).

Sheet DCF
A1: ="Discounted Cash Flows for "&Name -> Discounted Cash Flows for Forgent Power Solutions, Inc.
A2: (Dollars in Millions unless stated)
B3: Year # | F3: 1 | G3: 2 | H3: 3 | I3: 4 | J3: 5 | K3: 6 | L3: 7 | M3: 8 | N3: 9 | O3: 10
F4: ="Projected — fiscal years ending "&TEXT(FYE,"mmmm d") -> Projected — fiscal years ending June 30
B5: Fiscal year | F5: =Inc_Stmt!F5 -> FY27E | G5: =Inc_Stmt!G5 -> FY28E | H5: =Inc_Stmt!H5 -> FY29E | I5: =Inc_Stmt!I5 -> FY30E | J5: =Inc_Stmt!J5 -> FY31E | K5: =Inc_Stmt!K5 -> FY32E | L5: =Inc_Stmt!L5 -> FY33E | M5: =Inc_Stmt!M5 -> FY34E | ... O5: =Inc_Stmt!O5 -> FY36E | Q5: Terminal Value Calculation
B6: Fiscal year end | F6: =EDATE(FYE,12*F3) -> 46568 | G6: =EDATE(FYE,12*G3) -> 46934 | H6: =EDATE(FYE,12*H3) -> 47299 | I6: =EDATE(FYE,12*I3) -> 47664 | J6: =EDATE(FYE,12*J3) -> 48029 | K6: =EDATE(FYE,12*K3) -> 48395 | L6: =EDATE(FYE,12*L3) -> 48760 | M6: =EDATE(FYE,12*M3) -> 49125 | ... O6: =EDATE(FYE,12*O3) -> 49856
B7: Discount period (years from valuation date) | F7: =(F6-valdate)/365-0.5*MidYear -> 0.26164384 | G7: =(G6-valdate)/365-0.5*MidYear -> 1.2643836 | H7: =(H6-valdate)/365-0.5*MidYear -> 2.2643836 | I7: =(I6-valdate)/365-0.5*MidYear -> 3.2643836 | J7: =(J6-valdate)/365-0.5*MidYear -> 4.2643836 | K7: =(K6-valdate)/365-0.5*MidYear -> 5.2671233 | L7: =(L6-valdate)/365-0.5*MidYear -> 6.2671233 | M7: =(M6-valdate)/365-0.5*MidYear -> 7.2671233 | ... O7: =(O6-valdate)/365-0.5*MidYear -> 9.269863 | Q7: =O5&" EBITDA" -> FY36E EBITDA | R7: =O10 -> 1430.863
Q8: Exit EV / EBITDA multiple | R8: =ExitMult -> 14
B9: Revenue | F9: =Inc_Stmt!F12 -> 2501.26 | G9: =Inc_Stmt!G12 -> 3266.9585 | H9: =Inc_Stmt!H12 -> 3909.8604 | I9: =Inc_Stmt!I12 -> 4448.1804 | J9: =Inc_Stmt!J12 -> 4886.6753 | K9: =Inc_Stmt!K12 -> 5277.3981 | L9: =Inc_Stmt!L12 -> 5613.4197 | M9: =Inc_Stmt!M12 -> 5890.4843 | ... O9: =Inc_Stmt!O12 -> 6307.1557 | Q9: Terminal value — exit multiple | R9: =R7*R8 -> 20032.082
B10: EBITDA (GAAP, SBC expensed) | F10: =Inc_Stmt!F40 -> 586.57901 | G10: =Inc_Stmt!G40 -> 817.66534 | H10: =Inc_Stmt!H40 -> 999.976 | I10: =Inc_Stmt!I40 -> 1134.8309 | J10: =Inc_Stmt!J40 -> 1236.2821 | K10: =Inc_Stmt!K40 -> 1304.1216 | L10: =Inc_Stmt!L40 -> 1354.9689 | M10: =Inc_Stmt!M40 -> 1389.917 | ... O10: =Inc_Stmt!O40 -> 1430.863
B11: =Inc_Stmt!B20 -> Operating income (EBIT) | F11: =Inc_Stmt!F20 -> 530.54546 | G11: =Inc_Stmt!G20 -> 753.42744 | H11: =Inc_Stmt!H20 -> 936.53016 | I11: =Inc_Stmt!I20 -> 1071.0549 | J11: =Inc_Stmt!J20 -> 1169.3048 | K11: =Inc_Stmt!K20 -> 1232.7695 | L11: =Inc_Stmt!L20 -> 1278.6005 | M11: =Inc_Stmt!M20 -> 1306.497 | ... O11: =Inc_Stmt!O20 -> 1335.7938 | Q11: =O5&" unlevered FCF" -> FY36E unlevered FCF | R11: =O17 -> 968.31679
B12: Less: taxes on EBIT | F12: =-F11*TaxRate -> -132.63636 | G12: =-G11*TaxRate -> -188.35686 | H12: =-H11*TaxRate -> -234.13254 | I12: =-I11*TaxRate -> -267.76372 | J12: =-J11*TaxRate -> -292.3262 | K12: =-K11*TaxRate -> -308.19237 | L12: =-L11*TaxRate -> -319.65011 | M12: =-M11*TaxRate -> -326.62426 | ... O12: =-O11*TaxRate -> -333.94846 | Q12: Terminal growth | R12: =TGR -> 0.03
B13: NOPAT | F13: =F11+F12 -> 397.90909 | G13: =G11+G12 -> 565.07058 | H13: =H11+H12 -> 702.39762 | I13: =I11+I12 -> 803.29115 | J13: =J11+J12 -> 876.97859 | K13: =K11+K12 -> 924.5771 | L13: =L11+L12 -> 958.95034 | M13: =M11+M12 -> 979.87277 | ... O13: =O11+O12 -> 1001.8454 | Q13: WACC | R13: =WACC -> 0.097525133
B14: Plus: depreciation & amortization | F14: =Inc_Stmt!F39 -> 56.03355 | G14: =Inc_Stmt!G39 -> 64.237907 | H14: =Inc_Stmt!H39 -> 63.445847 | I14: =Inc_Stmt!I39 -> 63.776047 | J14: =Inc_Stmt!J39 -> 66.977269 | K14: =Inc_Stmt!K39 -> 71.352148 | L14: =Inc_Stmt!L39 -> 76.368449 | M14: =Inc_Stmt!M39 -> 83.419984 | ... O14: =Inc_Stmt!O39 -> 95.069136 | Q14: Terminal value — Gordon growth | R14: =R11*(1+R12)/(R13-R12) -> 14770.297
B15: Less: capital expenditures | F15: =Inc_Stmt!F44 -> -87.0126 | G15: =Inc_Stmt!G44 -> -39.203502 | H15: =Inc_Stmt!H44 -> -50.828185 | I15: =Inc_Stmt!I44 -> -62.274525 | J15: =Inc_Stmt!J44 -> -73.30013 | K15: =Inc_Stmt!K44 -> -81.951156 | L15: =Inc_Stmt!L44 -> -100.53568 | M15: =Inc_Stmt!M44 -> -101.82568 | ... O15: =Inc_Stmt!O44 -> -103.53737
B16: Less: increase in NWC | F16: =-Inc_Stmt!F53 -> -136.1683 | G16: =-Inc_Stmt!G53 -> -94.594896 | H16: =-Inc_Stmt!H53 -> -79.266279 | I16: =-Inc_Stmt!I53 -> -67.42863 | J16: =-Inc_Stmt!J53 -> -56.183281 | K16: =-Inc_Stmt!K53 -> -51.759817 | L16: =-Inc_Stmt!L53 -> -45.240146 | M16: =-Inc_Stmt!M53 -> -38.095204 | ... O16: =-Inc_Stmt!O53 -> -25.060354 | Q16: Weight on Gordon | R16: =TVweight -> 0.5
B17: Unlevered free cash flow | F17: =SUM(F13:F16) -> 230.76174 | G17: =SUM(G13:G16) -> 495.51009 | H17: =SUM(H13:H16) -> 635.749 | I17: =SUM(I13:I16) -> 737.36404 | J17: =SUM(J13:J16) -> 814.47244 | K17: =SUM(K13:K16) -> 862.21828 | L17: =SUM(L13:L16) -> 889.54297 | M17: =SUM(M13:M16) -> 923.37187 | ... O17: =SUM(O13:O16) -> 968.31679 | Q17: Blended terminal value | R17: =R16*R14+(1-R16)*R9 -> 17401.189
B18: UFCF margin | F18: =F17/F9 -> 0.092258199 | G18: =G17/G9 -> 0.15167321 | H18: =H17/H9 -> 0.16260146 | I18: =I17/I9 -> 0.16576757 | J18: =J17/J9 -> 0.1666721 | K18: =K17/K9 -> 0.16337943 | L18: =L17/L9 -> 0.15846721 | M18: =M17/M9 -> 0.15675653 | ... O18: =O17/O9 -> 0.1535267 | Q18: TV discount period (year-end) | R18: =O7+0.5*MidYear -> 9.769863
B19: WACC | F19: =WACC -> 0.097525133 | Q19: PV of blended TV | R19: =R17/(1+WACC)^R18 -> 7010.2751
B20: Discount factor | F20: =1/(1+WACC)^F7 -> 0.97594603 | G20: =1/(1+WACC)^G7 -> 0.88899763 | H20: =1/(1+WACC)^H7 -> 0.81000207 | I20: =1/(1+WACC)^I7 -> 0.73802599 | J20: =1/(1+WACC)^J7 -> 0.67244564 | K20: =1/(1+WACC)^K7 -> 0.61253651 | L20: =1/(1+WACC)^L7 -> 0.55810705 | M20: =1/(1+WACC)^M7 -> 0.50851414 | ... O20: =1/(1+WACC)^O7 -> 0.42204947 | Q20: PV of Gordon TV | R20: =R14/(1+WACC)^R18 -> 5950.389
B21: PV of unlevered FCF | F21: =F17*F20 -> 225.21101 | G21: =G17*G20 -> 440.50729 | H21: =H17*H20 -> 514.95801 | I21: =I17*I20 -> 544.19382 | J21: =J17*J20 -> 547.68844 | K21: =K17*K20 -> 528.14018 | L21: =L17*L20 -> 496.4602 | M21: =M17*M20 -> 469.54765 | ... O21: =O17*O20 -> 408.67759 | Q21: PV of exit-multiple TV | R21: =R9/(1+WACC)^R18 -> 8070.1611
B24: Valuation Summary
B25: Sum of PV of UFCF (FY27–FY36) | E25: =SUM(F21:O21) -> 4613.128
B26: PV of terminal value (blended) | E26: =R19 -> 7010.2751
B27: Implied enterprise value | E27: =E25+E26 -> 11623.403
B28: Less: total debt | E28: =-totaldebt -> -598.5
B29: Plus: cash & equivalents | E29: =cash -> 97.477
B30: Less: TRA liability | E30: =-TRA -> -338.925 | G30: TRA pays 85% of step-up tax savings to pre-IPO owners; net claim ≈ $34m
B31: Plus: deferred tax asset backing TRA | E31: =DTA -> 280.971
B32: Plus: TRA-restricted cash | E32: =rcash -> 24.236
B33: Less: minority interest (see note) | E33: =-mininterest -> 0 | G33: Book NCI $107.1m not subtracted: Class B units are in the 305.1m fully-exchanged share count
B34: Less: preferred stock | E34: =-prefstock -> 0
B35: Implied equity value | E35: =SUM(E27:E34) -> 11088.662
B36: Diluted shares, fully exchanged (MM) | E36: =DilutedShares -> 305.12388
B37: Implied value per share | E37: =E35/E36 -> 36.341509
B38: Current share price | E38: =shareprice -> 38.97
B39: Upside / (downside) | E39: =E37/E38-1 -> -0.067449101
B40: Net claims (debt − cash + TRA − DTA − restricted cash + MI + pref) | E40: =-SUM(E28:E34) -> 534.741
B42: Method Cross-Check
B43: Implied price — Gordon growth only | E43: =(E25+R20-NetClaims)/DilutedShares -> 32.867883
B44: Implied price — exit multiple only | E44: =(E25+R21-NetClaims)/DilutedShares -> 39.815134
B45: PV of TV as % of EV (blended) | E45: =E26/E27 -> 0.60311726 | G45: Flag if > 75%
B46: Implied exit multiple from Gordon TV | E46: =R14/R7 -> 10.32265
B47: Implied perpetual growth from exit TV | E47: =(R9*WACC-R11)/(R9+R11) -> 0.046918854 | G47: Should be ≤ long-run nominal GDP (~3–4%); higher means the exit multiple is rich
B48: Exit-multiple TV / Gordon TV | E48: =R9/R14 -> 1.3562409
B51: Sensitivity Analysis — implied value per share
B53: Gordon growth: WACC (rows) × terminal growth (cols)
E54: WACC \ g | F54: =TGR-0.01 -> 0.02 | G54: =TGR-0.005 -> 0.025 | H54: =TGR+0 -> 0.03 | I54: =TGR+0.005 -> 0.035 | J54: =TGR+0.01 -> 0.04
E55: =WACC-0.01 -> 0.087525133 | F55: =(SUMPRODUCT($F$17:$O$17,1/(1+$E55)^$F$7:$O$7)+$O$17*(1+F$54)/($E55-F$54)/(1+$E55)^$R$18-NetClaims)/DilutedShares -> 35.183361 | G55: =(SUMPRODUCT($F$17:$O$17,1/(1+$E55)^$F$7:$O$7)+$O$17*(1+G$54)/($E55-G$54)/(1+$E55)^$R$18-NetClaims)/DilutedShares -> 36.983987 | H55: =(SUMPRODUCT($F$17:$O$17,1/(1+$E55)^$F$7:$O$7)+$O$17*(1+H$54)/($E55-H$54)/(1+$E55)^$R$18-NetClaims)/DilutedShares -> 39.097628 | I55: =(SUMPRODUCT($F$17:$O$17,1/(1+$E55)^$F$7:$O$7)+$O$17*(1+I$54)/($E55-I$54)/(1+$E55)^$R$18-NetClaims)/DilutedShares -> 41.613676 | J55: =(SUMPRODUCT($F$17:$O$17,1/(1+$E55)^$F$7:$O$7)+$O$17*(1+J$54)/($E55-J$54)/(1+$E55)^$R$18-NetClaims)/DilutedShares -> 44.659137
E56: =WACC-0.005 -> 0.092525133 | F56: =(SUMPRODUCT($F$17:$O$17,1/(1+$E56)^$F$7:$O$7)+$O$17*(1+F$54)/($E56-F$54)/(1+$E56)^$R$18-NetClaims)/DilutedShares -> 32.510668 | G56: =(SUMPRODUCT($F$17:$O$17,1/(1+$E56)^$F$7:$O$7)+$O$17*(1+G$54)/($E56-G$54)/(1+$E56)^$R$18-NetClaims)/DilutedShares -> 34.00181 | H56: =(SUMPRODUCT($F$17:$O$17,1/(1+$E56)^$F$7:$O$7)+$O$17*(1+H$54)/($E56-H$54)/(1+$E56)^$R$18-NetClaims)/DilutedShares -> 35.731438 | I56: =(SUMPRODUCT($F$17:$O$17,1/(1+$E56)^$F$7:$O$7)+$O$17*(1+I$54)/($E56-I$54)/(1+$E56)^$R$18-NetClaims)/DilutedShares -> 37.76174 | J56: =(SUMPRODUCT($F$17:$O$17,1/(1+$E56)^$F$7:$O$7)+$O$17*(1+J$54)/($E56-J$54)/(1+$E56)^$R$18-NetClaims)/DilutedShares -> 40.178581
E57: =WACC+0 -> 0.097525133 | F57: =(SUMPRODUCT($F$17:$O$17,1/(1+$E57)^$F$7:$O$7)+$O$17*(1+F$54)/($E57-F$54)/(1+$E57)^$R$18-NetClaims)/DilutedShares -> 30.187457 | G57: =(SUMPRODUCT($F$17:$O$17,1/(1+$E57)^$F$7:$O$7)+$O$17*(1+G$54)/($E57-G$54)/(1+$E57)^$R$18-NetClaims)/DilutedShares -> 31.435274 | H57: =(SUMPRODUCT($F$17:$O$17,1/(1+$E57)^$F$7:$O$7)+$O$17*(1+H$54)/($E57-H$54)/(1+$E57)^$R$18-NetClaims)/DilutedShares -> 32.867883 | I57: =(SUMPRODUCT($F$17:$O$17,1/(1+$E57)^$F$7:$O$7)+$O$17*(1+I$54)/($E57-I$54)/(1+$E57)^$R$18-NetClaims)/DilutedShares -> 34.529618 | J57: =(SUMPRODUCT($F$17:$O$17,1/(1+$E57)^$F$7:$O$7)+$O$17*(1+J$54)/($E57-J$54)/(1+$E57)^$R$18-NetClaims)/DilutedShares -> 36.480225
E58: =WACC+0.005 -> 0.10252513 | F58: =(SUMPRODUCT($F$17:$O$17,1/(1+$E58)^$F$7:$O$7)+$O$17*(1+F$54)/($E58-F$54)/(1+$E58)^$R$18-NetClaims)/DilutedShares -> 28.149958 | G58: =(SUMPRODUCT($F$17:$O$17,1/(1+$E58)^$F$7:$O$7)+$O$17*(1+G$54)/($E58-G$54)/(1+$E58)^$R$18-NetClaims)/DilutedShares -> 29.203717 | H58: =(SUMPRODUCT($F$17:$O$17,1/(1+$E58)^$F$7:$O$7)+$O$17*(1+H$54)/($E58-H$54)/(1+$E58)^$R$18-NetClaims)/DilutedShares -> 30.402772 | I58: =(SUMPRODUCT($F$17:$O$17,1/(1+$E58)^$F$7:$O$7)+$O$17*(1+I$54)/($E58-I$54)/(1+$E58)^$R$18-NetClaims)/DilutedShares -> 31.779398 | J58: =(SUMPRODUCT($F$17:$O$17,1/(1+$E58)^$F$7:$O$7)+$O$17*(1+J$54)/($E58-J$54)/(1+$E58)^$R$18-NetClaims)/DilutedShares -> 33.376195
E59: =WACC+0.01 -> 0.10752513 | F59: =(SUMPRODUCT($F$17:$O$17,1/(1+$E59)^$F$7:$O$7)+$O$17*(1+F$54)/($E59-F$54)/(1+$E59)^$R$18-NetClaims)/DilutedShares -> 26.348992 | G59: =(SUMPRODUCT($F$17:$O$17,1/(1+$E59)^$F$7:$O$7)+$O$17*(1+G$54)/($E59-G$54)/(1+$E59)^$R$18-NetClaims)/DilutedShares -> 27.246043 | H59: =(SUMPRODUCT($F$17:$O$17,1/(1+$E59)^$F$7:$O$7)+$O$17*(1+H$54)/($E59-H$54)/(1+$E59)^$R$18-NetClaims)/DilutedShares -> 28.258806 | I59: =(SUMPRODUCT($F$17:$O$17,1/(1+$E59)^$F$7:$O$7)+$O$17*(1+I$54)/($E59-I$54)/(1+$E59)^$R$18-NetClaims)/DilutedShares -> 29.411211 | J59: =(SUMPRODUCT($F$17:$O$17,1/(1+$E59)^$F$7:$O$7)+$O$17*(1+J$54)/($E59-J$54)/(1+$E59)^$R$18-NetClaims)/DilutedShares -> 30.73428
B62: Exit multiple: WACC (rows) × exit EV/EBITDA (cols)
E63: WACC \ x | F63: =ExitMult-6 -> 8 | G63: =ExitMult-3 -> 11 | H63: =ExitMult+0 -> 14 | I63: =ExitMult+3 -> 17 | J63: =ExitMult+6 -> 20
E64: =WACC-0.01 -> 0.087525133 | F64: =(SUMPRODUCT($F$17:$O$17,1/(1+$E64)^$F$7:$O$7)+$O$10*F$63/(1+$E64)^$R$18-NetClaims)/DilutedShares -> 30.591984 | G64: =(SUMPRODUCT($F$17:$O$17,1/(1+$E64)^$F$7:$O$7)+$O$10*G$63/(1+$E64)^$R$18-NetClaims)/DilutedShares -> 36.789764 | H64: =(SUMPRODUCT($F$17:$O$17,1/(1+$E64)^$F$7:$O$7)+$O$10*H$63/(1+$E64)^$R$18-NetClaims)/DilutedShares -> 42.987543 | I64: =(SUMPRODUCT($F$17:$O$17,1/(1+$E64)^$F$7:$O$7)+$O$10*I$63/(1+$E64)^$R$18-NetClaims)/DilutedShares -> 49.185322 | J64: =(SUMPRODUCT($F$17:$O$17,1/(1+$E64)^$F$7:$O$7)+$O$10*J$63/(1+$E64)^$R$18-NetClaims)/DilutedShares -> 55.383101
E65: =WACC-0.005 -> 0.092525133 | F65: =(SUMPRODUCT($F$17:$O$17,1/(1+$E65)^$F$7:$O$7)+$O$10*F$63/(1+$E65)^$R$18-NetClaims)/DilutedShares -> 29.512666 | G65: =(SUMPRODUCT($F$17:$O$17,1/(1+$E65)^$F$7:$O$7)+$O$10*G$63/(1+$E65)^$R$18-NetClaims)/DilutedShares -> 35.438824 | H65: =(SUMPRODUCT($F$17:$O$17,1/(1+$E65)^$F$7:$O$7)+$O$10*H$63/(1+$E65)^$R$18-NetClaims)/DilutedShares -> 41.364983 | I65: =(SUMPRODUCT($F$17:$O$17,1/(1+$E65)^$F$7:$O$7)+$O$10*I$63/(1+$E65)^$R$18-NetClaims)/DilutedShares -> 47.291141 | J65: =(SUMPRODUCT($F$17:$O$17,1/(1+$E65)^$F$7:$O$7)+$O$10*J$63/(1+$E65)^$R$18-NetClaims)/DilutedShares -> 53.217299
E66: =WACC+0 -> 0.097525133 | F66: =(SUMPRODUCT($F$17:$O$17,1/(1+$E66)^$F$7:$O$7)+$O$10*F$63/(1+$E66)^$R$18-NetClaims)/DilutedShares -> 28.479933 | G66: =(SUMPRODUCT($F$17:$O$17,1/(1+$E66)^$F$7:$O$7)+$O$10*G$63/(1+$E66)^$R$18-NetClaims)/DilutedShares -> 34.147533 | H66: =(SUMPRODUCT($F$17:$O$17,1/(1+$E66)^$F$7:$O$7)+$O$10*H$63/(1+$E66)^$R$18-NetClaims)/DilutedShares -> 39.815134 | I66: =(SUMPRODUCT($F$17:$O$17,1/(1+$E66)^$F$7:$O$7)+$O$10*I$63/(1+$E66)^$R$18-NetClaims)/DilutedShares -> 45.482734 | J66: =(SUMPRODUCT($F$17:$O$17,1/(1+$E66)^$F$7:$O$7)+$O$10*J$63/(1+$E66)^$R$18-NetClaims)/DilutedShares -> 51.150335
E67: =WACC+0.005 -> 0.10252513 | F67: =(SUMPRODUCT($F$17:$O$17,1/(1+$E67)^$F$7:$O$7)+$O$10*F$63/(1+$E67)^$R$18-NetClaims)/DilutedShares -> 27.491486 | G67: =(SUMPRODUCT($F$17:$O$17,1/(1+$E67)^$F$7:$O$7)+$O$10*G$63/(1+$E67)^$R$18-NetClaims)/DilutedShares -> 32.912909 | H67: =(SUMPRODUCT($F$17:$O$17,1/(1+$E67)^$F$7:$O$7)+$O$10*H$63/(1+$E67)^$R$18-NetClaims)/DilutedShares -> 38.334332 | I67: =(SUMPRODUCT($F$17:$O$17,1/(1+$E67)^$F$7:$O$7)+$O$10*I$63/(1+$E67)^$R$18-NetClaims)/DilutedShares -> 43.755755 | J67: =(SUMPRODUCT($F$17:$O$17,1/(1+$E67)^$F$7:$O$7)+$O$10*J$63/(1+$E67)^$R$18-NetClaims)/DilutedShares -> 49.177177
E68: =WACC+0.01 -> 0.10752513 | F68: =(SUMPRODUCT($F$17:$O$17,1/(1+$E68)^$F$7:$O$7)+$O$10*F$63/(1+$E68)^$R$18-NetClaims)/DilutedShares -> 26.545154 | G68: =(SUMPRODUCT($F$17:$O$17,1/(1+$E68)^$F$7:$O$7)+$O$10*G$63/(1+$E68)^$R$18-NetClaims)/DilutedShares -> 31.732134 | H68: =(SUMPRODUCT($F$17:$O$17,1/(1+$E68)^$F$7:$O$7)+$O$10*H$63/(1+$E68)^$R$18-NetClaims)/DilutedShares -> 36.919114 | I68: =(SUMPRODUCT($F$17:$O$17,1/(1+$E68)^$F$7:$O$7)+$O$10*I$63/(1+$E68)^$R$18-NetClaims)/DilutedShares -> 42.106095 | J68: =(SUMPRODUCT($F$17:$O$17,1/(1+$E68)^$F$7:$O$7)+$O$10*J$63/(1+$E68)^$R$18-NetClaims)/DilutedShares -> 47.293075

Sheet Comps Analysis
A1: ="Comparable Companies Analysis for "&Name -> Comparable Companies Analysis for Forgent Power Solutions, Inc.
A2: (Dollars in Millions except share price & EPS)
B5: Inputs for comparable companies analysis
B6: Company | C6: Price | D6: Shares | E6: Mkt cap | F6: Net debt | G6: Enterprise value | H6: LTM revenue | I6: LTM EBITDA
B7: ='Financial Data'!B8 -> Eaton | C7: ='Financial Data'!D8 -> 439.98 | D7: ='Financial Data'!E8 -> 388.4 | E7: =C7*D7 -> 170888.23 | F7: ='Financial Data'!G8-'Financial Data'!H8 -> 20631 | G7: ='Financial Data'!J8 -> 191564.23 | H7: ='Financial Data'!K8 -> 30026 | I7: ='Financial Data'!L8 -> 6640
B8: ='Financial Data'!B9 -> Vertiv | C8: ='Financial Data'!D9 -> 253.28 | D8: ='Financial Data'!E9 -> 384.99 | E8: =C8*D8 -> 97510.267 | F8: ='Financial Data'!G9-'Financial Data'!H9 -> 227 | G8: ='Financial Data'!J9 -> 97737.267 | H8: ='Financial Data'!K9 -> 11480 | I8: ='Financial Data'!L9 -> 2680
B9: ='Financial Data'!B10 -> Hubbell | C9: ='Financial Data'!D10 -> 466.62 | D9: ='Financial Data'!E10 -> 52.83 | E9: =C9*D9 -> 24651.535 | F9: ='Financial Data'!G10-'Financial Data'!H10 -> 5162.3 | G9: ='Financial Data'!J10 -> 29824.935 | H9: ='Financial Data'!K10 -> 6224 | I9: ='Financial Data'!L10 -> 1520
B10: ='Financial Data'!B11 -> nVent | C10: ='Financial Data'!D11 -> 164.41 | D10: ='Financial Data'!E11 -> 161.86 | E10: =C10*D10 -> 26611.403 | F10: ='Financial Data'!G11-'Financial Data'!H11 -> 1377 | G10: ='Financial Data'!J11 -> 27988.403 | H10: ='Financial Data'!K11 -> 4834 | I10: ='Financial Data'!L11 -> 1050
B11: ='Financial Data'!B12 -> GE Vernova | C11: ='Financial Data'!D12 -> 957.63 | D11: ='Financial Data'!E12 -> 266.33 | E11: =C11*D11 -> 255045.6 | F11: ='Financial Data'!G12-'Financial Data'!H12 -> -9000 | G11: ='Financial Data'!J12 -> 247203.6 | H11: ='Financial Data'!K12 -> 41367 | I11: ='Financial Data'!L12 -> 3930
B12: ='Financial Data'!B13 -> Powell Industries | C12: ='Financial Data'!D13 -> 189.53 | D12: ='Financial Data'!E13 -> 36.43 | E12: =C12*D12 -> 6904.5779 | F12: ='Financial Data'!G13-'Financial Data'!H13 -> -631.04 | G12: ='Financial Data'!J13 -> 6273.5379 | H12: ='Financial Data'!K13 -> 1158 | I12: ='Financial Data'!L13 -> 236.2
B14: =Name -> Forgent Power Solutions, Inc. | C14: =shareprice -> 38.97 | D14: =DilutedShares -> 305.12388 | E14: =marketcap -> 11863.594 | F14: =NetClaims -> 534.741 | G14: =Enterprise -> 12398.335 | H14: =Inc_Stmt!E12 -> 1420.059 | I14: =Inc_Stmt!E43 -> 322.9
B17: Trading multiples
B18: Company | C18: EV / LTM revenue | D18: EV / LTM EBITDA | E18: LTM P/E (GAAP) | F18: NTM P/E (adj.) | G18: LTM EBITDA margin
B19: =B7 -> Eaton | C19: =IF(G7/H7>0,G7/H7,"N/A") -> 6.3799451 | D19: =IF(G7/I7>0,G7/I7,"N/A") -> 28.850035 | E19: =IF(C7/'Financial Data'!M8>0,C7/'Financial Data'!M8,"N/A") -> 44.804481 | F19: =IF(C7/'Financial Data'!N8>0,C7/'Financial Data'!N8,"N/A") -> 28.422481 | G19: =I7/H7 -> 0.22114168
B20: =B8 -> Vertiv | C20: =IF(G8/H8>0,G8/H8,"N/A") -> 8.5136992 | D20: =IF(G8/I8>0,G8/I8,"N/A") -> 36.46913 | E20: =IF(C8/'Financial Data'!M9>0,C8/'Financial Data'!M9,"N/A") -> 57.303167 | F20: =IF(C8/'Financial Data'!N9>0,C8/'Financial Data'!N9,"N/A") -> 29.537026 | G20: =I8/H8 -> 0.23344948 | I20: GEV LTM P/E distorted by non-operating gains; medians are robust to it.
B21: =B9 -> Hubbell | C21: =IF(G9/H9>0,G9/H9,"N/A") -> 4.7919239 | D21: =IF(G9/I9>0,G9/I9,"N/A") -> 19.621667 | E21: =IF(C9/'Financial Data'!M10>0,C9/'Financial Data'!M10,"N/A") -> 27.610651 | F21: =IF(C9/'Financial Data'!N10>0,C9/'Financial Data'!N10,"N/A") -> 20.917629 | G21: =I9/H9 -> 0.24421594
B22: =B10 -> nVent | C22: =IF(G10/H10>0,G10/H10,"N/A") -> 5.7899054 | D22: =IF(G10/I10>0,G10/I10,"N/A") -> 26.655622 | E22: =IF(C10/'Financial Data'!M11>0,C10/'Financial Data'!M11,"N/A") -> 45.043836 | F22: =IF(C10/'Financial Data'!N11>0,C10/'Financial Data'!N11,"N/A") -> 26.560582 | G22: =I10/H10 -> 0.21721142
B23: =B11 -> GE Vernova | C23: =IF(G11/H11>0,G11/H11,"N/A") -> 5.9758648 | D23: =IF(G11/I11>0,G11/I11,"N/A") -> 62.901679 | E23: =IF(C11/'Financial Data'!M12>0,C11/'Financial Data'!M12,"N/A") -> 27.407842 | F23: =IF(C11/'Financial Data'!N12>0,C11/'Financial Data'!N12,"N/A") -> 43.146204 | G23: =I11/H11 -> 0.095003263
B24: =B12 -> Powell Industries | C24: =IF(G12/H12>0,G12/H12,"N/A") -> 5.417563 | D24: =IF(G12/I12>0,G12/I12,"N/A") -> 26.560279 | E24: =IF(C12/'Financial Data'!M13>0,C12/'Financial Data'!M13,"N/A") -> 36.308429 | F24: =IF(C12/'Financial Data'!N13>0,C12/'Financial Data'!N13,"N/A") -> 27.114449 | G24: =I12/H12 -> 0.20397237
B26: =B14 -> Forgent Power Solutions, Inc. | C26: =G14/H14 -> 8.7308589 | D26: =G14/I14 -> 38.396825 | E26: =C14/'Financial Data'!M15 -> 111.98339 | F26: =C14/'Financial Data'!N15 -> 29.08209 | G26: =I14/H14 -> 0.22738492
B28: Max | C28: =MAX(C19:C24) -> 8.5136992 | D28: =MAX(D19:D24) -> 62.901679 | E28: =MAX(E19:E24) -> 57.303167 | F28: =MAX(F19:F24) -> 43.146204 | G28: =MAX(G19:G24) -> 0.24421594
B29: 75th percentile | C29: =QUARTILE(C19:C24,3) -> 6.278925 | D29: =QUARTILE(D19:D24,3) -> 34.564356 | E29: =QUARTILE(E19:E24,3) -> 44.983997 | F29: =QUARTILE(F19:F24,3) -> 29.25839 | G29: =QUARTILE(G19:G24,3) -> 0.23037253
B30: Median | C30: =MEDIAN(C19:C24) -> 5.8828851 | D30: =MEDIAN(D19:D24) -> 27.752828 | E30: =MEDIAN(E19:E24) -> 40.556455 | F30: =MEDIAN(F19:F24) -> 27.768465 | G30: =MEDIAN(G19:G24) -> 0.21917655
B31: Mean | C31: =AVERAGE(C19:C24) -> 6.1448169 | D31: =AVERAGE(D19:D24) -> 33.509735 | E31: =AVERAGE(E19:E24) -> 39.746401 | F31: =AVERAGE(F19:F24) -> 29.283062 | G31: =AVERAGE(G19:G24) -> 0.20249902
B32: 25th percentile | C32: =QUARTILE(C19:C24,1) -> 5.5106486 | D32: =QUARTILE(D19:D24,1) -> 26.584115 | E32: =QUARTILE(E19:E24,1) -> 29.785095 | F32: =QUARTILE(F19:F24,1) -> 26.699048 | G32: =QUARTILE(G19:G24,1) -> 0.20728213
B33: Min | C33: =MIN(C19:C24) -> 4.7919239 | D33: =MIN(D19:D24) -> 19.621667 | E33: =MIN(E19:E24) -> 27.407842 | F33: =MIN(F19:F24) -> 20.917629 | G33: =MIN(G19:G24) -> 0.095003263
B36: ="Implied valuation of "&Name -> Implied valuation of Forgent Power Solutions, Inc.
C37: LTM revenue | D37: LTM adj. EBITDA | E37: LTM EPS | F37: NTM EPS | G37: Primary (NTM P/E)
B38: =Ticker&" metric" -> FPS metric | C38: =H14 -> 1420.059 | D38: =I14 -> 322.9 | E38: ='Financial Data'!M15 -> 0.34799803 | F38: ='Financial Data'!N15 -> 1.34
B40: Implied share price
B41: Max | C41: =(C28*C$38-NetClaims)/DilutedShares -> 37.870567 | D41: =(D28*D$38-NetClaims)/DilutedShares -> 64.813711 | E41: =E28*E$38 -> 19.941389 | F41: =F28*F$38 -> 57.815913 | G41: =F41 -> 57.815913
B42: 75th percentile | C42: =(C29*C$38-NetClaims)/DilutedShares -> 27.469836 | D42: =(D29*D$38-NetClaims)/DilutedShares -> 34.825493 | E42: =E29*E$38 -> 15.654342 | F42: =F29*F$38 -> 39.206242 | G42: =F42 -> 39.206242
B43: Median | C43: =(C30*C$38-NetClaims)/DilutedShares -> 25.62665 | D43: =(D30*D$38-NetClaims)/DilutedShares -> 27.617135 | E43: =E30*E$38 -> 14.113566 | F43: =F30*F$38 -> 37.209743 | G43: =F43 -> 37.209743
B44: 25th percentile | C44: =(C32*C$38-NetClaims)/DilutedShares -> 23.894246 | D44: =(D32*D$38-NetClaims)/DilutedShares -> 26.380333 | E44: =E32*E$38 -> 10.365155 | F44: =F32*F$38 -> 35.776725 | G44: =F44 -> 35.776725
B45: Min | C45: =(C33*C$38-NetClaims)/DilutedShares -> 20.549272 | D45: =(D33*D$38-NetClaims)/DilutedShares -> 19.012263 | E45: =E33*E$38 -> 9.5378751 | F45: =F33*F$38 -> 28.029622 | G45: =F45 -> 28.029622
B47: Primary comps method = NTM P/E: FPS FY26 LTM EBITDA/revenue understate run-rate for a company guiding +76% revenue growth, and peer consensus EBITDA was not available to build NTM EV/EBITDA.
B48: EV-based prices subtract FPS net claims (debt − cash + TRA − DTA − restricted cash).

Sheet Financial Data
A1: Comparable Company Financial Data
A2: (Dollars in Millions except per share; prices at 9/25/2026 close; balance sheets at quarter ended 6/30/2026)
B7: Company | C7: Ticker | D7: Price | E7: Shares (MM) | F7: Market cap | G7: Total debt | H7: Cash & STI | I7: Minority int. | J7: Enterprise value | K7: LTM revenue | L7: LTM EBITDA | M7: LTM EPS (GAAP) | N7: NTM EPS (adj.) | O7: FYE | P7: Notes
B8: Eaton | C8: ETN | D8: 439.98 | E8: 388.4 | F8: =D8*E8 -> 170888.23 | G8: 21326 | H8: 695 | I8: 45 | J8: =F8+G8+I8-H8 -> 191564.23 | K8: 30026 | L8: 6640 | M8: 9.82 | N8: =0.25*13.56+0.75*16.12 -> 15.48 | O8: Dec | P8: ~25% of revenue in Aerospace/Mobility
B9: Vertiv | C9: VRT | D9: 253.28 | E9: 384.99 | F9: =D9*E9 -> 97510.267 | G9: 3338 | H9: 3111 | I9: 0 | J9: =F9+G9+I9-H9 -> 97737.267 | K9: 11480 | L9: 2680 | M9: 4.42 | N9: =0.25*6.73+0.75*9.19 -> 8.575 | O9: Dec | P9: FY27 EPS from Finviz
B10: Hubbell | C10: HUBB | D10: 466.62 | E10: 52.83 | F10: =D10*E10 -> 24651.535 | G10: 5557 | H10: 394.7 | I10: 11.1 | J10: =F10+G10+I10-H10 -> 29824.935 | K10: 6224 | L10: 1520 | M10: 16.9 | N10: =0.25*20.47+0.75*22.92 -> 22.3075 | O10: Dec
B11: nVent | C11: NVT | D11: 164.41 | E11: 161.86 | F11: =D11*E11 -> 26611.403 | G11: 1633 | H11: 256 | I11: 0 | J11: =F11+G11+I11-H11 -> 27988.403 | K11: 4834 | L11: 1050 | M11: 3.65 | N11: =0.25*5.14+0.75*6.54 -> 6.19 | O11: Dec | P11: FY26 growth ~40% incl. M&A; FY27 EPS from Finviz
B12: GE Vernova | C12: GEV | D12: 957.63 | E12: 266.33 | F12: =D12*E12 -> 255045.6 | G12: 3720 | H12: 12720 | I12: 1158 | J12: =F12+G12+I12-H12 -> 247203.6 | K12: 41367 | L12: 3930 | M12: 34.94 | N12: =0.25*15.16+0.75*24.54 -> 22.195 | O12: Dec | P12: LTM EPS inflated by non-op gains; EBITDA depressed by Wind
B13: Powell Industries | C13: POWL | D13: 189.53 | E13: 36.43 | F13: =D13*E13 -> 6904.5779 | G13: 2.52 | H13: 633.56 | I13: 0 | J13: =F13+G13+I13-H13 -> 6273.5379 | K13: 1158 | L13: 236.2 | M13: 5.22 | N13: 6.99 | O13: Sep | P13: NTM = FY Sep-27 consensus; closest pure-play switchgear (not named in FPS 10-K)
B15: Forgent Power Solutions | C15: =Ticker -> FPS | D15: =shareprice -> 38.97 | E15: =DilutedShares -> 305.12388 | F15: =marketcap -> 11863.594 | G15: =totaldebt -> 598.5 | H15: =cash -> 97.477 | I15: =TRA-DTA-rcash -> 33.718 | J15: =Enterprise -> 12398.335 | K15: =Inc_Stmt!E12 -> 1420.059 | L15: =Inc_Stmt!E43 -> 322.9 | M15: =Inc_Stmt!E36 -> 0.34799803 | N15: 1.34 | O15: Jun | P15: Col I = net TRA claim. LTM EBITDA = adj. (IPO one-offs); NTM EPS = FY27 consensus
B18: Sources
B19: Prices / shares / beta: StockAnalysis.com quote & statistics pages, 9/25/2026 close.
B20: Debt, cash, minority interest: latest 10-Q balance sheets (quarter ended 6/30/2026) via StockAnalysis.
B21: LTM revenue / EBITDA / GAAP EPS: StockAnalysis TTM to 6/30/2026 (EBITDA unadjusted; POWL TTM to fiscal Q3).
B22: NTM EPS: calendarized 0.25 x FY26E + 0.75 x FY27E (adj. consensus, StockAnalysis forecast / Finviz 'EPS next Y').
B23: NOT FOUND in free sources: peer consensus EBITDA and FY27 revenue — hence no NTM EV/EBITDA or EV/Revenue columns.
B24: FPS: 10-K FY26 (filed 9/15/2026); FY27 EPS consensus $1.34 (StockAnalysis, 9/24/2026).

Sheet Fwd Comps
A1: ="Forward Trading Comparables for "&Name -> Forward Trading Comparables for Forgent Power Solutions, Inc.
A2: (Dollars in Millions except share price; SU, LR in EUR and HPS.A in CAD - multiples are currency-neutral)
B3: Adds consensus CY26E/CY27E revenue and EBITDA (MarketScreener), which 'Comps Analysis' lacks. Prices and balance sheets as of 9/25/2026 close (StockAnalysis).
B5: Company | C5: Ticker | D5: Price | E5: Shares (MM) | F5: Mkt cap | G5: Total debt | H5: Cash | I5: Enterprise value | J5: CY26E revenue | K5: CY27E revenue | L5: CY26E EBITDA | M5: CY27E EBITDA | N5: EV / CY26E revenue | O5: EV / CY26E EBITDA | P5: EV / CY27E EBITDA | Q5: CY26-27E revenue growth | R5: CY26E EBITDA margin | S5: Notes
B6: Vertiv | C6: VRT | D6: 253.28 | E6: 384.99 | F6: =D6*E6 -> 97510.267 | G6: 3340 | H6: 3110 | I6: =F6+G6-H6 -> 97740.267 | J6: 14019 | K6: 18239 | L6: 3488 | M6: 4817 | N6: =I6/J6 -> 6.9719857 | O6: =I6/L6 -> 28.021866 | P6: =I6/M6 -> 20.290693 | Q6: =K6/J6-1 -> 0.30102004 | R6: =L6/J6 -> 0.24880519 | S6: Market data: stockanalysis.com/stocks/vrt/statistics (25-Sep-2026). Consensus CY26E/CY27E revenue & EBITDA: MarketScreener /finances/ (accessed 26-Sep-2026).
B7: Eaton | C7: ETN | D7: 439.98 | E7: 388.4 | F7: =D7*E7 -> 170888.23 | G7: 21330 | H7: 695 | I7: =F7+G7-H7 -> 191523.23 | J7: 32683 | K7: 36626 | L7: 7754 | M7: 8991 | N7: =I7/J7 -> 5.8600261 | O7: =I7/L7 -> 24.699927 | P7: =I7/M7 -> 21.301661 | Q7: =K7/J7-1 -> 0.12064376 | R7: =L7/J7 -> 0.23724872 | S7: Market data: stockanalysis.com/stocks/etn/statistics (25-Sep-2026). Consensus CY26E/CY27E revenue & EBITDA: MarketScreener /finances/ (accessed 26-Sep-2026).
B8: GE Vernova | C8: GEV | D8: 957.63 | E8: 266.33 | F8: =D8*E8 -> 255045.6 | G8: 3720 | H8: 12720 | I8: =F8+G8-H8 -> 246045.6 | J8: 46282 | K8: 52740 | L8: 6359 | M8: 9574 | N8: =I8/J8 -> 5.3162266 | O8: =I8/L8 -> 38.692498 | P8: =I8/M8 -> 25.699352 | Q8: =K8/J8-1 -> 0.13953589 | R8: =L8/J8 -> 0.13739683 | S8: Market data: stockanalysis.com/stocks/gev/statistics (25-Sep-2026). Consensus CY26E/CY27E revenue & EBITDA: MarketScreener /finances/ (accessed 26-Sep-2026). LTM EBITDA is GAAP and depressed.
B9: Powell Industries (FYE Sep) | C9: POWL | D9: 189.53 | E9: 36.43 | F9: =D9*E9 -> 6904.5779 | G9: 2.5 | H9: 633.6 | I9: =F9+G9-H9 -> 6273.4779 | J9: 1191 | K9: 1483 | L9: 244.1 | M9: 315 | N9: =I9/J9 -> 5.2674038 | O9: =I9/L9 -> 25.700442 | P9: =I9/M9 -> 19.915803 | Q9: =K9/J9-1 -> 0.24517212 | R9: =L9/J9 -> 0.20495382 | S9: Market data: stockanalysis.com/stocks/powl/statistics (25-Sep-2026). Consensus CY26E/CY27E revenue & EBITDA: MarketScreener /finances/ (accessed 26-Sep-2026). Fiscal years end September (not calendarized).
B10: Hubbell | C10: HUBB | D10: 466.62 | E10: 52.83 | F10: =D10*E10 -> 24651.535 | G10: 5560 | H10: 394.7 | I10: =F10+G10-H10 -> 29816.835 | J10: 6871 | K10: 7572 | L10: 1688 | M10: 1923 | N10: =I10/J10 -> 4.3395189 | O10: =I10/L10 -> 17.664002 | P10: =I10/M10 -> 15.505374 | Q10: =K10/J10-1 -> 0.102023 | R10: =L10/J10 -> 0.24567021 | S10: Market data: stockanalysis.com/stocks/hubb/statistics (25-Sep-2026). Consensus CY26E/CY27E revenue & EBITDA: MarketScreener /finances/ (accessed 26-Sep-2026).
B11: nVent Electric | C11: NVT | D11: 164.41 | E11: 161.86 | F11: =D11*E11 -> 26611.403 | G11: 1630 | H11: 256 | I11: =F11+G11-H11 -> 27985.403 | J11: 5460 | K11: 6421 | L11: 1217 | M11: 1443 | N11: =I11/J11 -> 5.1255316 | O11: =I11/L11 -> 22.995401 | P11: =I11/M11 -> 19.393903 | Q11: =K11/J11-1 -> 0.17600733 | R11: =L11/J11 -> 0.22289377 | S11: Market data: stockanalysis.com/stocks/nvt/statistics (25-Sep-2026). Consensus CY26E/CY27E revenue & EBITDA: MarketScreener /finances/ (accessed 26-Sep-2026).
B12: Schneider Electric (EUR) | C12: SU FP | D12: 291 | E12: 562.33 | F12: =D12*E12 -> 163638.03 | G12: 20810 | H12: 4520 | I12: =F12+G12-H12 -> 179928.03 | J12: 44918 | K12: 49022 | L12: 9719 | M12: 11171 | N12: =I12/J12 -> 4.0056999 | O12: =I12/L12 -> 18.513019 | P12: =I12/M12 -> 16.106708 | Q12: =K12/J12-1 -> 0.09136649 | R12: =L12/J12 -> 0.21637206 | S12: Market data: stockanalysis.com/quote/epa/SU/statistics (25-Sep-2026). Consensus CY26E/CY27E revenue & EBITDA: MarketScreener /finances/ (accessed 26-Sep-2026).
B13: Legrand (EUR) | C13: LR FP | D13: 134.85 | E13: 262.14 | F13: =D13*E13 -> 35349.579 | G13: 7720 | H13: 1970 | I13: =F13+G13-H13 -> 41099.579 | J13: 11031 | K13: 12193 | L13: 2622 | M13: 2939 | N13: =I13/J13 -> 3.7258253 | O13: =I13/L13 -> 15.674897 | P13: =I13/M13 -> 13.984205 | Q13: =K13/J13-1 -> 0.1053395 | R13: =L13/J13 -> 0.23769377 | S13: Market data: stockanalysis.com/quote/epa/LR/statistics (25-Sep-2026). Consensus CY26E/CY27E revenue & EBITDA: MarketScreener /finances/ (accessed 26-Sep-2026).
B14: Hammond Power Solutions (CAD, pro forma AEG) | C14: HPS.A CN | D14: 279.22 | E14: 11.9 | F14: =D14*E14 -> 3322.718 | G14: 505 | H14: 33.63 | I14: =F14+G14-H14 -> 3794.088 | J14: 1409 | K14: 1708 | L14: 215.5 | M14: 263 | N14: =I14/J14 -> 2.6927523 | O14: =I14/L14 -> 17.605977 | P14: =I14/M14 -> 14.42619 | Q14: =K14/J14-1 -> 0.21220724 | R14: =L14/J14 -> 0.15294535 | S14: Market data: stockanalysis.com/quote/tsx/HPS.A/statistics (25-Sep-2026). Consensus CY26E/CY27E revenue & EBITDA: MarketScreener /finances/ (accessed 26-Sep-2026). Debt = C$94.75mm reported + ~C$410mm (US$300mm term debt) drawn to fund AEG Power Solutions (closed 29-Jun-2026), pro forma. LTM EBITDA omitted: GAAP figure distorted by deal costs.
B16: Max | N16: =MAX(N6:N14) -> 6.9719857 | O16: =MAX(O6:O14) -> 38.692498 | P16: =MAX(P6:P14) -> 25.699352 | Q16: =MAX(Q6:Q14) -> 0.30102004 | R16: =MAX(R6:R14) -> 0.24880519
B17: 75th percentile | N17: =QUARTILE(N6:N14,3) -> 5.3162266 | O17: =QUARTILE(O6:O14,3) -> 25.700442 | P17: =QUARTILE(P6:P14,3) -> 20.290693 | Q17: =QUARTILE(Q6:Q14,3) -> 0.21220724 | R17: =QUARTILE(R6:R14,3) -> 0.23769377
B18: Median | N18: =MEDIAN(N6:N14) -> 5.1255316 | O18: =MEDIAN(O6:O14) -> 22.995401 | P18: =MEDIAN(P6:P14) -> 19.393903 | Q18: =MEDIAN(Q6:Q14) -> 0.13953589 | R18: =MEDIAN(R6:R14) -> 0.22289377
B19: Mean | N19: =AVERAGE(N6:N14) -> 4.8116634 | O19: =AVERAGE(O6:O14) -> 23.285336 | P19: =AVERAGE(P6:P14) -> 18.513765 | Q19: =AVERAGE(Q6:Q14) -> 0.16592393 | R19: =AVERAGE(R6:R14) -> 0.2115533
B20: 25th percentile | N20: =QUARTILE(N6:N14,1) -> 4.0056999 | O20: =QUARTILE(O6:O14,1) -> 17.664002 | P20: =QUARTILE(P6:P14,1) -> 15.505374 | Q20: =QUARTILE(Q6:Q14,1) -> 0.1053395 | R20: =QUARTILE(R6:R14,1) -> 0.20495382
B21: Min | N21: =MIN(N6:N14) -> 2.6927523 | O21: =MIN(O6:O14) -> 15.674897 | P21: =MIN(P6:P14) -> 13.984205 | Q21: =MIN(Q6:Q14) -> 0.09136649 | R21: =MIN(R6:R14) -> 0.13739683
B23: =Name -> Forgent Power Solutions, Inc. | C23: =Ticker -> FPS | D23: =shareprice -> 38.97 | E23: =DilutedShares -> 305.12388 | F23: =marketcap -> 11863.594 | G23: =totaldebt -> 598.5 | H23: =cash -> 97.477 | I23: =Enterprise -> 12398.335 | J23: =0.5*Inc_Stmt!E12+0.5*Inc_Stmt!F12 -> 1960.6595 | K23: =0.5*Inc_Stmt!F12+0.5*Inc_Stmt!G12 -> 2884.1092 | L23: =0.5*Inc_Stmt!E43+0.5*Inc_Stmt!F43 -> 464.74454 | M23: =0.5*Inc_Stmt!F43+0.5*Inc_Stmt!G43 -> 725.19505 | N23: =I23/J23 -> 6.3235533 | O23: =I23/L23 -> 26.677741 | P23: =I23/M23 -> 17.096552 | Q23: =K23/J23-1 -> 0.47098935 | R23: =L23/J23 -> 0.23703481
B26: ="Implied valuation of "&Name -> Implied valuation of Forgent Power Solutions, Inc.
B27: Multiple | D27: FPS metric | E27: 25th pct | F27: Median | G27: 75th pct | H27: Price @ 25th | I27: Price @ median | J27: Price @ 75th
B28: EV / CY26E EBITDA | D28: =L23 -> 464.74454 | E28: =O20 -> 17.664002 | F28: =O18 -> 22.995401 | G28: =O17 -> 25.700442 | H28: =(E28*$D28-NetClaims)/DilutedShares -> 25.152103 | I28: =(F28*$D28-NetClaims)/DilutedShares -> 33.272538 | J28: =(G28*$D28-NetClaims)/DilutedShares -> 37.392679
B29: EV / CY27E EBITDA | D29: =M23 -> 725.19505 | E29: =P20 -> 15.505374 | F29: =P18 -> 19.393903 | G29: =P17 -> 20.290693 | H29: =(E29*$D29-NetClaims)/DilutedShares -> 35.099448 | I29: =(F29*$D29-NetClaims)/DilutedShares -> 44.341406 | J29: =(G29*$D29-NetClaims)/DilutedShares -> 46.472826
B30: EV / CY26E revenue | D30: =J23 -> 1960.6595 | E30: =N20 -> 4.0056999 | F30: =N18 -> 5.1255316 | G30: =N17 -> 5.3162266 | H30: =(E30*$D30-NetClaims)/DilutedShares -> 23.987217 | I30: =(F30*$D30-NetClaims)/DilutedShares -> 31.183011 | J30: =(G30*$D30-NetClaims)/DilutedShares -> 32.408375
B32: EV-based prices subtract NetClaims (debt - cash + TRA - DTA - restricted cash), the same bridge as 'Comps Analysis'.
B33: CY27E is the more relevant anchor: FPS guides +76% FY27 revenue growth vs. ~10-30% for peers, so CY26E multiples understate a growth-adjusted value.
B34: LTM/consensus caveats: GE Vernova EBITDA depressed by Wind; Hammond is pro forma for AEG (closed 6/29/2026, ~C$410m acquisition debt added); Powell FY ends Sep (not calendarized). MarketScreener consensus date could not be confirmed; CY26 revenue matched StockAnalysis at 9/25/2026.

Sheet Precedents
A1: ="Precedent Transactions for "&Name -> Precedent Transactions for Forgent Power Solutions, Inc.
A2: (Dollars in Millions; multiples on the basis each acquirer disclosed - see Basis column)
B3: Includes a control premium, so values are not directly comparable to a minority trading price. 'In stats' = 1 for electrical distribution / modular power / grid equipment; adjacent deals shown for context only.
B5: Announced | C5: Acquirer | D5: Target | E5: Description | F5: Enterprise value | G5: Target revenue | H5: Target EBITDA | I5: EV / revenue | J5: EV / EBITDA | K5: Basis | L5: In stats | M5: EV/rev (stats) | N5: EV/EBITDA (stats) | O5: Source
B6: Sep-2026 | C6: Flex | D6: EPC Power | E6: Power conversion (rectifiers, DC-DC, SSTs) for data centers and grid | F6: 4400 | G6: 800 | H6: 336 | I6: =IF(ISNUMBER(G6),F6/G6,"N/A") -> 5.5 | J6: =IF(ISNUMBER(H6),F6/H6,"N/A") -> 13.095238 | K6: Rev 2026E; EBITDA 2027E derived (~40% growth, ~30% margin) | L6: 1 | M6: =IF(AND(L6=1,ISNUMBER(I6)),I6,"") -> 5.5 | N6: =IF(AND(L6=1,ISNUMBER(J6)),J6,"") -> 13.095238 | O6: investors.flex.com release 3-Sep-2026; mgrid.org 3-Sep-2026
B7: Sep-2026 | C7: Vertiv | D7: UtilityInnovation Group | E7: Microgrid switchgear and power controls for data centers | F7: 1450 | G7: N/A | H7: 112 | I7: =IF(ISNUMBER(G7),F7/G7,"N/A") -> N/A | J7: =IF(ISNUMBER(H7),F7/H7,"N/A") -> 12.946429 | K7: 2027E EBITDA; ~13x stated; excludes up to $1.15bn earnout | L7: 1 | M7: =IF(AND(L7=1,ISNUMBER(I7)),I7,"") | N7: =IF(AND(L7=1,ISNUMBER(J7)),J7,"") -> 12.946429 | O7: Vertiv 8-K ex-99.1, SEC 0001193125-26-379306
B8: Mar-2026 | C8: Flex | D8: Electrical Power Products (EP2) | E8: Engineered control/relay panels, modular control buildings | F8: 1100 | G8: 323 | H8: N/A | I8: =IF(ISNUMBER(G8),F8/G8,"N/A") -> 3.4055728 | J8: =IF(ISNUMBER(H8),F8/H8,"N/A") -> N/A | K8: Rev FY Mar-26; EBITDA not disclosed; ~$100mm tax benefit | L8: 1 | M8: =IF(AND(L8=1,ISNUMBER(I8)),I8,"") -> 3.4055728 | N8: =IF(AND(L8=1,ISNUMBER(J8)),J8,"") | O8: prnewswire, Flex to acquire EP2, 30-Mar-2026
B9: Oct-2025 | C9: GE Vernova | D9: Prolec GE (remaining 50%) | E9: Power, distribution and specialty transformers (North America) | F9: 10550 | G9: 3000 | H9: 750 | I9: =IF(ISNUMBER(G9),F9/G9,"N/A") -> 3.5166667 | J9: =IF(ISNUMBER(H9),F9/H9,"N/A") -> 14.066667 | K9: 2025E; 50% stake price ($5.275bn) scaled to 100%; EBITDA derived at ~25% margin | L9: 1 | M9: =IF(AND(L9=1,ISNUMBER(I9)),I9,"") -> 3.5166667 | N9: =IF(AND(L9=1,ISNUMBER(J9)),J9,"") -> 14.066667 | O9: gevernova.com press release 21-Oct-2025
B10: Aug-2025 | C10: Hubbell | D10: DMC Power | E10: Substation and transmission connector systems | F10: 825 | G10: 130 | H10: 60 | I10: =IF(ISNUMBER(G10),F10/G10,"N/A") -> 6.3461538 | J10: =IF(ISNUMBER(H10),F10/H10,"N/A") -> 13.75 | K10: 2026E | L10: 1 | M10: =IF(AND(L10=1,ISNUMBER(I10)),I10,"") -> 6.3461538 | N10: =IF(AND(L10=1,ISNUMBER(J10)),J10,"") -> 13.75 | O10: Hubbell 8-K ex-99.1, SEC 0001193125-25-180835
B11: Mar-2025 | C11: Eaton | D11: Fibrebond | E11: Pre-integrated modular power enclosures / skids (data centers, utilities) | F11: 1400 | G11: 378 | H11: 110 | I11: =IF(ISNUMBER(G11),F11/G11,"N/A") -> 3.7037037 | J11: =IF(ISNUMBER(H11),F11/H11,"N/A") -> 12.727273 | K11: Rev TTM Feb-25; EBITDA 2025E; excl. $240mm assumed retention awards | L11: 1 | M11: =IF(AND(L11=1,ISNUMBER(I11)),I11,"") -> 3.7037037 | N11: =IF(AND(L11=1,ISNUMBER(J11)),J11,"") -> 12.727273 | O11: Eaton release; Eaton 10-Q Q2-2025
B12: Mar-2025 | C12: nVent | D12: Avail Electrical Products Group | E12: Enclosures, switchgear and bus systems for utilities and data centers | F12: 975 | G12: 375 | H12: 78 | I12: =IF(ISNUMBER(G12),F12/G12,"N/A") -> 2.6 | J12: 12.5 | K12: TTM; 12.5x stated | L12: 1 | M12: =IF(AND(L12=1,ISNUMBER(I12)),I12,"") -> 2.6 | N12: =IF(AND(L12=1,ISNUMBER(J12)),J12,"") -> 12.5 | O12: nVent release 10-Mar-2025; switchgear-magazine.com
B13: Jun-2024 | C13: nVent | D13: Trachte | E13: Custom-engineered control buildings (utility, data center) | F13: 695 | G13: 250 | H13: 58 | I13: =IF(ISNUMBER(G13),F13/G13,"N/A") -> 2.78 | J13: 12 | K13: 2024E; ~12x 'effective' stated | L13: 1 | M13: =IF(AND(L13=1,ISNUMBER(I13)),I13,"") -> 2.78 | N13: =IF(AND(L13=1,ISNUMBER(J13)),J13,"") -> 12 | O13: nVent release 6-Jun-2024
B14: Oct-2023 | C14: Hubbell | D14: Systems Control | E14: Substation control and relay panels, control buildings | F14: 1100 | G14: 400 | H14: 91.6 | I14: =IF(ISNUMBER(G14),F14/G14,"N/A") -> 2.75 | J14: =IF(ISNUMBER(H14),F14/H14,"N/A") -> 12.008734 | K14: 2024E; ~12x stated | L14: 1 | M14: =IF(AND(L14=1,ISNUMBER(I14)),I14,"") -> 2.75 | N14: =IF(AND(L14=1,ISNUMBER(J14)),J14,"") -> 12.008734 | O14: Hubbell 8-K ex-99.1, SEC 0001193125-23-266285
B15: Apr-2023 | C15: nVent | D15: ECM Industries | E15: Electrical connectors, tools and consumables | F15: 1100 | G15: 415 | H15: 104 | I15: =IF(ISNUMBER(G15),F15/G15,"N/A") -> 2.6506024 | J15: 10.6 | K15: TTM adj.; ~10.6x 'effective' stated | L15: 1 | M15: =IF(AND(L15=1,ISNUMBER(I15)),I15,"") -> 2.6506024 | N15: =IF(AND(L15=1,ISNUMBER(J15)),J15,"") -> 10.6 | O15: nVent release 3-Apr-2023
B16: Sep-2021 | C16: Vertiv | D16: E&I Engineering / Powerbar Gulf | E16: Switchgear, busway, integrated modular power for data centers | F16: 1800 | G16: 460 | H16: 150 | I16: =IF(ISNUMBER(G16),F16/G16,"N/A") -> 3.9130435 | J16: =IF(ISNUMBER(H16),F16/H16,"N/A") -> 12 | K16: Rev 2021E; EBITDA 2022E pre-synergy; excl. up to $200mm earnout | L16: 1 | M16: =IF(AND(L16=1,ISNUMBER(I16)),I16,"") -> 3.9130435 | N16: =IF(AND(L16=1,ISNUMBER(J16)),J16,"") -> 12 | O16: Vertiv 8-K ex-99.1, SEC 0001193125-21-267213
B17: Nov-2025 | C17: Eaton | D17: Boyd Thermal | E17: Liquid cooling for AI data centers (thermal, not power) | F17: 9500 | G17: 1700 | H17: 422 | I17: =IF(ISNUMBER(G17),F17/G17,"N/A") -> 5.5882353 | J17: 22.5 | K17: 2026E adj.; 22.5x stated. Excluded: thermal | L17: 0 | M17: =IF(AND(L17=1,ISNUMBER(I17)),I17,"") | N17: =IF(AND(L17=1,ISNUMBER(J17)),J17,"") | O17: Eaton release 3-Nov-2025
B18: Nov-2025 | C18: Vertiv | D18: PurgeRite | E18: Fluid-management services for liquid cooling | F18: 1000 | G18: N/A | H18: N/A | I18: =IF(ISNUMBER(G18),F18/G18,"N/A") -> N/A | J18: 10 | K18: 2026E post-synergy, stated. Excluded: services/thermal | L18: 0 | M18: =IF(AND(L18=1,ISNUMBER(I18)),I18,"") | N18: =IF(AND(L18=1,ISNUMBER(J18)),J18,"") | O18: Vertiv 8-K ex-99.1, SEC 0001193125-25-261623
B19: Jul-2024 | C19: Quanta Services | D19: Cupertino Electric | E19: Electrical contractor for data centers (not a manufacturer) | F19: 1540 | G19: 2150 | H19: 165 | I19: =IF(ISNUMBER(G19),F19/G19,"N/A") -> 0.71627907 | J19: =IF(ISNUMBER(H19),F19/H19,"N/A") -> 9.3333333 | K19: 2024E adj. midpoints. Excluded: contractor | L19: 0 | M19: =IF(AND(L19=1,ISNUMBER(I19)),I19,"") | N19: =IF(AND(L19=1,ISNUMBER(J19)),J19,"") | O19: Quanta release 18-Jul-2024
B20: Apr-2024 | C20: Prysmian | D20: Encore Wire | E20: US building wire and cable | F20: 4160 | G20: N/A | H20: N/A | I20: =IF(ISNUMBER(G20),F20/G20,"N/A") -> N/A | J20: 8.2 | K20: 2023A, 8.2x stated (6.3x post-synergy). Excluded: commodity cable | L20: 0 | M20: =IF(AND(L20=1,ISNUMBER(I20)),I20,"") | N20: =IF(AND(L20=1,ISNUMBER(J20)),J20,"") | O20: prysmian.com release 15-Apr-2024
D22: Max | I22: =MAX(M6:M20) -> 6.3461538 | J22: =MAX(N6:N20) -> 14.066667
D23: 75th percentile | I23: =QUARTILE(M6:M20,3) -> 3.8607085 | J23: =QUARTILE(N6:N20,3) -> 13.058036
D24: Median | I24: =MEDIAN(M6:M20) -> 3.4611197 | J24: =MEDIAN(N6:N20) -> 12.613636
D25: Mean | I25: =AVERAGE(M6:M20) -> 3.7165743 | J25: =AVERAGE(N6:N20) -> 12.569434
D26: 25th percentile | I26: =QUARTILE(M6:M20,1) -> 2.7575 | J26: =QUARTILE(N6:N20,1) -> 12.002183
D27: Min | I27: =MIN(M6:M20) -> 2.6 | J27: =MIN(N6:N20) -> 10.6
B29: ="Implied valuation of "&Name&" (core deals)" -> Implied valuation of Forgent Power Solutions, Inc. (core deals)
B30: Multiple | D30: FPS CY26E metric | E30: 25th pct | F30: Median | G30: 75th pct | H30: Price @ 25th | I30: Price @ median | J30: Price @ 75th
B31: EV / EBITDA | D31: ='Fwd Comps'!L23 -> 464.74454 | E31: =J26 -> 12.002183 | F31: =J24 -> 12.613636 | G31: =J23 -> 13.058036 | H31: =(E31*$D31-NetClaims)/DilutedShares -> 16.528396 | I31: =(F31*$D31-NetClaims)/DilutedShares -> 17.459721 | J31: =(G31*$D31-NetClaims)/DilutedShares -> 18.1366
B32: EV / revenue | D32: ='Fwd Comps'!J23 -> 1960.6595 | E32: =I26 -> 2.7575 | F32: =I24 -> 3.4611197 | G32: =I23 -> 3.8607085 | H32: =(E32*$D32-NetClaims)/DilutedShares -> 15.966556 | I32: =(F32*$D32-NetClaims)/DilutedShares -> 20.487863 | J32: =(G32*$D32-NetClaims)/DilutedShares -> 23.055534
B34: Forgent's own roll-up deals under Neos (MGM Transformer $424.7m, VanTran $432.7m, PwrQ $103.0m, States Manufacturing $68.5m; 2023-24) disclose price only, so no multiples (424B4).
B35: Revenue multiples mix LTM and forward bases and span 2.6-6.3x; treat the EV/revenue row as a cross-check only.

Sheet Football Field
A1: ="Valuation Summary for "&Name -> Valuation Summary for Forgent Power Solutions, Inc.
A2: ="Value per share; current price $"&TEXT(shareprice,"0.00")&"; live DCF scenario: "&Assumptions!D45 -> Value per share; current price $38.97; live DCF scenario: Base
B4: Methodology | C4: Low | D4: High | E4: Spread | F4: Midpoint | G4: Midpoint vs. current
B5: DCF - Gordon growth only (WACC +/-0.5%, g 2.5-3.5%) | C5: =MIN(DCF!G56:I58) -> 29.203717 | D5: =MAX(DCF!G56:I58) -> 37.76174 | E5: =D5-C5 -> 8.5580227 | F5: =AVERAGE(C5,D5) -> 33.482728 | G5: =F5/shareprice-1 -> -0.14080758
B6: DCF - exit multiple only (WACC +/-0.5%, exit +/-3x) | C6: =MIN(DCF!G65:I67) -> 32.912909 | D6: =MAX(DCF!G65:I67) -> 47.291141 | E6: =D6-C6 -> 14.378232 | F6: =AVERAGE(C6,D6) -> 40.102025 | G6: =F6/shareprice-1 -> 0.029048622
B7: DCF - blended TV, Bear to Bull scenario | C7: =MIN(Assumptions!L9:L11) -> 22.8707 | D7: =MAX(Assumptions!L9:L11) -> 47.7447 | E7: =D7-C7 -> 24.874 | F7: =AVERAGE(C7,D7) -> 35.3077 | G7: =F7/shareprice-1 -> -0.093977419
B8: Trading comps - NTM P/E (25th-75th) | C8: ='Comps Analysis'!G44 -> 35.776725 | D8: ='Comps Analysis'!G42 -> 39.206242 | E8: =D8-C8 -> 3.4295174 | F8: =AVERAGE(C8,D8) -> 37.491484 | G8: =F8/shareprice-1 -> -0.037939859
B9: Forward comps - EV / CY27E EBITDA (25th-75th) | C9: ='Fwd Comps'!H29 -> 35.099448 | D9: ='Fwd Comps'!J29 -> 46.472826 | E9: =D9-C9 -> 11.373378 | F9: =AVERAGE(C9,D9) -> 40.786137 | G9: =F9/shareprice-1 -> 0.046603457
B10: Forward comps - EV / CY26E EBITDA (25th-75th) | C10: ='Fwd Comps'!H28 -> 25.152103 | D10: ='Fwd Comps'!J28 -> 37.392679 | E10: =D10-C10 -> 12.240575 | F10: =AVERAGE(C10,D10) -> 31.272391 | G10: =F10/shareprice-1 -> -0.19752653
B11: Precedent transactions - EV / CY26E EBITDA (25th-75th) | C11: =Precedents!H31 -> 16.528396 | D11: =Precedents!J31 -> 18.1366 | E11: =D11-C11 -> 1.6082045 | F11: =AVERAGE(C11,D11) -> 17.332498 | G11: =F11/shareprice-1 -> -0.55523485
B12: Since-IPO trading range | C12: =low -> 25.95 | D12: =high -> 66 | E12: =D12-C12 -> 40.05 | F12: =AVERAGE(C12,D12) -> 45.975 | G12: =F12/shareprice-1 -> 0.17975366
B13: Analyst consensus price target (reference) | C13: 57.9 | D13: 57.9 | E13: =D13-C13 -> 0 | F13: =AVERAGE(C13,D13) -> 57.9 | G13: =F13/shareprice-1 -> 0.48575828
B15: Current share price | C15: =shareprice -> 38.97
B16: Target price (base DCF, blended TV) | C16: =TargetPrice -> 36.341509
B17: Market-implied EV / FY27E adj. EBITDA | C17: =Enterprise/Inc_Stmt!F43 -> 20.439429
B18: DCF rows follow the live scenario except the Bear-Bull row, which uses the pasted values in Assumptions!L9:L11.

Sheet Notes
B1: Model notes, conventions & sources
B3: Conventions
B4: Blue font = hardcoded input (sourced in the grey note column); black = formula. Yellow fill = key selector / analyst cells (Scenario, Recommendation, exit-multiple override, DCF price).
B5: Scenario switch: Assumptions!C45 (1 Base / 2 Bull / 3 Bear). Every projected driver = OFFSET(live row, Scenario).
B6: Structural decisions (differ from the Oracle template)
B7: 1. 10-year projection (FY27–FY36): FPS is still growing ~10% in year 5, so a 5-year model would back-load EV into the terminal value.
B8: 2. Up-C: value is divided by fully-exchanged shares (Class A + Class B + RSUs = 305.1m); book NCI is therefore NOT subtracted. Tax is normalized at 25% because the reported 16.8% ETR excludes the untaxed NCI share.
B9: 3. TRA: bridge subtracts the $338.9m liability and adds back the $281.0m DTA and $24.2m TRA-restricted cash that fund it (net claim ≈ $33.7m). Subtracting the liability alone would understate value by ~$0.92/share.
B10: 4. SBC is expensed (GAAP EBITDA), not added back. IPO one-offs ($64.2m in FY26) are zero in projections.
B11: 5. Capacity: revenue beyond Capacity × Util triggers growth capex at $35m per $800m of capacity (mgmt's PTS expansion economics).
B12: 6. Operating leases are not debt (US GAAP lease cost is already inside EBITDA).
B13: Fixes vs. the Oracle template
... B28: Assumptions!L9:L11 re-pasted after the exit-multiple change (Base / Bull / Bear).
